Workbook

Sheet 09_Dashboard
A1: upGrad School of Technology | I1: Admission Cycle | K1: As of | M1: Auto-updating
A2: LOAN OPERATIONS MANAGEMENT SYSTEM | I2: ='02_Configuration'!B83 | K2: ='02_Configuration'!B82 | M2: Formula-driven
A4: FILTERS | B4: Campus | C4: ='08_Dashboard_Tables'!B4 | D4: Critical | E4: ='08_Dashboard_Tables'!B7 | F4: Loan Required | G4: ='08_Dashboard_Tables'!B8 | H4: Dup Vendor | I4: ='08_Dashboard_Tables'!B9 | K4: Edit filters on 08_Dashboard_Tables!B4:B9 → Ops lists honor them in v2. KPI strip = global truth.
A6: EXECUTIVE SNAPSHOT
A7: Total Students | B7: Need Loan | C7: Processing | D7: Docs Pending | E7: Sanctioned | F7: Disbursed | G7: Rejected
A8: ='08_Dashboard_Tables'!B13 | B8: ='08_Dashboard_Tables'!B14 | C8: ='08_Dashboard_Tables'!B16 | D8: ='08_Dashboard_Tables'!B17 | E8: ='08_Dashboard_Tables'!B18 | F8: ='08_Dashboard_Tables'!B19 | G8: ='08_Dashboard_Tables'!B20
A10: Need FLDG | B10: Need Vidyalakshmi | C10: Critical Cases | D10: Dup Vendors | E10: Avg Vendors | F10: With Vendor | G10: Not Started
A11: ='08_Dashboard_Tables'!B21 | B11: ='08_Dashboard_Tables'!B22 | C11: ='08_Dashboard_Tables'!B23 | D11: ='08_Dashboard_Tables'!B24 | E11: ='08_Dashboard_Tables'!B25 | F11: ='08_Dashboard_Tables'!B26 | G11: ='08_Dashboard_Tables'!B27
A13: LOAN FUNNEL | F13: VENDOR PERFORMANCE
A14: Stage | B14: Students | C14: vs Need Loan | D14: Bar | F14: Vendor | G14: Unique | H14: Apps | I14: In Status | J14: Sanctioned | K14: Critical | L14: Appr%
A15: ='08_Dashboard_Tables'!D13 | B15: ='08_Dashboard_Tables'!E13 | C15: ='08_Dashboard_Tables'!F13 | D15: =IF($B$15=0,"",REPT("█",ROUND(B15/$B$15*20,0))) | F15: ='08_Dashboard_Tables'!A38 | G15: ='08_Dashboard_Tables'!B38 | H15: ='08_Dashboard_Tables'!C38 | I15: ='08_Dashboard_Tables'!D38 | J15: ='08_Dashboard_Tables'!E38 | K15: ='08_Dashboard_Tables'!F38 | L15: ='08_Dashboard_Tables'!G38
A16: ='08_Dashboard_Tables'!D14 | B16: ='08_Dashboard_Tables'!E14 | C16: ='08_Dashboard_Tables'!F14 | D16: =IF($B$15=0,"",REPT("█",ROUND(B16/$B$15*20,0))) | F16: ='08_Dashboard_Tables'!A39 | G16: ='08_Dashboard_Tables'!B39 | H16: ='08_Dashboard_Tables'!C39 | I16: ='08_Dashboard_Tables'!D39 | J16: ='08_Dashboard_Tables'!E39 | K16: ='08_Dashboard_Tables'!F39 | L16: ='08_Dashboard_Tables'!G39
A17: ='08_Dashboard_Tables'!D15 | B17: ='08_Dashboard_Tables'!E15 | C17: ='08_Dashboard_Tables'!F15 | D17: =IF($B$15=0,"",REPT("█",ROUND(B17/$B$15*20,0))) | F17: ='08_Dashboard_Tables'!A40 | G17: ='08_Dashboard_Tables'!B40 | H17: ='08_Dashboard_Tables'!C40 | I17: ='08_Dashboard_Tables'!D40 | J17: ='08_Dashboard_Tables'!E40 | K17: ='08_Dashboard_Tables'!F40 | L17: ='08_Dashboard_Tables'!G40
A18: ='08_Dashboard_Tables'!D16 | B18: ='08_Dashboard_Tables'!E16 | C18: ='08_Dashboard_Tables'!F16 | D18: =IF($B$15=0,"",REPT("█",ROUND(B18/$B$15*20,0))) | F18: ='08_Dashboard_Tables'!A41 | G18: ='08_Dashboard_Tables'!B41 | H18: ='08_Dashboard_Tables'!C41 | I18: ='08_Dashboard_Tables'!D41 | J18: ='08_Dashboard_Tables'!E41 | K18: ='08_Dashboard_Tables'!F41 | L18: ='08_Dashboard_Tables'!G41
A19: ='08_Dashboard_Tables'!D17 | B19: ='08_Dashboard_Tables'!E17 | C19: ='08_Dashboard_Tables'!F17 | D19: =IF($B$15=0,"",REPT("█",ROUND(B19/$B$15*20,0))) | F19: ='08_Dashboard_Tables'!A42 | G19: ='08_Dashboard_Tables'!B42 | H19: ='08_Dashboard_Tables'!C42 | I19: ='08_Dashboard_Tables'!D42 | J19: ='08_Dashboard_Tables'!E42 | K19: ='08_Dashboard_Tables'!F42 | L19: ='08_Dashboard_Tables'!G42
A20: ='08_Dashboard_Tables'!D18 | B20: ='08_Dashboard_Tables'!E18 | C20: ='08_Dashboard_Tables'!F18 | D20: =IF($B$15=0,"",REPT("█",ROUND(B20/$B$15*20,0)))
F21: Overlap matrix → see 05_Vendor_Analytics (heatmap)
A22: CAMPUS PERFORMANCE
A23: Campus | B23: Total | C23: Need Loan | D23: Processing | E23: Sanctioned | F23: Disbursed | G23: Rejected | H23: Critical
A24: ='08_Dashboard_Tables'!H13 | B24: ='08_Dashboard_Tables'!I13 | C24: ='08_Dashboard_Tables'!J13 | D24: ='08_Dashboard_Tables'!K13 | E24: ='08_Dashboard_Tables'!L13 | F24: ='08_Dashboard_Tables'!M13 | G24: ='08_Dashboard_Tables'!N13 | H24: ='08_Dashboard_Tables'!O13
A25: ='08_Dashboard_Tables'!H14 | B25: ='08_Dashboard_Tables'!I14 | C25: ='08_Dashboard_Tables'!J14 | D25: ='08_Dashboard_Tables'!K14 | E25: ='08_Dashboard_Tables'!L14 | F25: ='08_Dashboard_Tables'!M14 | G25: ='08_Dashboard_Tables'!N14 | H25: ='08_Dashboard_Tables'!O14
A27: RISK DASHBOARD | D27: STUDENT AGEING | H27: DROP-OFF REASONS
A28: Flag | B28: Count | D28: Bucket | E28: Count | H28: Reason | I28: Count
A29: ='08_Dashboard_Tables'!A48 | B29: ='08_Dashboard_Tables'!B48 | D29: ='08_Dashboard_Tables'!D48 | E29: ='08_Dashboard_Tables'!E48 | F29: =IF(SUM($E$29:$E$34)=0,"",REPT("█",ROUND(E29/MAX($E$29:$E$34)*15,0))) | H29: ='08_Dashboard_Tables'!G48 | I29: ='08_Dashboard_Tables'!H48
A30: ='08_Dashboard_Tables'!A49 | B30: ='08_Dashboard_Tables'!B49 | D30: ='08_Dashboard_Tables'!D49 | E30: ='08_Dashboard_Tables'!E49 | F30: =IF(SUM($E$29:$E$34)=0,"",REPT("█",ROUND(E30/MAX($E$29:$E$34)*15,0))) | H30: ='08_Dashboard_Tables'!G49 | I30: ='08_Dashboard_Tables'!H49
A31: ='08_Dashboard_Tables'!A50 | B31: ='08_Dashboard_Tables'!B50 | D31: ='08_Dashboard_Tables'!D50 | E31: ='08_Dashboard_Tables'!E50 | F31: =IF(SUM($E$29:$E$34)=0,"",REPT("█",ROUND(E31/MAX($E$29:$E$34)*15,0))) | H31: ='08_Dashboard_Tables'!G50 | I31: ='08_Dashboard_Tables'!H50
A32: ='08_Dashboard_Tables'!A51 | B32: ='08_Dashboard_Tables'!B51 | D32: ='08_Dashboard_Tables'!D51 | E32: ='08_Dashboard_Tables'!E51 | F32: =IF(SUM($E$29:$E$34)=0,"",REPT("█",ROUND(E32/MAX($E$29:$E$34)*15,0))) | H32: ='08_Dashboard_Tables'!G51 | I32: ='08_Dashboard_Tables'!H51
A33: ='08_Dashboard_Tables'!A52 | B33: ='08_Dashboard_Tables'!B52 | D33: ='08_Dashboard_Tables'!D52 | E33: ='08_Dashboard_Tables'!E52 | F33: =IF(SUM($E$29:$E$34)=0,"",REPT("█",ROUND(E33/MAX($E$29:$E$34)*15,0))) | H33: ='08_Dashboard_Tables'!G52 | I33: ='08_Dashboard_Tables'!H52
A34: ='08_Dashboard_Tables'!A53 | B34: ='08_Dashboard_Tables'!B53 | D34: ='08_Dashboard_Tables'!D53 | E34: ='08_Dashboard_Tables'!E53 | F34: =IF(SUM($E$29:$E$34)=0,"",REPT("█",ROUND(E34/MAX($E$29:$E$34)*15,0))) | H34: ='08_Dashboard_Tables'!G53 | I34: ='08_Dashboard_Tables'!H53
A35: ='08_Dashboard_Tables'!A54 | B35: ='08_Dashboard_Tables'!B54 | H35: ='08_Dashboard_Tables'!G54 | I35: ='08_Dashboard_Tables'!H54
A36: ='08_Dashboard_Tables'!A55 | B36: ='08_Dashboard_Tables'!B55 | H36: ='08_Dashboard_Tables'!G55 | I36: ='08_Dashboard_Tables'!H55
A37: ='08_Dashboard_Tables'!A56 | B37: ='08_Dashboard_Tables'!B56 | H37: ='08_Dashboard_Tables'!G56 | I37: ='08_Dashboard_Tables'!H56
A38: ='08_Dashboard_Tables'!A57 | B38: ='08_Dashboard_Tables'!B57
A41: LOAN STATUS DISTRIBUTION | F41: TOP PENDING STUDENTS
A42: Stage | B42: Count | C42: Share | F42: See sheet 10_Ops_Views for live Top Pending, FLDG list, Vidyalakshmi list, and student search.
A43: ='08_Dashboard_Tables'!A62 | B43: ='08_Dashboard_Tables'!B62 | C43: =IF(SUM($B$43:$B$54)=0,0,B43/SUM($B$43:$B$54)) | D43: =IF(SUM($B$43:$B$54)=0,"",REPT("█",ROUND(B43/MAX($B$43:$B$54)*18,0)))
A44: ='08_Dashboard_Tables'!A63 | B44: ='08_Dashboard_Tables'!B63 | C44: =IF(SUM($B$43:$B$54)=0,0,B44/SUM($B$43:$B$54)) | D44: =IF(SUM($B$43:$B$54)=0,"",REPT("█",ROUND(B44/MAX($B$43:$B$54)*18,0))) | F44: QUICK NAVIGATION
A45: ='08_Dashboard_Tables'!A64 | B45: ='08_Dashboard_Tables'!B64 | C45: =IF(SUM($B$43:$B$54)=0,0,B45/SUM($B$43:$B$54)) | D45: =IF(SUM($B$43:$B$54)=0,"",REPT("█",ROUND(B45/MAX($B$43:$B$54)*18,0))) | F45: → 04_Student_360 — One row per student
A46: ='08_Dashboard_Tables'!A65 | B46: ='08_Dashboard_Tables'!B65 | C46: =IF(SUM($B$43:$B$54)=0,0,B46/SUM($B$43:$B$54)) | D46: =IF(SUM($B$43:$B$54)=0,"",REPT("█",ROUND(B46/MAX($B$43:$B$54)*18,0))) | F46: → 05_Vendor_Analytics — Unique vs Apps + Overlap heatmap
A47: ='08_Dashboard_Tables'!A66 | B47: ='08_Dashboard_Tables'!B66 | C47: =IF(SUM($B$43:$B$54)=0,0,B47/SUM($B$43:$B$54)) | D47: =IF(SUM($B$43:$B$54)=0,"",REPT("█",ROUND(B47/MAX($B$43:$B$54)*18,0))) | F47: → 06_Stage_Analytics — Full funnel
A48: ='08_Dashboard_Tables'!A67 | B48: ='08_Dashboard_Tables'!B67 | C48: =IF(SUM($B$43:$B$54)=0,0,B48/SUM($B$43:$B$54)) | D48: =IF(SUM($B$43:$B$54)=0,"",REPT("█",ROUND(B48/MAX($B$43:$B$54)*18,0))) | F48: → 07_Risk_Analytics — Risk & reasons
A49: ='08_Dashboard_Tables'!A68 | B49: ='08_Dashboard_Tables'!B68 | C49: =IF(SUM($B$43:$B$54)=0,0,B49/SUM($B$43:$B$54)) | D49: =IF(SUM($B$43:$B$54)=0,"",REPT("█",ROUND(B49/MAX($B$43:$B$54)*18,0))) | F49: → 10_Ops_Views — Action lists
A50: ='08_Dashboard_Tables'!A69 | B50: ='08_Dashboard_Tables'!B69 | C50: =IF(SUM($B$43:$B$54)=0,0,B50/SUM($B$43:$B$54)) | D50: =IF(SUM($B$43:$B$54)=0,"",REPT("█",ROUND(B50/MAX($B$43:$B$54)*18,0))) | F50: → 01_Master_Data — Edit data here ONLY
A51: ='08_Dashboard_Tables'!A70 | B51: ='08_Dashboard_Tables'!B70 | C51: =IF(SUM($B$43:$B$54)=0,0,B51/SUM($B$43:$B$54)) | D51: =IF(SUM($B$43:$B$54)=0,"",REPT("█",ROUND(B51/MAX($B$43:$B$54)*18,0))) | F51: → 11_Documentation — Dictionary & rules
A52: ='08_Dashboard_Tables'!A71 | B52: ='08_Dashboard_Tables'!B71 | C52: =IF(SUM($B$43:$B$54)=0,0,B52/SUM($B$43:$B$54)) | D52: =IF(SUM($B$43:$B$54)=0,"",REPT("█",ROUND(B52/MAX($B$43:$B$54)*18,0)))
A53: ='08_Dashboard_Tables'!A72 | B53: ='08_Dashboard_Tables'!B72 | C53: =IF(SUM($B$43:$B$54)=0,0,B53/SUM($B$43:$B$54)) | D53: =IF(SUM($B$43:$B$54)=0,"",REPT("█",ROUND(B53/MAX($B$43:$B$54)*18,0)))
A54: ='08_Dashboard_Tables'!A73 | B54: ='08_Dashboard_Tables'!B73 | C54: =IF(SUM($B$43:$B$54)=0,0,B54/SUM($B$43:$B$54)) | D54: =IF(SUM($B$43:$B$54)=0,"",REPT("█",ROUND(B54/MAX($B$43:$B$54)*18,0)))
A56: Leadership should read this sheet in under 30 seconds. Operations should open 10_Ops_Views for drill-down.

Sheet 01_Master_Data
A1: S. No | B1: Name | C1: Mobile Number | D1: Provisional ID | E1: Campus | F1: Need Loan (SST input) | G1: Criticality (SST INput) | H1: Scholarship | I1: Loan Amt req | J1: 12th percentage | K1: Co-Applicant Relation | L1: Occupation | M1: Annual Income | N1: Income Proof | O1: Any other loan | P1: Co-applcant Cibil | Q1: Co-lateral | R1: Co-lateral details | S1: SST Remarks | T1: Pranjal Comments | U1: Loan required (Latest) | V1: Shared to ICICI | W1: Shared to Propelld | X1: Shared to Study4Buddy | Y1: Shared to Poonawala Fincorp | Z1: Shared to GyanDhan | AA1: Initial Case Status | AB1: CurrentCase Status (started on 31/7) | AC1: Tentative Loan Date | AD1: Intent to be Reverted to SST | AE1: Mentor Flag | AF1: SST Comments | AG1: Loan Stage | AH1: Loan Status | AI1: Need FLDG attention | AJ1: Needs Vishwa's attention | AK1: Special Vidyalaksmi attention | AL1: Reason if not started | AM1: Column 37 | AN1: Banker Status | AO1: Column 39 | AP1: Column 40 | AQ1: Column 41
A2: 1 | B2: Priyanshu Jena | C2: 7606059075 | D2: PROV260602396 | E2: SSAHE | F2: Yes | G2: Non Critical | H2: 0.05 | I2: 25 | J2: 66.5 | K2: Father | L2: Salaried | M2: 13 | N2: ITR | O2: No | P2: NA | Q2: No | R2: NA | S2: Waiting for the bank to reach them out Need assitance from us | T2: 9/7/26: Requires loan of 25Lakhs, good cibil score, good income, please reach out to this student , bank hasn't called back yet 18/7: Ongoing on with ICICI bank. 28/7 : Student suggest that process has been completed from icici but they haven't reverted anything about this one 30/7 : Student loan has been rejected by icici due to other bank , | U2: Yes | V2: Yes | W2: No | X2: No | Y2: No | Z2: Yes | AA2: Control | AB2: Control | AG2: Ongoing | AH2: Processing by Icici | AI2: No | AJ2: No | AK2: No
A3: 2 | B3: Arithra Kabiraj | C3: 7990739081 | D3: PROV260501340 | E3: SSAHE | F3: Yes | G3: Non Critical | H3: 0.05 | I3: 25 | J3: 81 | K3: Father | L3: Salaried | M3: 7.8 | N3: ITR | O3: Yes | P3: 720 | Q3: Yes | R3: Residential | S3: Waiting for the bank to reach them out Need assitance from us | T3: 9/7/26 : DNP *15/7/26: In talks with Propelled : Shared to ICICI : Also trying at their level 20/7: Ongoing in talks with SBI as well. 29/7: Propell offering at 15%, have also started with GyanDhan | U3: Yes | V3: Yes | W3: Yes | X3: No | Y3: No | Z3: Yes | AA3: Control | AB3: Control | AG3: Ongoing | AH3: Processing by Propelld, Loan sanctioned by gyan dhan | AI3: No | AJ3: No | AK3: No
A4: 3 | B4: Ayansh Maurya | C4: 6306995363 | D4: PROV260610670 | E4: SSAHE | F4: Yes | G4: Non Critical | H4: 0.125 | I4: 26 | J4: 72.8 | K4: Uncle | L4: Salaried | M4: 9 | N4: Salary Slip | O4: Yes | P4: 759 | Q4: No | R4: NA | S4: Waiting for the bank to reach them out Need assitance from us | T4: 9/7/26 : DNP 15/7/26 : 10th %age- 90.16 12th %age- 72.8 Loan Amount- 24 lakhs Co applicant- Gyan Prakash (uncle) Profession- Assistance professor Salary- 75k per month Cibil Score- 759 Existing emi- Rs14710 Contact number- 81150 37832 20/7: In talks with ICICI, have suggested to apply elsewhere as well. 28/7 : Case was rejected by icici and gyan dhan both . icici rejected his case due to FOIR. 29/7 : Mother called again , will try to processs it on mother, before it was processed on uncle's name. Gyan dhan came back telling this case is doable onn whatsapp. Moving it from control to risk 31/7 : Gyandhan is asking for relationship proof. have told gyandhan to connect with them. Mother called and is worried about the loan, has different offers as well. | U4: Yes | V4: Yes | W4: No | X4: No | Y4: No | Z4: Yes | AA4: Risk | AB4: Risk | AG4: Ongoing | AH4: Processing by Icici | AI4: No | AJ4: No | AK4: No
A5: 4 | B5: Harshit Singhi | C5: 9883379315 | D5: PROV260502866 | E5: SSAHE | F5: Yes | G5: Loan not required | H5: 0.05 | I5: 25 | J5: 70 | K5: Father | L5: Business | M5: 7 | N5: ITR | O5: No | P5: NA | Q5: No | R5: NA | S5: Waiting for the bank to reach them out Need assitance from us | T5: 9/7/26 : HAd in depth conversation, student already has 10L funds, and 10L he would require loan, which he would not avail in this year. Suggested him to pay the fees within this month. | U5: No | V5: No | W5: No | AA5: Not required | AB5: Not required | AG5: Not required | AK5: No
A6: 5 | B6: Prem Sandeep Dipke | C6: 8605831946 | D6: PROV260506859 | E6: ADYPU | F6: Yes | G6: Non Critical | H6: 0.125 | I6: 25 | J6: 58 | K6: Father | L6: Salaried | M6: 3 | N6: Income Certificate | O6: No | P6: NA | Q6: No | R6: NA | S6: Propelled -24Lakh , Rate of intrest :11-12%, Going with Propelled | T6: 9/7/26 : Loan process has begun through propelld , they have offer 10L at 13%, he has some expectation of 10%, have spoken to student , student will make me talk to the father tomorrow. Father's number : 9359685429 10/7/26 : Called father , DNP. Father called back : not at all happy with 13% ROI, he said it would be too much to pay. Father was outside, so he told he would call me by evening to discuss this . ICICI hasn't reached out to them 21/7 : Pranjal : Have to be processed by GyanDhan. Student hasn't talked to any banks. Yearly incomr : 5L, ITR filed : No, Profession : Travel agent , Rental income : 0, started with propelled but 14% interest is too much 30/7: Approved | U6: Yes | V6: No | W6: Yes | AA6: Control | AB6: Control | AG6: Ongoing | AH6: Loan sanctioned by gyan dhan | AI6: No | AJ6: No | AK6: No
A7: 6 | B7: Manthan upmanyu | C7: 9399297905 | D7: PROV260604114 | E7: SSAHE | F7: Yes | G7: Non Critical | H7: 0.175 | I7: 25 | J7: 85 | K7: Mother | L7: Bussiness | M7: 8 | N7: ITR | O7: No | P7: NA | Q7: No | R7: NA | S7: Waiting for the bank to reach them out Need assitance from us | T7: 9/7/26 : Student was communicated wrong in terms of hostel fees. Mother was furious listening to the hostel fees due to miscommunication. Have suggested the student to drop me as well as to admissions team an email regarding the same. Counselor also committed 20% scholarship against which the student has got 17.5% ( 10% merit based + 7.5% EWS ) 20/7 : Need intent check from SST team. 27/7 : DNP 29/7 : DNP || spoke to the student , the student would pay the fees tomorrow. has requested for a single room if possible. Doesn't need loan for this year. Moving from risk to control | U7: No | V7: No | W7: No | X7: No | Y7: No | Z7: No | AA7: Control | AB7: Control | AD7: Student had some issue regarding fees and scholarship, wanted to check if that is sorted before moving to the loan part. Souhardya Bose Multiple calls have gone to this student, Please speak to him and let me know if his issues are resolved and is he willing to go for loan. Souhardya Bose Had a conversation with student , doesn't need SSt intervention : 29/7/26 | AG7: Not required
A8: 7 | B8: Akchat Bharti | C8: 9031350334 | D8: PROV1000000431 | E8: SSAHE | F8: Yes | G8: Non Critical | H8: 0.05 | I8: 22 | J8: 81.12 | K8: Father | L8: Salaried | M8: 7 | N8: ITR | O8: No | P8: 728 | Q8: No | R8: NA | S8: Waiting for the bank to reach them out Need assitance from us | T8: 9/7/26 : He is from Jharkhand, he is taking loan from Jharkhand govt of 15L at 4%, the loan is in process , the rest of the amount he will be take from diffferent banks. 20/7: Jharkahdn SCC is in process, Rejected propelld due to high int rate, next ICICI and Gyan Dhan Update by Gyandhan Learner got loan from govt scheme (jharkhand), cannot process another loan on same profile 28/7 : Semester fees will be paid by next week | U8: Yes | V8: No | W8: No | X8: No | Y8: No | Z8: No | AA8: Control | AB8: Control | AG8: Ongoing | AH8: Processing by Icici, Processing by GyanDhan, State Scheme | AI8: No | AJ8: No
A9: 8 | B9: SamarthG | C9: 9242410155 | D9: PROV1000000341 | E9: ADYPU | F9: Yes | G9: Loan not required | H9: 0.15 | I9: 25 | J9: 89 | K9: Father | L9: Self-Employed | M9: 7 | N9: Income Certificate | O9: No | P9: NA | Q9: No | R9: NA | S9: Waiting for the bank to reach them out Need assitance from us | T9: 9/7/26 This student would visit on 25th of july to ADYPU and would pay the fees there only. Please be in touch with them, they dont require the loan. | U9: No | AA9: Not required | AB9: Not required | AG9: Not required
A10: 9 | B10: AAVANI JITH | C10: 8091531491 | D10: PROV1000000399 | E10: SSAHE | F10: Yes | G10: Non Critical | H10: 0.1 | I10: 23 | J10: NA | K10: Father | L10: Salaried | M10: 10.2 | N10: Income Certificate | O10: Yes | P10: 772 | Q10: No | R10: NA | S10: its a positive case , student is going frwd with icici bank just need documents | T10: 9/7/26 : ICICI has rejected the loan due to bounce issues , they are in touch with the propelld. Propelld is processing it , have sent them the message to check the status on the saMe. 13/7/26 : Father called to check the status on the application, have asked propelld for the status 21/7: Sanctioned UTR Number : AUBLN62026072146425058 | U10: Yes | V10: No | W10: Yes | AA10: Control | AB10: Control | AG10: Disbursed | AH10: Disbursed, Loan sanctioned by Propelld | AI10: No | AJ10: No
A11: 10 | B11: Gulshan Kumar | C11: 8877535347 | D11: PROV1000000313 | E11: SSAHE | F11: Yes | G11: Non Critical | H11: 0.25 | I11: 22.5 | J11: 76 | K11: Father | L11: Farmer | M11: 5 | N11: Income Certificate | O11: No | P11: 750 | Q11: No | R11: NA | S11: its positive from icici bank, they are taking loan, need documents | T11: 9/7/26 : Student has got the call from ICICI bank , 1 week back , the student has not submitted the documents yet as the bank didn't reach out to him for the document. 10/7/26 : ICICI has reached out to the student, have shared the document list , they are taking this ahead 17/7/26 : Checked with the student, have sent the document to icici , they haven't responded yet 23/7: All process left only sanction done. 29/7 : His loan is still under process but he has paid the sem fees and hostel fees from their side | U11: Yes | V11: Yes | W11: No | AA11: Control | AB11: Control | AG11: Ongoing | AH11: Processing by Icici | AI11: No | AJ11: No | AK11: No
A12: 11 | B12: Prashant Kumar Raj | C12: 9376384908 | D12: PROV1000000265 | E12: SSAHE | F12: Yes | G12: Non Critical | H12: 0.2 | I12: 15 | J12: 80.2 | K12: Uncle | L12: business | M12: 15 | N12: ITR | O12: Yes | P12: 782 | Q12: No | R12: NA | S12: Waiting for the bank to reach them out Need assitance from us | T12: 9/7/26 : Have shared the number to ICICI , is looking for loan 15/7/26 : Shared to propelld , propelld will call them, icici rejected the case, 699 cibil. Father's income : 30K/m, Mom's shop : 3.5L , ITR mom only. Uncle cibil 20/7: Ongoing in various banks (Axis, propell, gyandhan) 29/7 : Have applied through PM vidyalakshmi, currently in the bank to get the loan. SBI - 7.5L , student says he would get loan by 15th Aug, I have pushed him to get it by 10th. 3/8 : Student have applied through bank and is asking for extension | U12: Yes | V12: Yes | W12: Yes | X12: No | Y12: No | Z12: Yes | AA12: Control | AB12: Control | AG12: Ongoing | AH12: Processing by Icici, Processing by GyanDhan | AI12: No | AJ12: No | AK12: Yes
A13: 12 | B13: Ayushman Tiwari | C13: 9109536213 | D13: PROV1000000316 | E13: SSAHE | F13: Yes | G13: Loan not required | H13: NA | I13: 25 | J13: NA | K13: Father | L13: Salaried | M13: 22 | N13: ITR | O13: Yes | P13: 783 | Q13: No | R13: NA | S13: Waiting for the bank to reach them out Need assitance from us | T13: 9/7/26 : Student will pay the fees of first sem + hostel., he is asking how to pay, have shared the number to SST , have told them to call. have told him that sooner you pay the fees, sooner you’ll be able to book the hostel room | U13: No | V13: No | W13: No | AA13: Not required | AB13: Not required | AG13: Not required
A14: 13 | B14: Bhupendra Saini | C14: 7307944285 | D14: PROV260503144 | E14: SSAHE | F14: Yes | G14: Non Critical | H14: 0.15 | I14: 25 | J14: 68 | K14: Father | L14: Salaried | M14: 8 | N14: ITR | O14: Yes | P14: 746 | Q14: No | R14: NA | S14: Waiting for the bank to reach them out Need assitance from us | T14: 9/7/26 : Requires loan and have shared his details with ICICI and propeld both to speak. He is looking for the loan of 25L. Income is correct 18/7: No revert from ICICI, have shared to more partners 21/7 : ICICI told they'll update but they haven't got back. Annual income : 7L, Father : Teacher ( Government ) , Cibil : 750, ITR filed : Yes || Processing through gyan Dhan. Mother is a housewife, father pays 90% of the emi to the interest of his sister's education 31/7: Docs submitted to GD | U14: Yes | V14: Yes | W14: Yes | AA14: Control | AB14: Control | AG14: Ongoing | AH14: Processing by GyanDhan | AI14: No | AJ14: No | AK14: No
A15: 14 | B15: Ankit Tiwari | C15: 9785596407 | D15: PROV260502511 | E15: SSAHE | F15: Yes | G15: Loan not required | H15: 0.2 | I15: 12 | J15: 82 | K15: Father | L15: Salaried | M15: 4 | N15: Income Certificate | O15: No | P15: 750 | Q15: No | R15: NA | S15: Waiting for the bank to reach them out Need assitance from us | T15: 9/7/26 : 1st year he doesnt require the loan , from the second year he requires loan. | U15: No | V15: No | W15: No | AA15: Not required | AB15: Not required | AG15: Not required
A16: 15 | B16: Harsh Kumar Hooda | C16: 7073472525 | D16: PROV1000000339 | E16: SSAHE | F16: Yes | G16: Loan not required | H16: 0.15 | I16: 20 | J16: 80.8 | K16: Father | L16: Salaried | M16: 8 | N16: Income Certificate | O16: No | P16: 750 | Q16: No | R16: NA | S16: Waiting for the bank to reach them out Need assitance from us | T16: 9/7/26 : HAd a word with student's father, student's father doesn't want to take loan , father would pay once he sees the campus through video call. Have provided the number to SST to arrange it. 10/7/26 : Student wants defence scholarship to be added || Shilpa has shown the campus today. | U16: No | V16: No | W16: No | AA16: Not required | AB16: Not required | AG16: Not required
A17: 16 | B17: Piyush Chetani | C17: 9358622412 | D17: PROV260503758 | E17: SSAHE | F17: Yes | G17: Non Critical | H17: 0.1 | I17: 24 | J17: 55 | K17: Father | L17: Self-Employed | M17: 6.5 | N17: ITR | O17: Yes | P17: 715 | Q17: No | R17: NA | S17: Waiting for the bank to reach them out Need assitance from us | T17: 10/7 : HAs got the call from Study4buddy, student has filled the icici form, 6.5 Lacs is the father income, ITR filed , Father's profession : Shop ( Self employed ). Student is worried that he is not getting +ve response from HDFC , hasn't got the call from ICICI. Student has no collateral 12/7 : Student called back, icici hasn;t called back. Student is worried about the loan. as study4buddy told he wont get the loan with this coaplicant. Shared to propelld again. 14/7 : Piyush's case has been rejected by all lenders due to low income and poor academics. Also, the father already has an existing personal loan EMI, so the income eligibility criteria are not being met. He needs to provide a strong additional co-applicant to relook the case. 21/7: Processing by propelld 31/7: Logged in with ES, GD also approved moving from risk to control | U17: Yes | V17: No | W17: Yes | AA17: Risk | AB17: Control | AG17: Ongoing | AH17: Loan sanctioned by gyan dhan | AI17: No | AJ17: No | AK17: No
A18: 17 | B18: Gautam Kumar | C18: 7033285170 | D18: PROV1000003995 | E18: SSAHE | F18: Yes | G18: Loan not required | H18: 0.2 | I18: 7 | J18: 63 | K18: Father | L18: Salaried | M18: 5.5 | N18: ITR | O18: No | P18: 750+ | Q18: No | R18: NA | S18: Waiting for the bank to reach them out Need assitance from us | T18: 10/7/26 :Called student , had a word with him, he'll pay the fees for first sem by himself and then take the loan. Parent is visiting tomorrow to the campus | U18: No | V18: No | W18: No | AA18: Not required | AB18: Not required | AG18: Not required
A19: 18 | B19: Mohammad Faizan | C19: 7541858761 | D19: PROV260500401 | E19: SSAHE | F19: Yes | G19: Non Critical | H19: 0.25 | I19: 25 | J19: 71.4 | K19: Father | L19: Salaried | M19: 8 | N19: EWS | O19: No | P19: NA | Q19: No | R19: NA | S19: Waiting for the bank to reach them out Need assitance from us | T19: 11/7 : Salaried , Salary : 8LPA, Father is talking in different banks || Loan required : need to ask father Father's number : 7782842226 Had a father , father hasn't received any call from icici || has already filled the form || Have shared the number to icici. Have talked to propelld , but father told that they would reach out to them once he processes it. Father is coming to bangalore on Monday. Requires full amount of loan 15/7 : Father came to office , he shared all the documents. Mother's PAN was left which he would share on 18th of July 18/7 : Has shared mother's PAN. suggested him to send to propelld directly. 22/7 : Propelld contacted him, again he has shared documents to propelld. 28/7 : It's with credit team of propelld,. they shall be confirming by 3pm. | U19: Yes | V19: Yes | W19: Yes | AA19: Control | AB19: Control | AG19: Ongoing | AH19: Processing by Propelld | AI19: No | AJ19: No | AK19: No
A20: 19 | B20: Vanshika Rathore | C20: 7597802620 | D20: PROV260502005 | E20: SSAHE | F20: Yes | G20: Non Critical | H20: 0.05 | I20: 20 | J20: 60 | K20: Father | L20: Salaried | M20: 29 | N20: ITR | O20: Yes | P20: NA | Q20: No | R20: NA | S20: In Conversation with HDFC | T20: 11/7 : Had contacted the mother, mother suggested that someone has died in the family, she would call back. 11/7 : Student has called back , they haven't processed any loan yet. Family would be coming on tuesday. So have to share the number with icici. have sent the reminder in my calendar to do it. 18/7 : Loan required : 20, they'll either proceed with either hdfc or icici 23/7 : Co applicant Name: Rupendra Singh Rathore Relationship: Father Co-applicant e-mail id: rsrathore81@gmail.com My mobile no. 8085351495 ITR filed:1.49 lacs Copy of last yr itr attached | U20: Yes | V20: No | W20: No | AA20: Control | AB20: Control | AG20: Ongoing | AH20: Processing at other bank, Processing by GyanDhan | AI20: No | AJ20: No | AK20: No
A21: 20 | B21: Aatharva uday Nirhali | C21: 9869868577 | D21: PROV260506354 | E21: SSAHE | F21: No | G21: Loan not required | H21: 0.05 | I21: 25 | J21: 73 | K21: Father | L21: Self-Employed | M21: 6 | N21: ITR | O21: Yes | P21: 650 | Q21: No | R21: NA | S21: Waiting for the bank to reach them out Need assitance from us | T21: 11/7 : Father wants to visit the campus within 8-15 days. Loan not required. Have shared the details with SST | U21: No | V21: No | W21: No | AA21: Not required | AB21: Not required | AG21: Not required
A22: 21 | B22: Ankit Kumar | C22: 8603034436 | D22: PROV260505049 | E22: SSAHE | F22: Yes | G22: Loan not required | H22: 0.275 | I22: 4 | J22: 73 | K22: Father | L22: Farmer | M22: 5 | N22: Income Certificate | O22: No | P22: NA | Q22: No | R22: NA | S22: Waiting for the bank to reach them out Need assitance from us | T22: 11/7 : Student is taking loan through Bihar Credit Card Scheme of 4L and the rest of the fees would be paid by student's father itself | U22: No | V22: No | W22: No | AA22: Not required | AB22: Not required | AG22: Not required
A23: 22 | B23: Rupali Yadav | C23: 9555375578 | D23: PROV260602216 | E23: SSAHE | F23: Yes | G23: Non Critical | H23: 0.15 | I23: 20 | J23: NA | K23: Self | L23: Self-Employed | M23: 5 | N23: NA | O23: No | P23: NA | Q23: No | R23: NA | S23: Waiting for the bank to reach them out Need assitance from us | T23: 11/7 : Student wants to take the loan after 2nd year, 10L would be paid by the family and 10L will be paid by the student. Father is in thailand. 14/7 : Brother called , wanted to enquire about the loan, 20/7: Have suggested her to take the loan sanction at least now, was not okay with high rate of interest, shared leads with our banks. | U23: No | AA23: Not required | AB23: Not required | AG23: Not required
A24: 23 | B24: Ankit Gupta | C24: 7870435737 | D24: PROV260501472 | E24: SSAHE | F24: Yes | G24: Non Critical | H24: 0.225 | I24: 20 | J24: 83 | K24: Father | L24: Self-Employed | M24: 6 | N24: Income certificate | O24: No | P24: NA | Q24: No | R24: NA | S24: in talks of BOI , DRCC IN BIHAR | T24: 11/7 : DNP 15/07/2026: In talks with BOI - wants BOI but BOI not providing * Pain Point - Low income but need collateral free, also not agreeing with high int as offered by Propelld * Shared profile with ICICI also to confirm that whether top up loan allowed over and above SCC schemes of states.(Student from Bihar) 20/7: DNP 23/7: Processing , is fairly confident, 27/7 : Still processing for the loan, has opened the account recently | U24: Yes | V24: yes | AA24: Control | AB24: Control | AG24: Ongoing | AH24: Processing by Icici | AK24: Yes
A25: 24 | B25: Bhuvan Tk | C25: 7259802878 | D25: PROV260606019 | E25: SSAHE | F25: Yes | G25: Critical | H25: 0.325 | I25: 20 | J25: 82 | K25: Father | L25: Salaried | M25: 2 | N25: Income certificate | O25: No | P25: NA | Q25: No | R25: NA | S25: Waiting for the bank to reach them out Need assitance from us | T25: 11/7 : this student has got revised SL for 32.5% schoolarship but POL as 22.5%, Can you please check and confirm , as its showing 22.5% on scholarship calculator and to the student on his portal. Loan : 20L , Father's income : 2LPA, no banks would be able to provide loan on this Student called again : asking for collateral loan. 16/7: Low income, but undisclosed income of rs. 25000/month from various properties. Probable sol: If NBFC's can by pass the lack of proof of income. Co app income = 12,000 unsecured loan requirement - 18,00,000 no other co app 25/7 : PM vidyalakshmi has been suggested , student told he will be able to manage post 7.5L 28/7 : Spoke to the student , guided him around the PM vidyalakshmi again. Suggested him to go to the bank and process this. | U25: Yes | V25: Yes | W25: Yes | Z25: Yes | AA25: Risk | AB25: Risk | AG25: Ongoing | AH25: Processing by GyanDhan | AJ25: No | AK25: Yes
A26: 25 | B26: Rohit Kumar | C26: 9279392342 | D26: PROV1000003417 | E26: SSAHE | F26: Yes | G26: Critical | H26: 0.075 | I26: 18 | J26: 51 | K26: Father | L26: Farmer | M26: 4 | N26: Income Certificate | O26: No | P26: NA | Q26: Yes | R26: Agricultural | S26: Waiting for the bank to reach them out Need assitance from us | T26: 11/7 : Loan required : 20L Father's income : 4L Father profession : Farmer ITR filed : No 16/7 : Not going with ICICI as do not have the requisite docs asked by the bank, waiting for a call back from propelld Probable sol: More than 3l so gyandhan or propelld may sanction, (if student is okay with the int rate) 23/7: Rejected from propelld, due to low income/Abroad Loans/low requirement/Others last option gyandhan | U26: Yes | V26: Yes | W26: Yes | Z26: Yes | AA26: Risk | AB26: Risk | AG26: Ongoing | AH26: Processing by GyanDhan | AJ26: No
A27: 26 | B27: Dhairya Sommanek | C27: 9699437102 | D27: PROV260605047 | E27: SSAHE | F27: Yes | G27: Critical | H27: 0.2 | I27: 25 | J27: 68.3 | K27: Father | L27: Self-Employed | M27: 9 | N27: Income Certificate | O27: No | P27: 790 | Q27: Yes | R27: Residential | S27: Waiting for the bank to reach them out Need assitance from us | T27: 9/7/26 : Had a conversation with the kid, looking for loan of 16 lakhs, sent it to icici 10/7/26 : Got the update from the student, he would proceed for the loan after 19th , since no PAN card available 16/7/26: Student will apply for PAN after his bday which is coming, ICICI said only issues is with PAN, based on income , loan might get sanction. Actual Problem:- Total time for PAN to come and then the loan process. Action: C+3, call back and check 21/7 : Father income : 9.5L, Mother : 6.5L, ITR filed : yes , Father's profession : Insurance business 30/7 : Icici got rejected. Student wants to talk to the Gyan dhan | U27: Yes | V27: Yes | W27: No | X27: No | Y27: No | Z27: Yes | AA27: Control | AB27: Control | AG27: Ongoing | AH27: Processing by Icici, Processing by GyanDhan | AI27: No | AJ27: Yes
A28: 27 | B28: Varsha B Patil | C28: 7090531131 | D28: PROV1000000485 | E28: SSAHE | F28: Yes | G28: Non Critical | H28: 0.125 | I28: 18 | J28: 87 | K28: Father | L28: Farmer | M28: 6 | N28: EWS | O28: Yes | P28: 644 | Q28: Yes | R28: Agricultural | S28: Only Propelled discussed and Rate of intrest is Higher-14% | T28: NATC *15/7/2026: DNP, reached out on mail *16/7/26: Has not started looking for loan, have shared the lead to all our partners *23/7: DNP 27/7 : DNP - 2nd call : Student mentioned they have some loan pending from their end for them to send | U28: Yes | V28: Yes | W28: Yes | Z28: Yes | AA28: Control | AB28: Control | AG28: Ongoing | AH28: Processing by GyanDhan | AL28: Were DNP until recently, and were not trying at personal level, have shared the leads.
A29: 28 | B29: Himanshu Kashyap | C29: 7635014278 | D29: PROV260608927 | E29: SSAHE | F29: Yes | G29: Non Critical | H29: 0.1 | I29: 10 | J29: 60.6 | K29: Father | L29: Salaried | M29: 2.76 | N29: EWS | O29: Yes | P29: 773 | Q29: Yes | R29: Agricultural | S29: Waiting for the bank to reach them out Need assitance from us | T29: 11/7 : Father's profession : Govt job ( Agriculature dept) Annual income : Loan to take : 10-12L , and the rest of the amount he would take loan. He will make me talk to the father in the evening. 21/7: DNP 21/7 : Student has already applied for collateral loan for PM vidyalakshmi. 31/7 : Student has got the top up loan on his exisisting home loan, should be disbursed in 2-3 days. | U29: Yes | V29: No | W29: No | AA29: Control | AB29: Control | AG29: Ongoing | AH29: Processing by PM vidyalakshmi
A30: 29 | B30: Aryan Santosh Pagar | C30: 9403503971 | D30: PROV1000001562 | E30: ADYPU | F30: Yes | G30: Non Critical | H30: 0 | I30: 28 | J30: 82 | K30: Father | L30: salaried | M30: 11 | N30: Income Certificate | O30: Yes | P30: NA | Q30: No | R30: NA | S30: Waiting for the bank to reach them out Need assitance from us | T30: 9/7/26 : Student has changed the campus , he wants to take loan. Student wants to take ₹16Lakhs loan. He is okay with icici and propelled, father is salaried 10/7/26 : Father confirmation required ,Details given to Aryan. 21/7 : Asked for gyan dhan and they are already processing with Central Bank. | U30: Yes | V30: Yes | W30: Yes | Z30: Yes | AA30: Control | AB30: Control | AG30: Ongoing | AH30: Processing by GyanDhan, Processing at other bank
A31: 30 | B31: Avne Deepak | C31: 8459692377 | D31: PROV1000000430 | E31: ADYPU | F31: Yes | G31: Non Critical | H31: 0.2 | I31: 15 | J31: 75 | K31: Father | L31: salaried | M31: 12 | N31: Income Certificate | O31: Yes | P31: 835 | Q31: Yes | R31: Resindetial | S31: Waiting for the bank to reach them out Need assitance from us | T31: 9/7/26 : Couldn't connect , was busy on another call *15/7/26: Call busy , seems number problem. Reached out on mail 20/7: Talked to his father, had not received any calls yet. shared the leads | U31: Yes | AA31: Control | AB31: Control | AG31: Ongoing | AH31: Processing by Icici, Processing by GyanDhan
A32: 31 | B32: Tatvagna Tandel | C32: 9054265913 | D32: PROV1000001374 | E32: ADYPU | F32: Yes | G32: Non Critical | H32: 0.2 | I32: 15 | J32: NA | K32: Father | L32: salaried | M32: 8 | N32: Salary Slip | O32: No | P32: 780 | Q32: No | R32: NA | S32: Waiting for the bank to reach them out Need assitance from us | T32: 9/7/26 : 20 lakhs, fathers income 8L, Father is a NRI, merchant navy. 10/7/26 : Spoke with the student and shared the list of required documents. He will confirm with his father and then share the documents. 21/7: Decided not to take loan, will pay the sem fees in 2-3 days | U32: No | V32: Yes | W32: Yes | AA32: Not required | AB32: Not required | AG32: Not required
A33: 32 | B33: Raj Harkal | C33: 8459935236 | D33: PROV260503159 | E33: ADYPU | F33: Yes | G33: Non Critical | H33: 0.175 | I33: 17 | J33: 68.8 | K33: Father | L33: Farmer | M33: 1 | N33: EWS | O33: Yes | P33: NA | Q33: Yes | R33: Agricultural | S33: Wating for SBI as its our partner mentioned in the website | T33: 9/7/26 : 20 lakhs, father's income : 60k/month + agriculture income : 15L , have got the call from icici filled the form today and processing the loan with icici 21/7:In process with ICICI and gyandhan. 31/7: GD (Process has successfully logged in with Poonawalla. Process initiated and all documents received with Credila and Gyandhan. ICICI status is case forwarded.) | U33: Yes | V33: Yes | W33: No | Z33: Yes | AA33: Control | AB33: Control | AG33: Ongoing | AH33: Processing by Icici, Processing by GyanDhan
A34: 33 | B34: Ashlesha sinha | C34: 7982258229 | D34: PROV260502939 | E34: SSAHE | F34: Yes | G34: Non Critical | H34: 0.125 | I34: 25 | J34: 67 | K34: Mother | L34: Self-Employed | M34: 24 | N34: Income Certificate | O34: No | P34: NA | Q34: No | R34: NA | S34: Waiting for the bank to reach them out Need assitance from us | T34: 11/7 : ITR not available, have really good income with no income proof, Has solid working income upto 1Cr in an year. Father will talk to the CA for filing the ITR. Father has nothing in pakka form. 13/7 : Parents spoke with me in length, have shared their details with PRopelld 16/7 : shared all the details with propelld. 20/7 : PRopelld approved it for 20L, with 13% interest , father and mother wanted me to share the profile with gyan dhan , have shared it 27/7 : Gyan dhan have told them that the interest to provide it for 11%, they want it 10%, still the file is pending for complete approval | U34: Yes | V34: Yes | W34: Yes | AA34: Control | AB34: Control | AG34: Ongoing | AH34: Processing by GyanDhan, Loan sanctioned by Propelld
A35: 34 | B35: suman jana | C35: 7003207775 | D35: PROV260500865 | E35: ADYPU | F35: Yes | G35: Critical | H35: 0.075 | I35: 25 | J35: 81 | K35: Father | L35: Self-Employed | M35: 2 | N35: Income Certificate | O35: No | P35: NA | Q35: Yes | R35: Residential | S35: in Discussion with SBI, Looking for option from our side | T35: 9/7/26 : dnp 10/7/26 : DNP , have sent the details to SST to check the activeness of the student . Divyansh tried reaching to the student *15/7/26- In Discussion with SBI at personal level Shared profile 21/7: DNP 23/7: DNP | U35: Yes | V35: Yes | W35: Yes | AA35: Risk | AB35: Risk | AD35: Hi Student is DNP for long and is a risk case, can we check on the activeness of the student. | AF35: will call | AG35: Ongoing | AH35: Processing at other bank | AJ35: No
A36: 35 | B36: Aman Kumar Pandey | C36: 9049158666 | D36: PROV260502978 | E36: ADYPU | F36: Yes | G36: Non Critical | H36: 0.175 | I36: 25 | J36: 73 | K36: Father | L36: salaried | M36: 4.5 | N36: EWS | O36: Yes | P36: 760+ | Q36: Yes | R36: Residential | S36: Propelld contacted didn't like what was offered , waiting for more options | T36: 9/7/26 :Student has got offer from propelld of 15%, father's income : 45k/month , have sent to icici to talk. Loan amt : 28 Lacs. 18/7: He didnt like the proposal from propelld since he could not explain properly, have shared his number with Gyan Dhan 28/7 : Student has submitted all the documents to credilla, Field verification is pending 31/7 : Student has got the placement report from adypu, arranged it and sent it ot him. he is taking loan from pnb | U36: Yes | V36: Yes | W36: Yes | AA36: Control | AB36: Control | AG36: Ongoing | AH36: Processing by GyanDhan
A37: 36 | B37: Dev Anand kumar | C37: 9162847749 | D37: PROV260600189 | E37: SSAHE | F37: Yes | G37: Non Critical | H37: 0.25 | I37: 18 | J37: 73.6 | K37: Father | L37: Salaried | M37: 5.4 | N37: Salary slip | O37: Yes | P37: 800 | Q37: No | R37: NA | S37: Waiting for the bank to reach them out Need assitance from us | T37: 12/7 : Student will take loan. Student is already talking to ICIC, HDFC, Axis. Father's income : 45k/month, Father profession : Government teacher. Tentative date for loan, : Monday tuesday loan should be processed. 14/7 : 18L loan, icici didn't approve, hdfc , student wants help now, sending it to propelld. 21/7:Rejected from everywhere , only Gyandhan option left. 31/7: Deemed not eligible by GD 01/8 : Student has not got a call from gyan so he is trying from the | U37: Yes | V37: No | W37: No | AA37: Risk | AB37: Risk | AG37: Rejected | AH37: Processing by GyanDhan, Processing by Propelld | AK37: Yes
A38: 37 | B38: Raghav Parashar | C38: 9770750570 | D38: PROV260506203 | E38: ADYPU | F38: Yes | G38: Non Critical | H38: 0.2 | I38: 25 | J38: 64.4 | K38: Father, Mother | L38: Self-Employed | M38: 5 | N38: EWS | O38: Yes | P38: NA | Q38: No | R38: No | S38: Waiting for the bank to reach them out Need assitance from us | T38: 9/7/26 : Student requires the loan of 25 L. Father's income under 5L. Have shared the details to icici and propelld both 16/7/26 : Waiting on the documents from students side ( PRopelld). 21/7 : Propelld called, student still doesnt have PAN. Once the PAN comes he would proceed with it | U38: Yes | V38: Yes | W38: Yes | AA38: Control | AB38: Control | AG38: Ongoing | AH38: Docs Pending
A39: 38 | B39: RIDDHIT BHUTRA | C39: 9662748817 | D39: PROV260606462 | E39: ADYPU | F39: Yes | G39: Non Critical | H39: 0 | I39: 25 | J39: 78.4 | K39: Father | L39: Self-Employed | M39: 8 | N39: ITR | O39: Yes | P39: 700 | Q39: No | R39: No | S39: Waiting for the bank to reach them out Need assitance from us | T39: 9/7/26 : dnp *15/7/26 - Need to call mother 9887970001 - poornima (DNP) dont need loan | U39: No | AA39: Not required | AB39: Not required | AD39: Mother just said they dont want a loan and cut the call, so maybe an intent check is needed here. | AG39: Not required
A40: 39 | B40: Aarohan prasad | C40: 7811062400 | D40: PROV260607342 | E40: ADYPU | F40: Yes | G40: Critical | H40: 0.075 | I40: 25 | J40: 60 | K40: Father | L40: Self-Employed | M40: 5 | N40: ITR | O40: No | P40: NA | Q40: No | R40: No | S40: Waiting for the bank to reach them out Need assitance from us | T40: 9/7/26 : Student wants to pay the interest and principal amt after 4 years. he has received call from icici bank and propelld, but icici has rejected due to income and propelld has higher rate of interest. Need to send their number to study4buddy. 16/7/26: Student in talks with cuku finance, has asked to reconnect with proplld (initially rejected the same), interested in offering by gyandhan. Prob sol: - Student admitted that he initially rejected proppld , but realised in his case he wont get the product he wants so seems more flexible with the offerings. 17/7 : Student is panicking because of the loan , student told he wouldn't be able to handle the interest monthly. He is a drop student. 18/7 : Student's last year of the admission. Student is worried about the monthly expenses and is a good student. He has been in stress, intent is too high. Student arranged the block from his brother which he has to return. 29/7: Docs pending with GD but a high risk case and not ready to pay high rate of int.. might frop | U40: Yes | V40: Yes | W40: Yes | AA40: Risk | AB40: Risk | AG40: Ongoing | AH40: Processing by GyanDhan | AJ40: Yes | AK40: Yes
A41: 40 | B41: AMIT CHANDRA | C41: 7520947325 | D41: PROV260503971 | E41: ADYPU | F41: Yes | G41: Non Critical | H41: 0.175 | I41: 10 | J41: 66 | K41: Father | L41: army Retired | M41: 3 | N41: ITR | O41: No | P41: 750+ | Q41: Yes | R41: Agricultural | S41: Waiting for the bank to reach them out Need assitance from us | T41: 10/7/26 : DNP *15/7/26 : Student has started trying from their side now. : Also have shared their profile with our partners. 20/7: DIdnt receive any calls , to follow up and is trying in SBI 29/7: GD has agreed to loan at 14%, waiting for student docs to starte the process. | U41: Yes | AA41: Control | AB41: Control | AG41: Ongoing | AH41: Processing at other bank, Processing by GyanDhan | AJ41: No
A42: 41 | B42: Jivhesh Shekatkar | C42: 7058558414 | D42: PROV260604523 | E42: ADYPU | F42: Drop | G42: Critical | H42: 0.275 | I42: 15 | J42: 56.6 | K42: Father | L42: Self-Employed | M42: 2.8 | N42: Income Certificate | O42: No | P42: 750+ | Q42: Yes | R42: Residential | S42: Propelld contacted didn't like what was offered , waiting for more options | T42: 10/7/26 : Loan required : Father is doing business of electricals || Student found the SBI cheaper and is in touch with him. Student hasn't started the process yet, student hasn't considered the admission due to high fees. Student has the offer letter from Next wave , next wave fees : 14.5 Lakhs. Student is only factoring all the new age of techonology. Father;s income : 2.8Lakhs , if yes, he would be proceeding ahead with us. Have sent the case to Vishwa, for extended scholarship. 14/7 : Had a word, inquiring about CSIS scheme. 21/7 : Student is still under doubt whether he should move ahead or not with upgrad due to scholarship issue. Student is insisting about the same 25% scholarship and hence waiting on the loan to process. Conveyed him clearly we cant go above 20%. | U42: Refund | V42: No | AA42: Refund case | AB42: Refund case | AG42: Ongoing | AH42: Processing by PM vidyalakshmi, Processing by GyanDhan | AI42: No | AJ42: No
A43: 42 | B43: Prince Prajapati | C43: 8176069823 | D43: PROV260502017 | E43: ADYPU | F43: Yes | G43: Non Critical | H43: 0.125 | I43: 18 | J43: 75 | K43: Father | L43: salaried | M43: 12 | N43: Salary Slip | O43: No | P43: 750+ | Q43: No | R43: NA | S43: ICICI taken detail student waiting for call back | T43: - 14/7 : father stays outside india, 🇮🇳 fabricator , annual income : 12L , ITr filed : No , 780 cibil, loan required : 8L 20/7: Not started yet anything , since only 8L have suggested to go to vidyalakshmi portal, also sharing leads 3/8:- Still not sure whether want loan or not , have suggested to start if don't or pay the fees. | U43: Yes | V43: Yes | W43: Yes | X43: No | Y43: No | AA43: Control | AB43: Control | AG43: Ongoing | AH43: Processing by Icici, Processing by Propelld
A44: 43 | B44: Riya somani | C44: 7067219297 | D44: PROV260606480 | E44: ADYPU | F44: Yes | G44: Critical | H44: 0.235 | I44: 20 | J44: 86.2 | K44: Father | L44: Self-Employed | M44: 6 | N44: EWS | O44: No | P44: NA | Q44: No | R44: NA | S44: Waiting for the bank to reach them out Need assitance from us | T44: 10/7/26 : Dialed number was busy 15/7/26 : Have shared leads to banks. They are starting from their side as well. 20/7: Said received no calls, need to check back 27/7 : Have started the process, 20L, she is speaking with sbi and icici | U44: Yes | V44: Yes | W44: Yes | AA44: Control | AB44: Control | AG44: Ongoing | AJ44: No | AL44: Leads were shared a while back but student contested no calls received, and bank feedback say unreachable. Have asked banks to call again.
A45: 44 | B45: Ashu kumar | C45: 9608008286 | D45: PROV260607929 | E45: SSAHE | F45: Yes | G45: Non Critical | H45: 0.15 | I45: 20 | J45: 74 | K45: Father | L45: Self-Employed | M45: 4 | N45: ITR | O45: No | P45: 750 | Q45: Yes | R45: Residential | S45: Waiting for the bank to reach them out Need assitance from us | T45: 12/7 : DNP Student called back. Student wants the loan, Student is already talking with HDFC. Father's income : 6L/ annum. ICICI has rejected the loan , HDFC was ready to provide but didn't like the proposal of paying the interest from first month. Loan amount required : 20Lakhs 20/7: In talks with PNB(fairly positive) 31/7: Ongoing with PNB only will be done | U45: Yes | V45: No | W45: No | X45: Yes | AA45: Control | AB45: Control | AG45: Ongoing | AH45: Processing at other bank
A46: 45 | B46: Kishlay Aanand | C46: 7970421213 | D46: PROV260600269 | E46: SSAHE | F46: Yes | G46: Non Critical | H46: 0.05 | I46: 20 | J46: 73.8 | K46: Father | L46: Salaried | M46: 12 | N46: Salary Slip | O46: Yes | P46: NA | Q46: Yes | R46: Residential | S46: Waiting for the bank to reach them out Need assitance from us | T46: 12/7 : Is already talking with study4buddy, Father's income : 1.10L, mother's co applicant , mother's income : 40k/month. icici denied due to loan income, already talking to hdfc credilla. 20L loan required. Will be telling till monday and tuesday/ 20/7: Ongoing with gyandhan, rejected by credilla 31/7: Payment done for 1st sem | U46: No | V46: No | W46: Yes | X46: Yes | Z46: Yes | AA46: Control | AB46: Control | AC46: 14/7/2026, | AG46: Not required | AH46: Processing by GyanDhan
A47: 46 | B47: Aman Jindrali | C47: 9380913035 | D47: PROV260601798 | E47: SSAHE | F47: Yes | G47: Non Critical | H47: 0.1 | I47: 23 | J47: 75.2 | K47: Father | L47: army retired | M47: 5 | N47: Income Certificate | O47: No | P47: 750 | Q47: Yes | R47: Agricultural | S47: Waiting for the bank to reach them out Need assitance from us | T47: 12/7 Student doesnt want loan through us right now, already in talks with SBI home branch. Told, in case required h'll contact back. He has shared the details with SBi, he should be knowing the status by 13, 14. 20/7: Fairly confident that loan will be sanctioned.Have suggested to take a backup 31/7: SBI taking time but confident will happen | U47: Yes | V47: No | W47: No | X47: No | AA47: Control | AB47: Control | AG47: Ongoing | AH47: Processing at other bank
A48: 47 | B48: Prithviraj Dashrath Patil | C48: 9579318055 | D48: PROV260609754 | E48: SSAHE | F48: Yes | G48: Non Critical | H48: 0 | I48: 25 | J48: 69 | K48: Father | L48: Salaried | M48: 4.5 | N48: Income Certificate | O48: No | P48: NA | Q48: No | R48: NA | S48: got call from buddy for study ,Waiting for the bank to reach them out Need assitance from us | T48: 12/7 :Loan required : 25 L, is already talking ICICI and yes bank, father's income : 7L/ year. Documents have been provided by the student, loan has not been sanctioned yet. 20/7: Process still going on various banks, have suggested toapply in more banks. 23/7 : Father was in pharma, but there is no proof of income , he recently resigned , after that he is a consultant but there is no income to show. has filed ITR of 10L. | U48: Yes | V48: Yes | W48: No | X48: Yes | AA48: Control | AB48: Control | AG48: Ongoing | AH48: Processing by Icici, Processing by GyanDhan, Loan Sanctioned by Proplld
A49: 48 | B49: Hari Kishan Sharma | C49: 9636324452 | D49: PROV260608906 | E49: SSAHE | F49: Yes | G49: Non Critical | H49: 0.05 | I49: 11 | J49: 68 | K49: Father | L49: Salaried | M49: 4 | N49: EWS | O49: Yes | P49: 776 | Q49: No | R49: NA | S49: Waiting for the bank to reach them out Need assitance from us | T49: 12/7 : Loan required : 25 , Co applicant : Father , Father's salary : 6.5L , ITR filed : yes , requires collateral loan. Student asked me for suggestion which company should he go for, suggested ICICI. 14/7 : Contacted by multiple people from ICICI. Called to confirm the associate. number 20/7: In process with ICICI, most probably yes, if not then he has asked to share his leads elsewhere. | U49: Yes | V49: Yes | W49: Yes | X49: No | Y49: Yes | Z49: Yes | AA49: Control | AB49: Control | AG49: Ongoing | AH49: Processing by Icici
A50: 49 | B50: Priyanshu Agrawal | C50: 8269939000 | D50: PROV260503817 | E50: SSAHE | F50: Yes | G50: Non Critical | H50: 0.075 | I50: 18 | J50: N/A | K50: Father | L50: Self-Employed | M50: 6 | N50: ITR | O50: Yes | P50: arit | Q50: No | R50: NA | S50: wants to pay the intrest nd principal after BTECH, multiple banks contacted | T50: 12/7 : Requires Loan, 15-18 Lakhs,ITR filed: 6.75 L , father has a shop, have tried in different banks, he requires the loan without collateral, he has already tried public banks and they have told that he will have to pay interest from the first month which he didn't want. I guided him RBI says that any non collateral education loan student will have to bear the interest cost from 1st month , also I have guided him to go with public banks if the loan is getting approved. Also sharing his number with icici. 20/7: Busy 21/7: Paying first sem fees himself, will take a loan then , have suggested to sanction it now only | U50: No | V50: Yes | W50: No | X50: No | AA50: Not required | AB50: Not required | AG50: Not required | AJ50: No
A51: 50 | B51: Bipin kumar | C51: 9155013036 | D51: PROV260608012 | E51: SSAHE | F51: Yes | G51: Critical | H51: 0.115 | I51: 20 | J51: 77.6 | K51: Father | L51: Farmer | M51: 5 | N51: NA | O51: No | P51: NA | Q51: No | R51: NA | S51: Waiting for the bank to reach them out Need assitance from us | T51: 12/7 : Loan required : 20L, Father's profession : Farmer, Income yearly : 5L , ITR filed : No , He has not received any call from the bank. He belongs from Bihar. He has not tried any loans from anywhere. Not willing to pay interest from the first month. suggested him the collateral loan option as well. Student was worried and have calmed him down and suggested him to reach out to public bank as well 16/7: Switch off 21/7: Gyandhan offering 15% int, student not comfortable. 27/7 : Student is taking loan from their side , pnb bank. Gyan dhan he is not comfortable with interest. hasn't started the process yet | U51: Yes | V51: No | W51: Yes | X51: Yes | AA51: Risk | AB51: Risk | AG51: Not even started | AI51: Yes | AJ51: No | AL51: Student rejected Propelld and GyanDhan due to high int, got rejected by ICICI, have suggested to reach out to other banks as well.
A52: 51 | B52: DEEPIKA KUMARI | C52: 9908200168 | D52: PROV260503681 | E52: SSAHE | F52: Yes | G52: Non Critical | H52: 0.3 | I52: 18 | J52: 82 | K52: Father | L52: Self-Employed | M52: 12 | N52: ITR | O52: Yes | P52: NA | Q52: No | R52: NA | S52: Waiting for the bank to reach them out Need assitance from us | T52: 12/7 : Loan required : 20L, mother picked the call, mother suggested that father will talk to him, Father has a transport business. Father will call back on my number. 13/7 : 1st update : 7075803172, father called , but then he recevied another call , will call back. 13/7 : 16L Loan required , father's income : 12L, ITR filed : 1cr || HDFC,BOB. 21/7: Have dropped the leads, everywhere. | U52: Yes | V52: Yes | W52: No | X52: No | AA52: Control | AB52: Control | AG52: Ongoing | AH52: Processing by Propelld, Processing by Icici, Processing by GyanDhan
A53: 52 | B53: Piyush Hole | C53: 8237855763 | D53: PROV1000001309 | E53: ADYPU | F53: No | G53: Loan not required | H53: 0.1 | I53: 25 | J53: 55.4 | K53: Father | L53: self imployed | M53: 6.5 | N53: ITR | O53: Yes | P53: NA | Q53: No | R53: NA | S53: In discussion with buddy4study,Waiting for the bank to reach them out Need assitance from us | T53: 10/7/26 : Not required loan, need guidance to pay the fees. Have shared it sst team. | U53: No | V53: No | W53: No | AA53: Not required | AB53: Not required | AG53: Not required
A54: 53 | B54: Ankit Kumar(2) | C54: 6205356806 | D54: PROV260606398 | E54: SSAHE | F54: Drop | G54: Loan not required | H54: 0.05 | I54: 8 | J54: 65 | K54: Father | L54: Salaried | M54: 14 | N54: ITR | O54: No | P54: NA | Q54: No | R54: NA | S54: Waiting for the bank to reach them out Need assitance from us | T54: 12/7 : Student has raised the refund request. | U54: Refund | V54: No | W54: No | AA54: Refund case | AB54: Refund case | AG54: Not required
A55: 54 | B55: Aryan Mishra | C55: 7004672915 | D55: PROV260501578 | E55: SSAHE | F55: Yes | G55: Critical | H55: 0.125 | I55: 20 | J55: 59 | K55: Father | L55: Salaried | M55: 4 | N55: EWS | O55: No | P55: NA | Q55: No | R55: NA | S55: Waiting for the bank to reach them out Need assitance from us | T55: 12/7 : Loan required : 20L , Father's profession : Hotel sector Father Salary : 30000/m , Mother salary : 10000/m , ITR filed : no. 16/7: Student has been contacted by proplld and study4buddy, Problem:- Student seemed lethargic on the doc sharing and talking to bank front, have suggested to do all the process and reach out if any problem 23/7: DNP | U55: Yes | V55: No | W55: Yes | X55: Yes | AA55: Control | AB55: Control | AD55: Needs an intent check | AG55: Ongoing | AH55: Processing by Propelld | AJ55: No
A56: 55 | B56: Rydham Arora | C56: 8094803647 | D56: PROV260606411 | E56: SSAHE | F56: Yes | G56: Non Critical | H56: NA | I56: 15 | J56: NA | K56: Uncle | L56: Salaried | M56: 20 | N56: ITR | O56: Yes | P56: 800+ | Q56: No | R56: NA | S56: Waiting for the bank to reach them out Need assitance from us | T56: 12/7: Mother picked the call, father wants to take loan and he is coming on thursday and friday to meet vishwa , Father's number : 8824057469, Father wants to first meet vishwa and then take loan. however have told him that I would forward his details to icici. 18/7: called father, call went busy 21/7 : called father, call DNP 23/7 : Father had come to office will process his file. once he shares the details with me. his brother will be the coapplicant. 29/7 : Student doesnt have PAN card yet, they would get the PAN by next week. Student is not 18 yet, so no PAN card yet. | U56: Yes | AA56: Control | AB56: Control | AG56: Not even started | AL56: Father is waiting to come to campus, will reach on 22nd july tomorrow
A57: 56 | B57: Rohan Kumar Rai | C57: 7002382047 | D57: PROV1000000453 | E57: SSAHE | F57: Yes | G57: Non Critical | H57: 0.1 | I57: 10 | J57: 87 | K57: Father | L57: Salaried | M57: 7 | N57: Income Certificate | O57: Yes | P57: 750 | Q57: No | R57: NA | S57: Waiting for the bank to reach them out Need assitance from us | T57: 12/7 : Student says he has not decided how he would pay the fees. Loan required : Not sure. He wanted to know the details of the loan which I have given. Have guided the student around loan ROI. He was asking when the fees has to be paid, i told him after the document verification 15 days is the time in which you have to pay the fees. 21/7: Need loan from 2nd year | U57: No | AA57: Not required | AB57: Not required | AG57: Not required
A58: 57 | B58: Raj Ambolikar | C58: 8087388564 | D58: PROV260609029 | E58: ADYPU | F58: Yes | G58: Non Critical | H58: 0 | I58: 20 | J58: 68 | K58: Father | L58: salaried | M58: 12 | N58: Salary Slip | O58: No | P58: 750+ | Q58: No | R58: NA | S58: Waiting for the bank to reach them out Need assitance from us | T58: 13/7 : DNP *15/7 : Student will give a call back when they are free 17/7: student will have someone talk from their family. risk: seem hesistant to share any info. 28/7: Dont want loan | U58: No | AA58: Not required | AB58: Not required | AD58: Need an intent check. This student seemed disinterested in sharing any information. Need an intent check. | AG58: Not required
A59: 58 | B59: Sarthak Pharande | C59: 8208569611 | D59: PROV260501326 | E59: ADYPU | F59: Yes | G59: Loan not required | H59: 0.1 | I59: 20 | J59: 63 | K59: Father | L59: salaried | M59: 7 | N59: Income Certificate | O59: No | P59: Good | Q59: No | R59: NA | S59: Waiting for the bank to reach them out Need assitance from us | T59: 13/7 : DNP 17/7: Student said they dont need any assistance from us right now. Action: Based on income level a C+2 callback can be done. | U59: No | AA59: Not required | AB59: Not required | AG59: Not required
A60: 59 | B60: Sarthak Agarwal | D60: PROV260611061 | E60: ADYPU | F60: Yes | G60: Non Critical | H60: 0.2 | I60: 25 | J60: NA | K60: Mother | L60: salaried | M60: 10 | N60: Income Certificate | O60: Yes | P60: NA | Q60: No | R60: NA | S60: Waiting for the bank to reach them out Need assitance from us | T60: 13/7 : Loan required : 25 Father : Unemployed Mother : DPS - teacher Co-applicant : Mother Salary : 10L/A Father number : 9810829998 - Rajeev Agarwal Student requested to call his father 21/7: Already has 3 loans, wants sister to be co-applicant who will start job next month Has asked not to call before next week." | U60: Yes | V60: Yes | W60: Yes | X60: No | AA60: Control | AB60: Control | AG60: Not even started | AL60: Already has 3 loans, wants sister to be co-applicant who will start job next month Will first ask bank fisrt
A61: 60 | B61: dhruv vaviya | C61: 9769631979 | D61: PROV260610532 | E61: SSAHE | F61: Yes | G61: Non Critical | H61: 0.2 | I61: 25 | J61: 45.5 | K61: Self | L61: Salaried | M61: 4 | N61: Salary Slip | O61: Yes | P61: 750 | Q61: No | R61: NA | S61: Waiting for the bank to reach them out Need assitance from us | T61: 13/7: Student is not sure whether he wants the loan or not. He says he wants to know the last date of the payment. Have forwarded him to SST. 20/7: Looking for non collateral loan under 10%, seems difficult have shared with out partners. 31/7 : DNP | U61: Yes | AA61: Risk | AB61: Risk | AG61: Ongoing | AH61: Processing by GyanDhan
A62: 61 | B62: Sanjukta Kalita | C62: 9864256523 | D62: PROV1000000391 | E62: SSAHE | F62: Yes | G62: Non Critical | H62: 0.3 | I62: 7.5 | J62: 93.2 | K62: Father | L62: Bussiness | M62: 1.5 | N62: EWS | O62: No | P62: NA | Q62: No | R62: NA | S62: Going to apply on PM Vidyalaskhmi portal Want the ,Not a critical case if she goes to pulic bank with PM vidyalaskhni | T62: 11/7/26 : DNP 14/7/26 : Father's income : 1.5 L Father : Shop, Business Mother, : Homemaker Loan : 7.5L Already processed with uco, sbi and pnb from vidyalakshmi scheme 21/7: In process | U62: Yes | AA62: Control | AB62: Control | AG62: Ongoing | AH62: Processing at other bank
A63: 62 | B63: Hritik Nanda | C63: 9350583736 | D63: PROV260605465 | E63: SSAHE | F63: Yes | G63: Non Critical | H63: 0.05 | I63: 6.5 | K63: Father, Mother | L63: Rental Income, Salried | M63: 6 | N63: ITR | S63: already getting the loan (hdfc bank - credilla) | T63: 9/7/26 : Have shared the details with propeld , he requires the loan of 6.5Lakhs. Rental income : 84200. wouldnt be feasible for icici bank. 21/7: Disbursed | U63: Yes | V63: No | W63: Yes | AA63: Control | AB63: Control | AG63: Disbursed | AH63: Disbursed
A64: 63 | B64: Naman | C64: 8824685303 | D64: PROV1000000344 | E64: SSAHE | F64: Drop | G64: Critical | H64: 0.6 | I64: 25 | J64: 0.932 | K64: Father | L64: Salaried | M64: 2.4 | N64: ITR | O64: Yes | P64: NA | Q64: No | R64: NA | S64: Waiting for the bank to reach them out Need assitance from us | T64: 9/7 : Spoke today, since the case was not clear yesterday, he has got 60% scholarship. Have shared the details to icici. 16/7: Student semmed distressed due to not getting loan and said might drop. Working to ascertain the reason for the same. | U64: Refund | V64: Yes | W64: No | Z64: Yes | AA64: Refund case | AB64: Refund case | AG64: Not required | AJ64: Yes
A65: 64 | B65: Sarvesh S M | C65: 9353659042 | D65: PROV260607627 | E65: SSAHE | F65: Yes | G65: Critical | H65: 0.35 | I65: 18 | J65: 0.94 | K65: Father | L65: Transportation Business | M65: 0.25 | N65: Income Certificate | O65: No | P65: 730 | Q65: No | R65: NA | S65: Student has been contacted by Propelled regarding the loan application. | T65: 10/7 : Had a word with the student, ICICI has rejected the loan. Have shared his details to propelld. 16/7 : ICICI and IDFC have rejected the loan, proplld has told to update by today evening, suggested gyandhan. 17/7 : Propelld has rejected his loan. low cibil going on through GyanDhan NBFC. 27/7 : Gyandhan would provide the loan to him ,is waiting on the state level exam results, which he has already provided. Moving this case from risk to control 28/8 : Loan approved from gyan dhan | U65: Yes | V65: Yes | W65: Yes | AA65: Control | AB65: Control | AG65: Loan Proccessed/Accepted | AH65: Loan sanctioned by gyan dhan | AI65: No | AJ65: No
A66: 65 | B66: Gooty Mukthyaar | C66: 9481468696 | D66: PROV260613069 | E66: SSAHE | F66: No | G66: Loan not required | H66: 0.2 | I66: 8 | J66: 0.88 | K66: Father | L66: PVT Employee | M66: 0.32 | N66: Income Certificate | O66: Yes | P66: 800 | Q66: No | R66: NA | S66: Student requires assistance with the education loan process. | T66: - 13/7 : Student took father on the call, as he was unaware of it. Had a word with student's father, Father mentioned they haven't recieved any call, want the loan of 8L. Father income > 10L, ITr filed , Cbil : 800, sending it to icici for approval. Student's father is claiming AC Indu has mentioned him that the fees has to be paid till 24th of August, raised it with Sales team. 16/7: DNR 21/7 : As per today, student is not planning to take any loan, he would take the loan in sem 3- sem 4 | U66: No | V66: Yes | W66: No | X66: No | AA66: Not required | AB66: Not required | AG66: Not required | AJ66: No
A67: 66 | B67: HIMESH PADHAN | C67: 6370810692 | D67: PROV260506232 | E67: ADYPU | F67: Yes | G67: Critical | H67: 0.125 | I67: 25 | J67: 59 | K67: Father | L67: Farmer | M67: 0.4 | N67: Income Certificate | O67: No | P67: NA | Q67: No | R67: NA | S67: Waiting for the bank to reach them out Need assitance from us | T67: 10/7 : Student is ready to keep collateral for the loan. Have talked to icici bank for this 15/7 : Student got a call from icici, loan rejected from all places. 16/7 : Have suggested the student to go to sbi home branch and make him talk to me 29/7: Father , PAN Aadhar has gone for correction | U67: Yes | V67: Yes | W67: Yes | AA67: Risk | AB67: Risk | AG67: Ongoing | AH67: Processing by PM vidyalakshmi, Processing by GyanDhan | AI67: Yes | AJ67: Yes | AK67: Yes
A68: 67 | B68: Anand Pal | C68: 7705025068 | D68: PROV260502710 | E68: SSAHE | F68: Yes | G68: Critical | H68: 0.1 | I68: 20 | J68: 0.6707 | K68: Father | L68: Farmer | M68: 0.48 | N68: old income certificate | O68: NA | P68: NA | Q68: No | R68: NA | S68: Student requires assistance with the education loan process. | T68: 13/7 : Loan required : 18 L, father : farmer : Yearly income : 16/7/26:Real Risk: Low income + no collateral, not comfortable with high EMI to be paid from day 1 20/7: Not wanting the high rate by Gyandhan , want public or private bank, thinking of canl. 23/7 : Annual Income : 4.5L , concerned about the high interest rate, have informed 27/7 : Family is not okay from NBFC , have suggested him from to go from PM vidyalakshmi, he has a agricultural land. | U68: Refund | V68: Yes | W68: Yes | AA68: Refund case | AB68: Refund case | AG68: Not required | AI68: Yes | AJ68: No | AK68: Yes
A69: 68 | B69: HARSHIT VISHWKARMA | C69: 7617288784 | D69: PROV1000000337 | E69: SSAHE | F69: Yes | G69: Non Critical | H69: 0.2 | I69: 8 | J69: 0.758 | K69: Mother | L69: Self Emloyed | M69: 0.6 | N69: Income Certificate | O69: No | P69: NA | Q69: No | R69: NA | S69: Student has not yet been contacted by ICICI Bank or Propelled. Follow-up required. | T69: DNP called at 1:52 pm today, Called on 9th July : For the remaining amount, already have some savings. A loan of up to ₹8 lakh will be sufficient. He would like to apply under the PM Vidyalaxmi scheme. family's annual income is below ₹75,000 | U69: No | V69: No | W69: No | AA69: Not required | AB69: Not required | AG69: Not required | AJ69: No
A70: 69 | B70: Monika kushwaha | C70: 7225872182 | D70: PROV260502635 | E70: SSAHE | F70: Yes | G70: Critical | H70: 0.225 | I70: 20 | J70: 0.856 | K70: Father | L70: Farmer | M70: 0.6 | N70: Income Certificate | O70: NA | P70: NA | Q70: No | R70: NA | S70: Student is currently not engaged with any lending institution for an education loan. | T70: Busy on another call : called at 1:53pm on 8th July.Have Provided friends number, original number : 6261696422. dnp. The information previously shared was correct. 16/7:DNP , 18/7 : Monika kushwaha Gangadeen kushwaha 9243359684 gangadeen2009@gmail.com 9617192219 20 lack No 60000 Gangadeen kushwaha NE for any loan 29/7: Doc pending with Gyandhan | U70: Yes | AA70: Risk | AB70: Risk | AG70: Ongoing | AH70: Processing by PM vidyalakshmi | AI70: Yes | AJ70: Yes | AK70: Yes
A71: 70 | B71: Mahadeb Sarkar | C71: 9800367685 | D71: PROV1000001218 | E71: SSAHE | F71: Yes | G71: Critical | H71: 0.3 | I71: 25 | J71: 0.82 | K71: Brother | L71: Farmer | M71: 0.72 | N71: Income Certificate | O71: Yes | P71: 650 | Q71: No | R71: NA | S71: Student has received an initial call from ICICI Bank and is awaiting further communication to proceed. | T71: 13/7 : Loan : Father's income : 3l/year. hostel fees will be managed by the student. Provided it to propelld but chances are low for the student. has shown 1L/ year as income but in real its 3L/year. Father is a farmer. There is no income proof , neither is the father employed anywhere. Total loan required : 14L 16/7: Going with WB SCCS, needs some documents from the university, to share with the bank. 28/7 : DNP, (Shilpa has to confirm the WBCCS , they have already mailed ) | U71: Yes | AA71: Risk | AB71: Risk | AG71: Ongoing | AH71: Processing at other bank | AI71: No | AJ71: No
A72: 71 | B72: Devasy Keshari | C72: 9120455276 | D72: PROV260603237 | E72: SSAHE | F72: Yes | G72: Non Critical | H72: 0.125 | I72: 20 | J72: 0.764 | K72: Sister | L72: Business | M72: 0.72 | N72: Income Certificate | O72: No | P72: NA | Q72: No | R72: NA | S72: Student reports that no lending partner has contacted them. Follow-up required. | T72: DNP called on 13/7 at 5:53pm. 14/7 : Student called back Loan required : 22L Father's income : 5L, ITR filed : no Father profession : Shop Co applicant : Uncle , jwellery shop 21/7: Student rejected Poona & Propell due to high int, have told to apply in public banks but less possibility. 22/7 : Student called wont be able to do interest every month, have suggested him to apply PM Vidyalakshmi 30/7 : Collateral is there with mama, student went to bank for PM vidyalakshmi, manager has told that the 7.5L will be distributed within 4 years. have told the student to make me talk to BM since he is not allowing mama to be coapplicant | U72: Yes | Z72: Yes | AA72: Control | AB72: Control | AG72: Ongoing | AH72: Processing by PM vidyalakshmi | AJ72: No | AK72: Yes
A73: 72 | B73: Shubhashish Sharma | C73: 9009965351 | D73: PROV1000002099 | E73: SSAHE | F73: Yes | G73: Critical | H73: 0.3 | I73: 25 | J73: 0.56 | K73: Father | L73: Business | M73: 0.8 | N73: EWS | O73: No | P73: 740 | Q73: No | R73: NA | S73: Student has expressed preference for an education loan through ICICI Bank. | T73: 14/7 : - Loan amount : 20L - Father : Businessman - ITR : 4L - Annual Income : 5L 14/7 : Had a word with the Father , and have explained everything, shared the details to propelld 16/6: DNP 17/6: Have started the process, documents pending, NO ETA. Action: Call checkback C+2. 23/7: DNP | U73: Yes | V73: Yes | W73: Yes | AA73: Risk | AB73: Risk | AD73: Is DNP for a long time , not picking up banks' call also | AF73: Is active will pick up the next call | AG73: Ongoing | AH73: Processing at other bank | AJ73: No
A74: 73 | B74: Ansh Pratap Singh Tomar | C74: 9340910403 | D74: PROV1000000455 | E74: SSAHE | F74: Yes | G74: Non Critical | H74: 0.2 | I74: 10 | J74: 0.78 | K74: Father | L74: Self Emloyed | M74: 0.9 | N74: Income Certificate | O74: No | P74: 750 | Q74: Yes | R74: plots | S74: Student is interested in the Central Subsidy Scheme and is awaiting communication from ICICI Bank. | T74: DNP called at 1:54 pm today || DNR 9/7 16:47 *15/7 - Student is exploring loan options through various routes , we have also shared leads (not 100% sure , will take loan or not(based on int)) 28/7: Has given through SBI, asking for inc deadline | U74: Yes | AA74: Control | AB74: Control | AG74: Ongoing | AH74: Processing at other bank | AL74: Not sure, whether want loan or not
A75: 74 | B75: Saifulla Shaik | C75: 7331192674 | D75: PROV260607530 | E75: SSAHE | F75: Yes | G75: Critical | H75: 0.25 | I75: 18 | J75: 0.952 | K75: Father | L75: Farmer | M75: 0.9 | N75: Income Certificate | O75: Yes | P75: NA | Q75: No | R75: NA | S75: Student reports that no communication has been received from any loan partner. | T75: - Student says uncle will come in 1 -2 week , and then he will decide. 16/7: DNP - 25//7 - Spoke to me today about PM Vidyalakshmi , have guided him and have also provided his number to Gyan Dhan for process. | U75: Yes | AA75: Control | AB75: Control | AG75: Ongoing | AH75: Processing by GyanDhan, Processing by PM vidyalakshmi | AJ75: No | AL75: Not sure, whether want loan or not
A76: 75 | B76: Kaushal kumar | C76: 8210627860 | D76: PROV260503364 | E76: SSAHE | F76: Yes | G76: Loan not required | H76: 0.125 | I76: 10 | J76: 0.69 | K76: Brother | L76: LIC agent | M76: 0.9 | N76: OBC NCL | O76: NA | P76: NA | Q76: No | R76: NA | S76: Student requires assistance with the education loan process. | T76: 15/7 : Called , student's number is switched off, sharing it to SST 16/7: DNP 17/7:Do not require loan | U76: No | AA76: Not required | AB76: Not required | AG76: Not required | AJ76: No
A77: 76 | B77: Md Kamran Shah | C77: 9304099240 | D77: PROV260501165 | E77: SSAHE | F77: Yes | G77: Critical | H77: 0.2 | I77: 25 | J77: 0.714 | K77: Father | L77: Self Emloyed | M77: 0.95 | N77: Income certificate | O77: No | P77: NA | Q77: No | R77: NA | S77: Student has enquired about education loan options through Vijayalakshmi. | T77: PM vidyalakshmi scheme - Student has already filled the details reach out to them by today evening -8th July. 9th July : DNP on the call done, call back received , he hasn't submitted it as he has got the notice that the institute that he is registering he wouldn't get the non collateral loan > 7.5 Lakhs. Since he is from bihar , he can avail govt scholarship, will suggest him tomorrow 16/7 :- Student is wishing for PM Vidyalakshmi Scheme, (pending confirmation), have shared profile to NBFC partners(real risk) 23/7: Have talked to kamran he is waiting for the PM vidyalakshmi portal to be sorted out for SSHAE | U77: Yes | W77: Yes | Z77: Yes | AA77: Risk | AB77: Risk | AG77: Ongoing | AH77: Processing by Propelld, Processing by PM vidyalakshmi | AI77: Yes | AJ77: No | AK77: Yes
A78: 77 | B78: Md Adnan | C78: 8581979897 | D78: PROV260504282 | E78: SSAHE | F78: Yes | G78: Critical | H78: 0.125 | I78: 22 | J78: NA | K78: Father | L78: Salaried | M78: 0.95 | N78: Income Certificate | O78: NA | P78: NA | Q78: No | R78: NA | S78: Student has indicated that they may opt for a refund if adequate loan assistance is not provided. | T78: 14/7 : Loan required : 24L, has got a call from icici , brother's salary : 24k/monthly. Have sent to propelld, 16/7: Student rejected propelld due to high int, want loan from ICICI , real risk. (student wants loan but eligibility is lacking severly) 17/7 : have sent his details to icici today, his uncle will be the coapplicant now . 23/7: Doc pending stage at propelld, 27/7 : student called , had issues with Propelld since he doesnt have any coapplicant , his father is no more, so the case passing is difficult 29/7 : 10th Marks: 93.4% 12th Marks: 82.6% JEE Marks : 95 percentile (137 marks) | U78: Yes | V78: Yes | W78: Yes | Z78: Yes | AA78: Risk | AB78: Risk | AG78: Ongoing | AH78: Processing by Icici, Processing by GyanDhan | AI78: Yes | AK78: Yes
A79: 78 | B79: Aashish Tiwari | C79: 9608154327 | D79: PROV260501984 | E79: SSAHE | F79: Yes | G79: Critical | H79: 0.225 | I79: 7.5 | J79: 0.796 | K79: Father | L79: Farmer | M79: 0.96 | N79: EWS | O79: NA | P79: NA | Q79: No | R79: NA | S79: Student is in discussion with Bandhan Bank and requires assistance with a CSIS-supported education loan with collatera | T79: 15/7 : Loan required : 20L Father income : 5L, Income proof : No Low eligibility 16/7: Loan sanctioned by bank , disbursal by next week. | U79: Yes | V79: No | W79: yes | X79: yes | AA79: Control | AB79: Control | AG79: Loan Proccessed/Accepted | AH79: Loan sanctioned by other bank | AJ79: No
A80: 79 | B80: Tawheed Nazeer | C80: 8491900704 | D80: PROV1000000427 | E80: SSAHE | F80: Yes | G80: Critical | H80: 0 | I80: 25 | J80: 0.768 | K80: Father | L80: Fruit Business | M80: 1 | N80: Income Certificate | O80: No | P80: NA | Q80: No | R80: NA | S80: Student is interested in an education loan; however, low CIBIL score is currently affecting eligibility. | T80: Brother's number : 9682379423 : Mudassir : He is ready to be coaplicant but banks have issues to provide loan in J&K. He files the ITR of 5-6L, yearly income of 10Lakhs, he doesn't have the collateral 13/7 : Spoke to the student again, to check if he has got the call from icici, and he hasn't raised it with icici again. 15/7 : Poonawala fincorp called them, have informed the student 29/7: Docs pending with GD. 31/7 : Student is speaking with GD, student is also talking to the loan from local bank and trying from there. | U80: Yes | V80: Yes | W80: No | X80: Yes | Y80: Yes | Z80: Yes | AA80: Risk | AB80: Risk | AG80: Rejected | AH80: Not eligbile for any loan | AI80: Yes | AJ80: No
A81: 80 | B81: Muhammad Shabaz khan | C81: 8989444746 | D81: PROV260503502 | E81: SSAHE | F81: Yes | G81: Critical | H81: 0.075 | I81: 25 | J81: 0.606 | K81: Father | L81: Self Emloyed | M81: 1 | N81: Income Certificate | O81: No | P81: NA | Q81: No | R81: NA | S81: Student reports no communication from ICICI Bank or Propelled. Assistance required | T81: Mother's number : 7972584822 || Have passed on the details to icici 9/7/26 : ICICI had called the student and mother told they would be sharing the documents 16/7: Student will call later. 17/7: Mother said they are not getting loan locally, have dropped the leads. Real risk: Mother highlights they dont have any means to fund the education. Action: Check on the application status after c+2. 17/7 : Pranjal : Yearly income : 1.5 Lakhs, own house. doesnt have registry of the house. Income tax filed : no Have rejected his loan. 23/7: DNP | U81: Yes | AA81: Risk | AB81: Risk | AG81: Rejected | AH81: Not eligbile for any loan | AI81: Yes | AJ81: No | AK81: Yes
A82: 81 | B82: Rohit Kumar sharma | C82: 7645941951 | D82: PROV260600182 | E82: SSAHE | F82: Yes | G82: Critical | H82: 0.075 | I82: 22 | J82: 0.68 | K82: Father | L82: Private Sector | M82: 1 | N82: Salary Slip | O82: No | P82: 750 | Q82: No | R82: NA | S82: Student reports that no communication has been received from any loan partner. | T82: 15/7 : Student voice was too feeble to understand anything, have suggested to call me back . 16/7 : 22L loan , father profession : Mechanic, Yearly income : 2.4L, 23/7: Gyandhan rejected, as father not good enough for co applicant , no collateral, and processing for propelld but chances look slim 31/7: In credit review with PPL. | U82: Yes | V82: No | W82: No | Z82: Yes | AA82: Risk | AB82: Risk | AG82: Ongoing | AH82: Processing by Propelld | AI82: Yes | AJ82: Yes
A83: 82 | B83: Suhani Dhanaji Mahingade | C83: 9822116094 | D83: PROV260501685 | E83: SSAHE | F83: No | G83: Loan not required | H83: 0.205 | I83: 25 | J83: 76.83 | K83: Father | L83: Farmer | M83: 1 | N83: Income Certificate | O83: NA | P83: NA | Q83: No | R83: NA | S83: Student has received a call from ICICI Bank regarding the loan application. | T83: 15/7 : dnp, have shared with SST Loan not required for 1st year , wants it from the second year | U83: No | AA83: Not required | AB83: Not required | AG83: Not required
A84: 83 | B84: Nitesh Kumar | C84: 6202467610 | D84: PROV1000000433 | E84: SSAHE | F84: Yes | G84: Non Critical | H84: 0.075 | I84: 20 | J84: 0.8 | K84: Father | L84: Bussiness | M84: 1.2 | N84: Income Certificate | O84: No | P84: NA | Q84: NA | R84: NA | S84: Student requires assistance with the education loan process. | T84: DNP || 1st year will be paid by the student || He would be requiring loan for the second year. | U84: No | AA84: Not required | AB84: Not required | AG84: Not required | AJ84: No
A85: 84 | B85: Manas Santosh Thikekar | C85: 7058860840 | D85: PROV260602512 | E85: ADYPU | F85: Yes | G85: Critical | H85: 0.075 | I85: 20 | J85: 83 | K85: Brother | L85: Farmer | M85: 0.6 | N85: Income Certificate | O85: No | P85: NA | Q85: No | R85: NA | S85: Waiting for the bank to reach them out Need assitance from us | T85: 7 lakh from SBI, BOB and Union Bank, Agricultural Land works as a colletral , BOB said that ADYPU is not on BOB List , no more income above it. Second update (10/7/26) : BOB would be ready to give 25 lakhs , but would require ADYPU to be listed on BOB list 15/7 : Third update : Student called again for BOB 28/7 : DNP || Student called back, 7.5L , student is taking , non collateral education loan, after education. emi has to be paid+ Gold loan they'll be taking, student is also trying private scholarship. Student went to the bank yesterday for 7.5L from BOB and submitted his documents. Moving from Risk to control. | U85: Yes | V85: NO | W85: NO | X85: NO | Y85: NO | Z85: NO | AA85: Control | AB85: Control | AG85: Ongoing | AH85: Processing at other bank | AJ85: Yes
A86: 85 | B86: Tek Singh | C86: 8295461768 | D86: PROV260503720 | E86: ADYPU | F86: Yes | G86: Critical | H86: 0.225 | I86: 25 | J86: 82.2 | K86: Mother | L86: Farmer | M86: 1 | N86: EWS | O86: No | P86: NA | Q86: No | R86: NA | S86: Waiting for the bank to reach them out Need assitance from us | T86: Its actual case but looking for some other co-applicant. 17/7 : Loan required : 26 , Father : Farmer, Brother : Job , Income for the year : 2L/year / Provided to gyan dhan, rejected Co app - 2 lakh yearly income no ITR or any other income proof no additional co app NOT DOABLE 29/7: Has been suggested to with PM Vidya as is a bright student | U86: Yes | W86: Yes | X86: No | Y86: No | Z86: Yes | AA86: Risk | AB86: Risk | AG86: Rejected | AH86: Processing at other bank | AI86: Yes | AJ86: No | AK86: Yes
A87: 86 | B87: Deepesh Sharma | C87: 8305323128 | D87: PROV260606621 | E87: ADYPU | F87: Yes | G87: Non Critical | H87: 0.075 | I87: 28 | J87: 71.4 | K87: Father | L87: Business | M87: 1 | N87: Income Certificate | O87: No | P87: NA | Q87: Yes | R87: NA | S87: in conversation with SBI Bank already regarding the loan | T87: Student is already in talks with SBI, waiting on updated POL with 17.5% scholarship. Have been sent today with the updation 23/7: In process, collateral so will get | U87: Yes | AA87: Control | AB87: Control | AG87: Ongoing | AH87: Processing at other bank
A88: 87 | B88: Omkar Bhagwat | C88: 7249768047 | D88: PROV1000000251 | E88: ADYPU | F88: Yes | G88: Non Critical | H88: 0.3 | I88: 15.5 | J88: 67 | K88: Father | L88: Business | M88: 1.4 | N88: Income Certificate | O88: Yes | P88: NA | Q88: No | R88: NA | S88: Waiting for the bank to reach them out Need assitance from us | T88: Spoke with him, need to share his details to icici. Had a word with him , he has applied for PM vidyalakshmi 23/7 : wants to talk to gyandhan and propelld, have shared lead. 23/7 : Annual income : 50k, itr filed : yes, coapplicant 31/7: PF paid and loan sanctioned | U88: Yes | AA88: Risk | AB88: Control | AG88: Loan Proccessed/Accepted | AH88: Processing by PM vidyalakshmi, Processing by Propelld, Processing by GyanDhan | AJ88: No | AK88: Yes
A89: 88 | B89: Khushal Gupta | C89: 6377128330 | D89: PROV260505477 | E89: ADYPU | F89: Drop | G89: Critical | H89: 0.275 | I89: 28 | J89: 90.8 | K89: Father | L89: Bussiness | M89: 1.5 | N89: Income Certificate | O89: No | P89: NA | Q89: No | R89: NA | S89: Waiting for the bank to reach them out Need assitance from us | T89: Drop Case - Not moving forward with the Admission || too high fees | U89: Refund | AA89: Refund case | AB89: Refund case | AJ89: Yes
A90: 89 | B90: Harsha M | C90: 9731789273 | D90: PROV1000000434 | E90: SSAHE | F90: Yes | G90: Critical | H90: 0.125 | I90: 25 | J90: 0.71 | K90: Brother | L90: Self Emloyed | M90: 1.2 | N90: Income certificate | O90: Yes | P90: NA | Q90: No | R90: NA | S90: Student's loan application is currently under process with Propelled | T90: 15/7 : dnp, have shared wth sst 23/7: Going on with gyandhan and propelld 28/7 : No one called | U90: Yes | W90: Yes | AA90: Risk | AB90: Risk | AG90: Ongoing | AH90: Processing by Propelld, Processing by GyanDhan | AJ90: No
A91: 90 | B91: Rajeev yadav | C91: 7903653403 | D91: PROV260504859 | E91: SSAHE | F91: Yes | G91: Critical | H91: 0.125 | I91: 20 | J91: 0.68 | K91: Father | L91: Farmer | M91: 7.5 | N91: EWS | O91: NA | P91: NA | Q91: No | R91: NA | S91: Student's loan application with ICICI Bank was declined due to insufficient father's income as per eligibility criteria. | T91: 13/7 : Father name - Manu Yadav Occupation - Transport Bussiness Annual income -6lpa Itr - Filed this year of 7.5 lpa Sharing it to propelld, since cibil is 685 for the coapplicant 16/7 : Appid - 3681 - Propelld 23/7: Processing with Propelld , sharing with gyandhan 28/7 : Student called, connecting him with gyandhan again | U91: Yes | W91: Yes | Y91: Yes | AA91: Risk | AB91: Risk | AG91: Ongoing | AH91: Processing by Propelld | AJ91: No
A92: 91 | B92: Jhansi Urmila | C92: 9949273339 | D92: PROV1000001045 | E92: SSAHE | F92: Yes | G92: Critical | H92: 0.44 | I92: 25 | J92: 0.83 | K92: Father | L92: Business | M92: 1.5 | N92: Income Certificate | O92: No | P92: 700 | Q92: No | R92: NA | S92: Student reports no communication from ICICI Bank or Propelled. Assistance required | T92: DNP 10/7/26: Total loan required , father's profession : business ,Yearly income : 6L , No ITR. Have to share the details with ICICI and Propeld 21/7: Rejected propelld due to high rate of int, trying in other banks. | U92: Yes | V92: Yes | W92: Yes | AA92: Control | AB92: Control | AG92: Ongoing | AH92: Processing at other bank | AJ92: No
A93: 92 | B93: Dilkhush Kumar | C93: 7763994601 | D93: PROV260503046 | E93: SSAHE | F93: Yes | G93: Critical | H93: 0.075 | I93: 18 | J93: 0.726 | K93: Father | L93: Factory worker (construction) | M93: 1.5 | N93: Income certificate | O93: NA | P93: NA | Q93: No | R93: NA | S93: Student requires assistance with the education loan process. | T93: Annual Income : 3.6 Lakhs || Form has been filed as sent by us from icici team. Prefer it for GYAN DHAN 23/7: Going on with Credilla and GyanDhan through Gyandhan, closed in ICICI. 28/7 : Student called as he had few doubts related to the processing fees | U93: Yes | Z93: Yes | AA93: Control | AB93: Control | AG93: Ongoing | AH93: Loan sanctioned by gyan dhan | AJ93: No
A94: 93 | B94: ankit kumar(1) | C94: 9229246323 | D94: PROV1000000439 | E94: SSAHE | F94: Drop | G94: Critical | H94: 0.075 | I94: 14 | J94: 0.742 | K94: Father | L94: House wife (rents) | M94: 1.5 | N94: Income Certificate | O94: NA | P94: NA | Q94: No | R94: NA | S94: Student requires assistance with the education loan process. | T94: DNP 9/7/26 : DNP 10/7/26 : Mother' is a housewife, no income documents are available : 74.2% in 12th and JEE : XX. Not fit for loan Father has passed away, and the brother requested if we can hold the fees of 2 years till 2 year. " - 30/7 : Student doesnt want the refund, suggested him PM vidyalakshmi and poor situation, father is no more and 2 brothers, doesnt have any collateral | U94: Yes | AA94: Risk | AB94: Risk | AG94: Rejected | AH94: Not eligbile for any loan | AJ94: Yes
A95: 94 | B95: Suhani pandey | C95: 7307958714 | D95: PROV260613731 | E95: SSAHE | F95: Drop | G95: Critical | H95: 0.15 | I95: 23 | J95: 0.81 | K95: Father | L95: Driver (Pvt job) | M95: 1.5 | N95: EWS | O95: NA | P95: NA | Q95: No | R95: NA | S95: Student requires assistance with the education loan process. | T95: Have forwarded the contact to study4buddy. She wants the EMI to be paid after 4 years and not now. | U95: Refund | AA95: Refund case | AB95: Refund case | AG95: Rejected | AH95: Not eligbile for any loan | AJ95: Yes
A96: 95 | B96: Shubham kumar gupta | C96: 8956762898 | D96: PROV260503782 | E96: SSAHE | F96: Yes | G96: Critical | H96: 0.15 | I96: 25 | J96: 0.728 | K96: Father | L96: Salaried | M96: 2 | N96: Salary Slip | O96: Yes | P96: NA | Q96: No | R96: NA | S96: Student reports that no lending partner has contacted them. Follow-up required. | T96: 16/7:No calls have been received by ICICI Bank. He has total income of 3L/annum, salary (2L) + 1L ( home rent ) and all. 27/7 : Student wanted help with PM vidyalakshmi , have logged in his account and doing it 29/7 : Have spoken to the student, will set up a meeting with Vishwa, for interview | U96: Yes | AA96: Risk | AB96: Risk | AG96: Rejected | AH96: Not eligbile for any loan | AI96: Yes | AJ96: Yes | AK96: Yes
A97: 96 | B97: Atanu Nath | C97: 7628928018 | D97: PROV260502314 | E97: SSAHE | F97: Yes | G97: Critical | H97: 0.125 | I97: 25 | J97: 0.77 | K97: Father | L97: House wife/ Teacher | M97: 2.4 | N97: Income Certificate | O97: NA | P97: NA | Q97: No | R97: NA | S97: Student is currently not engaged with any lending institution for an education loan. | T97: Haven't received the call from icici bank, have forwarded the details. 10/7 : Atanu has received the call from ICICI bank. 20/7 : Have got call from icici and everywhere. Buddy4Study rejected the loan , in process with gyan dhan and poonawala 24/7 : Spoke to the student , he is worried about the EMI starting from first month, have informed him that it would be interest that would be starting , connected gyan dhan on the same call , and cleared him. Gyan dhan mentioned that Atanu has to share the bank statement of the sister and now he would be sending the bank statement. 28/7 : Sanctioned by GyanDhan | U97: Yes | V97: Yes | W97: Yes | X97: Yes | Y97: Yes | Z97: Yes | AA97: Risk | AB97: Control | AG97: Ongoing | AH97: Loan sanctioned by gyan dhan | AJ97: No
A98: 97 | B98: junaid maruf | C98: 6900724625 | D98: PROV260502382 | E98: SSAHE | F98: Yes | G98: Non Critical | H98: 0.225 | I98: 15 | J98: 0.792 | K98: Mother | L98: Farmer | M98: 3 | N98: EWS | O98: NA | P98: NA | Q98: No | R98: NA | S98: Student is in discussion with Axis Bank and requires additional support to complete the loan process | T98: 16/7:Might require in the near future, he is already processing with SBI. 29/7: DNP | U98: Yes | V98: No | W98: No | AA98: Control | AB98: Control | AG98: Ongoing | AH98: Processing at other bank | AJ98: No
A99: 98 | B99: Ashish Kumar | C99: 7294180072 | D99: PROV260505005 | E99: SSAHE | F99: Yes | G99: Critical | H99: 0.125 | I99: 23 | J99: 0.76 | K99: Father | L99: Shop owner | M99: 3 | N99: Income Certificate | O99: NA | P99: NA | Q99: No | R99: NA | S99: Student has not received the required loan assistance and requests support. | T99: Get him called on monday 17/7 : Income : 5L, father profession : shop Loan req : 20L, 27/7: ITR pending to be filed, got the bank statement | U99: Yes | V99: No | W99: yes | X99: No | Y99: yes | AA99: Control | AB99: Control | AG99: Ongoing | AH99: Processing by Poonawala Fincorp, Processing by GyanDhan | AJ99: No
A100: 99 | B100: Dipak kumar | C100: 6203899217 | D100: PROV260600907 | E100: SSAHE | F100: Yes | G100: Critical | H100: 0.15 | I100: 20 | J100: 0.8 | K100: Father | L100: Private job | M100: 3 | N100: Income Certificate | O100: No | P100: Good | Q100: No | R100: NA | S100: Student requires assistance with the education loan process. | T100: DNP *15/7/26: Student starting to looks for loans, have shared their profile to propelled 21/7: Student gave feedback to propelld, not intrested. | U100: Yes | W100: Yes | Z100: Yes | AA100: Control | AB100: Control | AG100: Not even started | AH100: Processing by GyanDhan | AJ100: No | AL100: Student rejected propelled due to high int
...

Sheet 02_Configuration
A1: uGSOT LOAN OPERATIONS — CONFIGURATION
A2: Edit this sheet only to add vendors, stages, mappings. Do not edit formulas on other sheets.
A4: VENDORS
A5: VendorID | B5: VendorName | C5: MasterCol | D5: MasterHeader | E5: Active | F5: SortOrder | G5: StatusToken
A6: 1 | B6: ICICI | C6: V | D6: Shared to ICICI | E6: Yes | F6: 1 | G6: Processing by Icici|Loan sanctioned by Icici
A7: 2 | B7: Propelld | C7: W | D7: Shared to Propelld | E7: Yes | F7: 2 | G7: Processing by Propelld|Loan sanctioned by Propelld|Loan Sanctioned by Proplld
A8: 3 | B8: Study4Buddy | C8: X | D8: Shared to Study4Buddy | E8: Yes | F8: 3 | G8: Processing by Study4Buddy
A9: 4 | B9: Poonawala Fincorp | C9: Y | D9: Shared to Poonawala Fincorp | E9: Yes | F9: 4 | G9: Processing by Poonawala Fincorp
A10: 5 | B10: GyanDhan | C10: Z | D10: Shared to GyanDhan | E10: Yes | F10: 5 | G10: Processing by GyanDhan|Loan sanctioned by gyan dhan
A11: 6 | B11: PM Vidyalakshmi | D11: Special Vidyalaksmi / Loan Status | E11: Yes | F11: 6 | G11: Processing by PM vidyalakshmi
A12: 7 | B12: Other Bank | D12: Loan Status token | E12: Yes | F12: 7 | G12: Processing at other bank|Loan sanctioned by other bank
A13: 8 | B13: State Scheme | D13: Loan Status token | E13: Yes | F13: 8 | G13: State Scheme
A14: 9 | B14: Auxilo | E14: No | F14: 9
A15: 10 | B15: InCred | E15: No | F15: 10
A18: CANONICAL STAGES (Funnel Order)
A19: StageID | B19: StageName | C19: FunnelOrder | D19: FunnelCore | E19: DashboardKPI | F19: Color
A20: 1 | B20: Need Loan | C20: 1 | D20: Yes | E20: Yes | F20: E31C24
A21: 2 | B21: Interested | C21: 2 | D21: No | E21: No | F21: 666666
A22: 3 | B22: Loan Started | C22: 3 | D22: Yes | E22: Yes | F22: 333333
A23: 4 | B23: Documents Pending | C23: 4 | D23: Yes | E23: Yes | F23: B45309
A24: 5 | B24: Vendor Assigned | C24: 5 | D24: No | E24: No | F24: 666666
A25: 6 | B25: Processing | C25: 6 | D25: Yes | E25: Yes | F25: 1D4ED8
A26: 7 | B26: Approved | C26: 7 | D26: Yes | E26: Yes | F26: 1B7A4E
A27: 8 | B27: Sanctioned | C27: 8 | D27: Yes | E27: No | F27: 1B7A4E
A28: 9 | B28: Disbursed | C28: 9 | D28: Yes | E28: Yes | F28: 1B7A4E
A29: 10 | B29: Completed | C29: 10 | D29: No | E29: No | F29: 111111
A30: 11 | B30: Rejected | C30: 90 | D30: No | E30: Yes | F30: E31C24
A31: 12 | B31: Refund | C31: 91 | D31: No | E31: No | F31: 6B6B6B
... A34: 15 | B34: Unclassified | C34: 99 | D34: No | E34: No | F34: 6B6B6B
A38: CAMPUS NORMALIZATION | D38: AGEING BUCKETS
A39: RawValue | B39: Normalized | C39: Active | D39: Bucket | E39: MinDays | F39: MaxDays
A40: SSAHE | B40: SSAHE | C40: Yes | D40: 0–3 Days | E40: 0 | F40: 3
A41: SSHAE | B41: SSAHE | C41: Yes | D41: 4–7 Days | E41: 4 | F41: 7
A42: ssHAE | B42: SSAHE | C42: Yes | D42: 8–15 Days | E42: 8 | F42: 15
A43: ssahe | B43: SSAHE | C43: Yes | D43: 16–30 Days | E43: 16 | F43: 30
A44: ADYPU | B44: ADYPU | C44: Yes | D44: 30+ Days | E44: 31 | F44: 9999
D45: Unknown | E45: -1 | F45: -1
A48: REASON BUCKETS (keyword → bucket) | D48: RISK FLAGS
A49: Keyword | B49: Bucket | D49: FlagName | E49: MasterCol | F49: YesValue
A50: DNP | B50: Unreachable / DNP | D50: Need FLDG | E50: AI | F50: Yes
A51: unreachable | B51: Unreachable / DNP | D51: Need Vishwa Attention | E51: AJ | F51: Yes
A52: interest | B52: High Interest / Terms | D52: Need Vidyalakshmi | E52: AK | F52: Yes
A53: eligib | B53: Eligibility / Income | D53: Critical | E53: G | F53: Critical
A54: income | B54: Eligibility / Income | D54: Refund | E54: U | F54: Refund
A55: Low | B55: Eligibility / Income | D55: Risk Case | E55: AA | F55: Risk
A56: start | B56: Process Yet to Start
A57: Newer | B57: Process Yet to Start
A58: Fresh | B58: Process Yet to Start
A59: Not sure | B59: Undecided
A60: reject | B60: Rejected Elsewhere
A61: SBI | B61: Rejected Elsewhere
A62: misunderstand | B62: Miscommunication
A63: automatic | B63: Miscommunication
A64: waiting | B64: Family / Dependency
A65: sister | B65: Family / Dependency
A66: father | B66: Family / Dependency
A67: call | B67: Bank Communication
... A70: info | B70: Insufficient Info
A74: BRAND COLORS
A75: Primary Red | B75: #E31C24
A76: Black | B76: #111111
A77: Background | B77: #F6F6F6
A78: Border | B78: #E5E5E5
A80: DASHBOARD FILTER DEFAULTS
A81: FilterAllToken | B81: (All)
A82: AsOfDate | B82: 46237
A83: AdmissionCycle | B83: 2026 Cycle

Sheet 03_Helper
A1: RowNum | B1: StudentKey | C1: StudentName | D1: Mobile | E1: ProvisionalID | F1: CampusRaw | G1: Campus | H1: LoanRequired | I1: NeedLoanSST | J1: Criticality | K1: Scholarship | L1: SharedICICI | M1: SharedPropelld | N1: SharedStudy4Buddy | O1: SharedPoonawala | P1: SharedGyanDhan | Q1: VendorCount | R1: DuplicateVendorFlag | S1: VendorsApplied | T1: PrimaryVendor | U1: CaseStatus | V1: LoanStageRaw | W1: LoanStatusRaw | X1: CanonicalStage | Y1: ApprovalStatus | Z1: DisbursementStatus | AA1: RiskCategory | AB1: CriticalFlag | AC1: NeedFLDG | AD1: NeedVidyalakshmi | AE1: NeedVishwa | AF1: ReasonRaw | AG1: ReasonBucket | AH1: TentativeDate | AI1: PendingDays | AJ1: AgeingBucket | AK1: IsLoanPipeline | AL1: PranjalComments | AM1: SSTRemarks | AN1: LoanAmt | AO1: Income | AP1: ProcessingByICICI | AQ1: ProcessingByPropelld | AR1: ProcessingByGyanDhan | AS1: ProcessingByVidya | AT1: ProcessingByOther | AU1: IsSanctioned | AV1: IsDocsPending | AW1: IsRejectedStatus
A2: =IF('01_Master_Data'!B2="","",1) | B2: =IF('01_Master_Data'!B2="","",IF('01_Master_Data'!C2<>"","MOB|"&TEXT('01_Master_Data'!C2,"0"),IF('01_Master_Data'!D2<>"","PID|"&TRIM('01_Master_Data'!D2&""),""))) | C2: =IF('01_Master_Data'!B2="","",'01_Master_Data'!B2) | D2: =IF('01_Master_Data'!B2="","",'01_Master_Data'!C2) | E2: =IF('01_Master_Data'!B2="","",'01_Master_Data'!D2) | F2: =IF('01_Master_Data'!B2="","",'01_Master_Data'!E2) | G2: =IF('01_Master_Data'!B2="","",IFERROR(VLOOKUP(TRIM('01_Master_Data'!E2&""),'02_Configuration'!$A$40:$B$44,2,FALSE),UPPER(TRIM('01_Master_Data'!E2&"")))) | H2: =IF('01_Master_Data'!B2="","",IF('01_Master_Data'!U2="","",TRIM('01_Master_Data'!U2&""))) | I2: =IF('01_Master_Data'!B2="","",TRIM('01_Master_Data'!F2&"")) | J2: =IF('01_Master_Data'!B2="","",TRIM('01_Master_Data'!G2&"")) | K2: =IF('01_Master_Data'!B2="","",'01_Master_Data'!H2) | L2: =IF('01_Master_Data'!B2="","",IF(LOWER(TRIM('01_Master_Data'!V2&""))="yes",1,0)) | M2: =IF('01_Master_Data'!B2="","",IF(LOWER(TRIM('01_Master_Data'!W2&""))="yes",1,0)) | N2: =IF('01_Master_Data'!B2="","",IF(LOWER(TRIM('01_Master_Data'!X2&""))="yes",1,0)) | O2: =IF('01_Master_Data'!B2="","",IF(LOWER(TRIM('01_Master_Data'!Y2&""))="yes",1,0)) | P2: =IF('01_Master_Data'!B2="","",IF(LOWER(TRIM('01_Master_Data'!Z2&""))="yes",1,0)) | Q2: =IF(A2="","",L2+M2+N2+O2+P2) | R2: =IF(A2="","",IF(Q2>1,"Yes","No")) | S2: =IF(A2="","",TEXTJOIN(", ",TRUE,IF(L2=1,"ICICI",""),IF(M2=1,"Propelld",""),IF(N2=1,"Study4Buddy",""),IF(O2=1,"Poonawala Fincorp",""),IF(P2=1,"GyanDhan",""))) | T2: =IF(A2="","",IF(L2=1,"ICICI",IF(M2=1,"Propelld",IF(P2=1,"GyanDhan",IF(N2=1,"Study4Buddy",IF(O2=1,"Poonawala Fincorp",IF(ISNUMBER(SEARCH("GyanDhan",W2&"")),"GyanDhan",IF(ISNUMBER(SEARCH("Icici",W2&"")),"ICICI",IF(ISNUMBER(SEARCH("Propelld",W2&"")),"Propelld",IF(ISNUMBER(SEARCH("vidyalakshmi",LOWER(W2&"")),"PM Vidyalakshmi","—")))))))))) | U2: =IF(A2="","",TRIM('01_Master_Data'!AA2&"")) | V2: =IF(A2="","",TRIM('01_Master_Data'!AG2&"")) | W2: =IF(A2="","",TRIM('01_Master_Data'!AH2&"")) | X2: =IF(A2="","",IF(OR(LOWER(H2)="refund",LOWER(U2)="refund case"),"Refund",IF(OR(LOWER(H2)="dnp",LOWER(U2)="dnp"),"DNP",IF(OR(LOWER(V2)="disbursed",ISNUMBER(SEARCH("Disbursed",W2&""))),"Disbursed",IF(OR(LOWER(V2)="loan proccessed/accepted",ISNUMBER(SEARCH("sanctioned",LOWER(W2&"")))),"Sanctioned",IF(OR(LOWER(V2)="rejected",ISNUMBER(SEARCH("Not eligbile",W2&"")),ISNUMBER(SEARCH("Not eligible",W2&""))),"Rejected",IF(ISNUMBER(SEARCH("Docs Pending",W2&"")),"Documents Pending",IF(AND(LOWER(H2)="yes",LOWER(V2)="ongoing"),"Processing",IF(AND(LOWER(H2)="yes",Q2>0,OR(V2="",LOWER(V2)="not even started")),"Vendor Assigned",IF(AND(LOWER(H2)="yes",LOWER(V2)="not even started"),"Need Loan",IF(LOWER(H2)="yes","Loan Started",IF(LOWER(H2)="not sure","Interested",IF(OR(LOWER(H2)="no",LOWER(V2)="not required"),"Not Required","Unclassified"))))))))))))) | Y2: =IF(A2="","",IF(OR(X2="Sanctioned",X2="Disbursed",X2="Approved"),"Approved",IF(X2="Rejected","Rejected",IF(OR(X2="Processing",X2="Documents Pending",X2="Vendor Assigned"),"In Progress",IF(X2="Need Loan","Pending Start","—")))) | Z2: =IF(A2="","",IF(X2="Disbursed","Disbursed",IF(X2="Sanctioned","Sanctioned - Awaiting Disbursement","Not Disbursed"))) | AA2: =IF(A2="","",IF(LOWER(TRIM('01_Master_Data'!AI2&""))="yes","Need FLDG",IF(LOWER(TRIM('01_Master_Data'!AK2&""))="yes","Need Vidyalakshmi",IF(LOWER(TRIM('01_Master_Data'!AJ2&""))="yes","Need Review",IF(LOWER(J2)="critical","Critical",IF(LOWER(U2)="risk","Risk Case",IF(X2="Refund","Refund","Normal"))))))) | AB2: =IF(A2="","",IF(OR(LOWER(J2)="critical",LOWER(TRIM('01_Master_Data'!AI2&""))="yes",LOWER(TRIM('01_Master_Data'!AK2&""))="yes",LOWER(U2)="risk"),"Yes","No")) | AC2: =IF(A2="","",IF(LOWER(TRIM('01_Master_Data'!AI2&""))="yes","Yes","No")) | AD2: =IF(A2="","",IF(LOWER(TRIM('01_Master_Data'!AK2&""))="yes","Yes","No")) | AE2: =IF(A2="","",IF(LOWER(TRIM('01_Master_Data'!AJ2&""))="yes","Yes","No")) | AF2: =IF(A2="","",TRIM('01_Master_Data'!AL2&"")) | AG2: =IF(A2="","",IF(AF2="","—",IF(ISNUMBER(SEARCH("DNP",AF2)),"Unreachable / DNP",IF(ISNUMBER(SEARCH("interest",LOWER(AF2))),"High Interest / Terms",IF(OR(ISNUMBER(SEARCH("eligib",LOWER(AF2))),ISNUMBER(SEARCH("income",LOWER(AF2)))),"Eligibility / Income",IF(OR(ISNUMBER(SEARCH("start",LOWER(AF2))),ISNUMBER(SEARCH("Newer",AF2)),ISNUMBER(SEARCH("Will start",AF2))),"Process Yet to Start",IF(ISNUMBER(SEARCH("sure",LOWER(AF2))),"Undecided",IF(OR(ISNUMBER(SEARCH("reject",LOWER(AF2))),ISNUMBER(SEARCH("SBI",AF2))),"Rejected Elsewhere",IF(ISNUMBER(SEARCH("call",LOWER(AF2))),"Bank Communication",IF(OR(ISNUMBER(SEARCH("father",LOWER(AF2))),ISNUMBER(SEARCH("sister",LOWER(AF2)))),"Family / Dependency","Other")))))))))) | AH2: =IF(A2="","",'01_Master_Data'!AC2) | AI2: =IF(A2="","",IF(OR(AH2="",NOT(ISNUMBER(AH2))),"",MAX(0,'02_Configuration'!$B$82-AH2))) | AJ2: =IF(A2="","",IF(AI2="","Unknown",IF(AI2<=3,"0–3 Days",IF(AI2<=7,"4–7 Days",IF(AI2<=15,"8–15 Days",IF(AI2<=30,"16–30 Days","30+ Days")))))) | AK2: =IF(A2="","",IF(LOWER(H2)="yes","Yes","No")) | AL2: =IF(A2="","",'01_Master_Data'!T2) | AM2: =IF(A2="","",'01_Master_Data'!S2) | AN2: =IF(A2="","",'01_Master_Data'!I2) | AO2: =IF(A2="","",'01_Master_Data'!M2) | AP2: =IF(A2="","",IF(ISNUMBER(SEARCH("Icici",W2&"")),1,0)) | AQ2: =IF(A2="","",IF(ISNUMBER(SEARCH("Propelld",W2&"")),1,0)) | AR2: =IF(A2="","",IF(ISNUMBER(SEARCH("GyanDhan",W2&"")),1,0)) | AS2: =IF(A2="","",IF(ISNUMBER(SEARCH("vidyalakshmi",LOWER(W2&""))),1,0)) | AT2: =IF(A2="","",IF(ISNUMBER(SEARCH("other bank",LOWER(W2&""))),1,0)) | AU2: =IF(A2="","",IF(ISNUMBER(SEARCH("sanctioned",LOWER(W2&""))),1,0)) | AV2: =IF(A2="","",IF(ISNUMBER(SEARCH("Docs Pending",W2&"")),1,0)) | AW2: =IF(A2="","",IF(OR(X2="Rejected",ISNUMBER(SEARCH("Not eligbile",W2&""))),1,0))
A3: =IF('01_Master_Data'!B3="","",2) | B3: =IF('01_Master_Data'!B3="","",IF('01_Master_Data'!C3<>"","MOB|"&TEXT('01_Master_Data'!C3,"0"),IF('01_Master_Data'!D3<>"","PID|"&TRIM('01_Master_Data'!D3&""),""))) | C3: =IF('01_Master_Data'!B3="","",'01_Master_Data'!B3) | D3: =IF('01_Master_Data'!B3="","",'01_Master_Data'!C3) | E3: =IF('01_Master_Data'!B3="","",'01_Master_Data'!D3) | F3: =IF('01_Master_Data'!B3="","",'01_Master_Data'!E3) | G3: =IF('01_Master_Data'!B3="","",IFERROR(VLOOKUP(TRIM('01_Master_Data'!E3&""),'02_Configuration'!$A$40:$B$44,2,FALSE),UPPER(TRIM('01_Master_Data'!E3&"")))) | H3: =IF('01_Master_Data'!B3="","",IF('01_Master_Data'!U3="","",TRIM('01_Master_Data'!U3&""))) | I3: =IF('01_Master_Data'!B3="","",TRIM('01_Master_Data'!F3&"")) | J3: =IF('01_Master_Data'!B3="","",TRIM('01_Master_Data'!G3&"")) | K3: =IF('01_Master_Data'!B3="","",'01_Master_Data'!H3) | L3: =IF('01_Master_Data'!B3="","",IF(LOWER(TRIM('01_Master_Data'!V3&""))="yes",1,0)) | M3: =IF('01_Master_Data'!B3="","",IF(LOWER(TRIM('01_Master_Data'!W3&""))="yes",1,0)) | N3: =IF('01_Master_Data'!B3="","",IF(LOWER(TRIM('01_Master_Data'!X3&""))="yes",1,0)) | O3: =IF('01_Master_Data'!B3="","",IF(LOWER(TRIM('01_Master_Data'!Y3&""))="yes",1,0)) | P3: =IF('01_Master_Data'!B3="","",IF(LOWER(TRIM('01_Master_Data'!Z3&""))="yes",1,0)) | Q3: =IF(A3="","",L3+M3+N3+O3+P3) | R3: =IF(A3="","",IF(Q3>1,"Yes","No")) | S3: =IF(A3="","",TEXTJOIN(", ",TRUE,IF(L3=1,"ICICI",""),IF(M3=1,"Propelld",""),IF(N3=1,"Study4Buddy",""),IF(O3=1,"Poonawala Fincorp",""),IF(P3=1,"GyanDhan",""))) | T3: =IF(A3="","",IF(L3=1,"ICICI",IF(M3=1,"Propelld",IF(P3=1,"GyanDhan",IF(N3=1,"Study4Buddy",IF(O3=1,"Poonawala Fincorp",IF(ISNUMBER(SEARCH("GyanDhan",W3&"")),"GyanDhan",IF(ISNUMBER(SEARCH("Icici",W3&"")),"ICICI",IF(ISNUMBER(SEARCH("Propelld",W3&"")),"Propelld",IF(ISNUMBER(SEARCH("vidyalakshmi",LOWER(W3&"")),"PM Vidyalakshmi","—")))))))))) | U3: =IF(A3="","",TRIM('01_Master_Data'!AA3&"")) | V3: =IF(A3="","",TRIM('01_Master_Data'!AG3&"")) | W3: =IF(A3="","",TRIM('01_Master_Data'!AH3&"")) | X3: =IF(A3="","",IF(OR(LOWER(H3)="refund",LOWER(U3)="refund case"),"Refund",IF(OR(LOWER(H3)="dnp",LOWER(U3)="dnp"),"DNP",IF(OR(LOWER(V3)="disbursed",ISNUMBER(SEARCH("Disbursed",W3&""))),"Disbursed",IF(OR(LOWER(V3)="loan proccessed/accepted",ISNUMBER(SEARCH("sanctioned",LOWER(W3&"")))),"Sanctioned",IF(OR(LOWER(V3)="rejected",ISNUMBER(SEARCH("Not eligbile",W3&"")),ISNUMBER(SEARCH("Not eligible",W3&""))),"Rejected",IF(ISNUMBER(SEARCH("Docs Pending",W3&"")),"Documents Pending",IF(AND(LOWER(H3)="yes",LOWER(V3)="ongoing"),"Processing",IF(AND(LOWER(H3)="yes",Q3>0,OR(V3="",LOWER(V3)="not even started")),"Vendor Assigned",IF(AND(LOWER(H3)="yes",LOWER(V3)="not even started"),"Need Loan",IF(LOWER(H3)="yes","Loan Started",IF(LOWER(H3)="not sure","Interested",IF(OR(LOWER(H3)="no",LOWER(V3)="not required"),"Not Required","Unclassified"))))))))))))) | Y3: =IF(A3="","",IF(OR(X3="Sanctioned",X3="Disbursed",X3="Approved"),"Approved",IF(X3="Rejected","Rejected",IF(OR(X3="Processing",X3="Documents Pending",X3="Vendor Assigned"),"In Progress",IF(X3="Need Loan","Pending Start","—")))) | Z3: =IF(A3="","",IF(X3="Disbursed","Disbursed",IF(X3="Sanctioned","Sanctioned - Awaiting Disbursement","Not Disbursed"))) | AA3: =IF(A3="","",IF(LOWER(TRIM('01_Master_Data'!AI3&""))="yes","Need FLDG",IF(LOWER(TRIM('01_Master_Data'!AK3&""))="yes","Need Vidyalakshmi",IF(LOWER(TRIM('01_Master_Data'!AJ3&""))="yes","Need Review",IF(LOWER(J3)="critical","Critical",IF(LOWER(U3)="risk","Risk Case",IF(X3="Refund","Refund","Normal"))))))) | AB3: =IF(A3="","",IF(OR(LOWER(J3)="critical",LOWER(TRIM('01_Master_Data'!AI3&""))="yes",LOWER(TRIM('01_Master_Data'!AK3&""))="yes",LOWER(U3)="risk"),"Yes","No")) | AC3: =IF(A3="","",IF(LOWER(TRIM('01_Master_Data'!AI3&""))="yes","Yes","No")) | AD3: =IF(A3="","",IF(LOWER(TRIM('01_Master_Data'!AK3&""))="yes","Yes","No")) | AE3: =IF(A3="","",IF(LOWER(TRIM('01_Master_Data'!AJ3&""))="yes","Yes","No")) | AF3: =IF(A3="","",TRIM('01_Master_Data'!AL3&"")) | AG3: =IF(A3="","",IF(AF3="","—",IF(ISNUMBER(SEARCH("DNP",AF3)),"Unreachable / DNP",IF(ISNUMBER(SEARCH("interest",LOWER(AF3))),"High Interest / Terms",IF(OR(ISNUMBER(SEARCH("eligib",LOWER(AF3))),ISNUMBER(SEARCH("income",LOWER(AF3)))),"Eligibility / Income",IF(OR(ISNUMBER(SEARCH("start",LOWER(AF3))),ISNUMBER(SEARCH("Newer",AF3)),ISNUMBER(SEARCH("Will start",AF3))),"Process Yet to Start",IF(ISNUMBER(SEARCH("sure",LOWER(AF3))),"Undecided",IF(OR(ISNUMBER(SEARCH("reject",LOWER(AF3))),ISNUMBER(SEARCH("SBI",AF3))),"Rejected Elsewhere",IF(ISNUMBER(SEARCH("call",LOWER(AF3))),"Bank Communication",IF(OR(ISNUMBER(SEARCH("father",LOWER(AF3))),ISNUMBER(SEARCH("sister",LOWER(AF3)))),"Family / Dependency","Other")))))))))) | AH3: =IF(A3="","",'01_Master_Data'!AC3) | AI3: =IF(A3="","",IF(OR(AH3="",NOT(ISNUMBER(AH3))),"",MAX(0,'02_Configuration'!$B$82-AH3))) | AJ3: =IF(A3="","",IF(AI3="","Unknown",IF(AI3<=3,"0–3 Days",IF(AI3<=7,"4–7 Days",IF(AI3<=15,"8–15 Days",IF(AI3<=30,"16–30 Days","30+ Days")))))) | AK3: =IF(A3="","",IF(LOWER(H3)="yes","Yes","No")) | AL3: =IF(A3="","",'01_Master_Data'!T3) | AM3: =IF(A3="","",'01_Master_Data'!S3) | AN3: =IF(A3="","",'01_Master_Data'!I3) | AO3: =IF(A3="","",'01_Master_Data'!M3) | AP3: =IF(A3="","",IF(ISNUMBER(SEARCH("Icici",W3&"")),1,0)) | AQ3: =IF(A3="","",IF(ISNUMBER(SEARCH("Propelld",W3&"")),1,0)) | AR3: =IF(A3="","",IF(ISNUMBER(SEARCH("GyanDhan",W3&"")),1,0)) | AS3: =IF(A3="","",IF(ISNUMBER(SEARCH("vidyalakshmi",LOWER(W3&""))),1,0)) | AT3: =IF(A3="","",IF(ISNUMBER(SEARCH("other bank",LOWER(W3&""))),1,0)) | AU3: =IF(A3="","",IF(ISNUMBER(SEARCH("sanctioned",LOWER(W3&""))),1,0)) | AV3: =IF(A3="","",IF(ISNUMBER(SEARCH("Docs Pending",W3&"")),1,0)) | AW3: =IF(A3="","",IF(OR(X3="Rejected",ISNUMBER(SEARCH("Not eligbile",W3&""))),1,0))
A4: =IF('01_Master_Data'!B4="","",3) | B4: =IF('01_Master_Data'!B4="","",IF('01_Master_Data'!C4<>"","MOB|"&TEXT('01_Master_Data'!C4,"0"),IF('01_Master_Data'!D4<>"","PID|"&TRIM('01_Master_Data'!D4&""),""))) | C4: =IF('01_Master_Data'!B4="","",'01_Master_Data'!B4) | D4: =IF('01_Master_Data'!B4="","",'01_Master_Data'!C4) | E4: =IF('01_Master_Data'!B4="","",'01_Master_Data'!D4) | F4: =IF('01_Master_Data'!B4="","",'01_Master_Data'!E4) | G4: =IF('01_Master_Data'!B4="","",IFERROR(VLOOKUP(TRIM('01_Master_Data'!E4&""),'02_Configuration'!$A$40:$B$44,2,FALSE),UPPER(TRIM('01_Master_Data'!E4&"")))) | H4: =IF('01_Master_Data'!B4="","",IF('01_Master_Data'!U4="","",TRIM('01_Master_Data'!U4&""))) | I4: =IF('01_Master_Data'!B4="","",TRIM('01_Master_Data'!F4&"")) | J4: =IF('01_Master_Data'!B4="","",TRIM('01_Master_Data'!G4&"")) | K4: =IF('01_Master_Data'!B4="","",'01_Master_Data'!H4) | L4: =IF('01_Master_Data'!B4="","",IF(LOWER(TRIM('01_Master_Data'!V4&""))="yes",1,0)) | M4: =IF('01_Master_Data'!B4="","",IF(LOWER(TRIM('01_Master_Data'!W4&""))="yes",1,0)) | N4: =IF('01_Master_Data'!B4="","",IF(LOWER(TRIM('01_Master_Data'!X4&""))="yes",1,0)) | O4: =IF('01_Master_Data'!B4="","",IF(LOWER(TRIM('01_Master_Data'!Y4&""))="yes",1,0)) | P4: =IF('01_Master_Data'!B4="","",IF(LOWER(TRIM('01_Master_Data'!Z4&""))="yes",1,0)) | Q4: =IF(A4="","",L4+M4+N4+O4+P4) | R4: =IF(A4="","",IF(Q4>1,"Yes","No")) | S4: =IF(A4="","",TEXTJOIN(", ",TRUE,IF(L4=1,"ICICI",""),IF(M4=1,"Propelld",""),IF(N4=1,"Study4Buddy",""),IF(O4=1,"Poonawala Fincorp",""),IF(P4=1,"GyanDhan",""))) | T4: =IF(A4="","",IF(L4=1,"ICICI",IF(M4=1,"Propelld",IF(P4=1,"GyanDhan",IF(N4=1,"Study4Buddy",IF(O4=1,"Poonawala Fincorp",IF(ISNUMBER(SEARCH("GyanDhan",W4&"")),"GyanDhan",IF(ISNUMBER(SEARCH("Icici",W4&"")),"ICICI",IF(ISNUMBER(SEARCH("Propelld",W4&"")),"Propelld",IF(ISNUMBER(SEARCH("vidyalakshmi",LOWER(W4&"")),"PM Vidyalakshmi","—")))))))))) | U4: =IF(A4="","",TRIM('01_Master_Data'!AA4&"")) | V4: =IF(A4="","",TRIM('01_Master_Data'!AG4&"")) | W4: =IF(A4="","",TRIM('01_Master_Data'!AH4&"")) | X4: =IF(A4="","",IF(OR(LOWER(H4)="refund",LOWER(U4)="refund case"),"Refund",IF(OR(LOWER(H4)="dnp",LOWER(U4)="dnp"),"DNP",IF(OR(LOWER(V4)="disbursed",ISNUMBER(SEARCH("Disbursed",W4&""))),"Disbursed",IF(OR(LOWER(V4)="loan proccessed/accepted",ISNUMBER(SEARCH("sanctioned",LOWER(W4&"")))),"Sanctioned",IF(OR(LOWER(V4)="rejected",ISNUMBER(SEARCH("Not eligbile",W4&"")),ISNUMBER(SEARCH("Not eligible",W4&""))),"Rejected",IF(ISNUMBER(SEARCH("Docs Pending",W4&"")),"Documents Pending",IF(AND(LOWER(H4)="yes",LOWER(V4)="ongoing"),"Processing",IF(AND(LOWER(H4)="yes",Q4>0,OR(V4="",LOWER(V4)="not even started")),"Vendor Assigned",IF(AND(LOWER(H4)="yes",LOWER(V4)="not even started"),"Need Loan",IF(LOWER(H4)="yes","Loan Started",IF(LOWER(H4)="not sure","Interested",IF(OR(LOWER(H4)="no",LOWER(V4)="not required"),"Not Required","Unclassified"))))))))))))) | Y4: =IF(A4="","",IF(OR(X4="Sanctioned",X4="Disbursed",X4="Approved"),"Approved",IF(X4="Rejected","Rejected",IF(OR(X4="Processing",X4="Documents Pending",X4="Vendor Assigned"),"In Progress",IF(X4="Need Loan","Pending Start","—")))) | Z4: =IF(A4="","",IF(X4="Disbursed","Disbursed",IF(X4="Sanctioned","Sanctioned - Awaiting Disbursement","Not Disbursed"))) | AA4: =IF(A4="","",IF(LOWER(TRIM('01_Master_Data'!AI4&""))="yes","Need FLDG",IF(LOWER(TRIM('01_Master_Data'!AK4&""))="yes","Need Vidyalakshmi",IF(LOWER(TRIM('01_Master_Data'!AJ4&""))="yes","Need Review",IF(LOWER(J4)="critical","Critical",IF(LOWER(U4)="risk","Risk Case",IF(X4="Refund","Refund","Normal"))))))) | AB4: =IF(A4="","",IF(OR(LOWER(J4)="critical",LOWER(TRIM('01_Master_Data'!AI4&""))="yes",LOWER(TRIM('01_Master_Data'!AK4&""))="yes",LOWER(U4)="risk"),"Yes","No")) | AC4: =IF(A4="","",IF(LOWER(TRIM('01_Master_Data'!AI4&""))="yes","Yes","No")) | AD4: =IF(A4="","",IF(LOWER(TRIM('01_Master_Data'!AK4&""))="yes","Yes","No")) | AE4: =IF(A4="","",IF(LOWER(TRIM('01_Master_Data'!AJ4&""))="yes","Yes","No")) | AF4: =IF(A4="","",TRIM('01_Master_Data'!AL4&"")) | AG4: =IF(A4="","",IF(AF4="","—",IF(ISNUMBER(SEARCH("DNP",AF4)),"Unreachable / DNP",IF(ISNUMBER(SEARCH("interest",LOWER(AF4))),"High Interest / Terms",IF(OR(ISNUMBER(SEARCH("eligib",LOWER(AF4))),ISNUMBER(SEARCH("income",LOWER(AF4)))),"Eligibility / Income",IF(OR(ISNUMBER(SEARCH("start",LOWER(AF4))),ISNUMBER(SEARCH("Newer",AF4)),ISNUMBER(SEARCH("Will start",AF4))),"Process Yet to Start",IF(ISNUMBER(SEARCH("sure",LOWER(AF4))),"Undecided",IF(OR(ISNUMBER(SEARCH("reject",LOWER(AF4))),ISNUMBER(SEARCH("SBI",AF4))),"Rejected Elsewhere",IF(ISNUMBER(SEARCH("call",LOWER(AF4))),"Bank Communication",IF(OR(ISNUMBER(SEARCH("father",LOWER(AF4))),ISNUMBER(SEARCH("sister",LOWER(AF4)))),"Family / Dependency","Other")))))))))) | AH4: =IF(A4="","",'01_Master_Data'!AC4) | AI4: =IF(A4="","",IF(OR(AH4="",NOT(ISNUMBER(AH4))),"",MAX(0,'02_Configuration'!$B$82-AH4))) | AJ4: =IF(A4="","",IF(AI4="","Unknown",IF(AI4<=3,"0–3 Days",IF(AI4<=7,"4–7 Days",IF(AI4<=15,"8–15 Days",IF(AI4<=30,"16–30 Days","30+ Days")))))) | AK4: =IF(A4="","",IF(LOWER(H4)="yes","Yes","No")) | AL4: =IF(A4="","",'01_Master_Data'!T4) | AM4: =IF(A4="","",'01_Master_Data'!S4) | AN4: =IF(A4="","",'01_Master_Data'!I4) | AO4: =IF(A4="","",'01_Master_Data'!M4) | AP4: =IF(A4="","",IF(ISNUMBER(SEARCH("Icici",W4&"")),1,0)) | AQ4: =IF(A4="","",IF(ISNUMBER(SEARCH("Propelld",W4&"")),1,0)) | AR4: =IF(A4="","",IF(ISNUMBER(SEARCH("GyanDhan",W4&"")),1,0)) | AS4: =IF(A4="","",IF(ISNUMBER(SEARCH("vidyalakshmi",LOWER(W4&""))),1,0)) | AT4: =IF(A4="","",IF(ISNUMBER(SEARCH("other bank",LOWER(W4&""))),1,0)) | AU4: =IF(A4="","",IF(ISNUMBER(SEARCH("sanctioned",LOWER(W4&""))),1,0)) | AV4: =IF(A4="","",IF(ISNUMBER(SEARCH("Docs Pending",W4&"")),1,0)) | AW4: =IF(A4="","",IF(OR(X4="Rejected",ISNUMBER(SEARCH("Not eligbile",W4&""))),1,0))
A5: =IF('01_Master_Data'!B5="","",4) | B5: =IF('01_Master_Data'!B5="","",IF('01_Master_Data'!C5<>"","MOB|"&TEXT('01_Master_Data'!C5,"0"),IF('01_Master_Data'!D5<>"","PID|"&TRIM('01_Master_Data'!D5&""),""))) | C5: =IF('01_Master_Data'!B5="","",'01_Master_Data'!B5) | D5: =IF('01_Master_Data'!B5="","",'01_Master_Data'!C5) | E5: =IF('01_Master_Data'!B5="","",'01_Master_Data'!D5) | F5: =IF('01_Master_Data'!B5="","",'01_Master_Data'!E5) | G5: =IF('01_Master_Data'!B5="","",IFERROR(VLOOKUP(TRIM('01_Master_Data'!E5&""),'02_Configuration'!$A$40:$B$44,2,FALSE),UPPER(TRIM('01_Master_Data'!E5&"")))) | H5: =IF('01_Master_Data'!B5="","",IF('01_Master_Data'!U5="","",TRIM('01_Master_Data'!U5&""))) | I5: =IF('01_Master_Data'!B5="","",TRIM('01_Master_Data'!F5&"")) | J5: =IF('01_Master_Data'!B5="","",TRIM('01_Master_Data'!G5&"")) | K5: =IF('01_Master_Data'!B5="","",'01_Master_Data'!H5) | L5: =IF('01_Master_Data'!B5="","",IF(LOWER(TRIM('01_Master_Data'!V5&""))="yes",1,0)) | M5: =IF('01_Master_Data'!B5="","",IF(LOWER(TRIM('01_Master_Data'!W5&""))="yes",1,0)) | N5: =IF('01_Master_Data'!B5="","",IF(LOWER(TRIM('01_Master_Data'!X5&""))="yes",1,0)) | O5: =IF('01_Master_Data'!B5="","",IF(LOWER(TRIM('01_Master_Data'!Y5&""))="yes",1,0)) | P5: =IF('01_Master_Data'!B5="","",IF(LOWER(TRIM('01_Master_Data'!Z5&""))="yes",1,0)) | Q5: =IF(A5="","",L5+M5+N5+O5+P5) | R5: =IF(A5="","",IF(Q5>1,"Yes","No")) | S5: =IF(A5="","",TEXTJOIN(", ",TRUE,IF(L5=1,"ICICI",""),IF(M5=1,"Propelld",""),IF(N5=1,"Study4Buddy",""),IF(O5=1,"Poonawala Fincorp",""),IF(P5=1,"GyanDhan",""))) | T5: =IF(A5="","",IF(L5=1,"ICICI",IF(M5=1,"Propelld",IF(P5=1,"GyanDhan",IF(N5=1,"Study4Buddy",IF(O5=1,"Poonawala Fincorp",IF(ISNUMBER(SEARCH("GyanDhan",W5&"")),"GyanDhan",IF(ISNUMBER(SEARCH("Icici",W5&"")),"ICICI",IF(ISNUMBER(SEARCH("Propelld",W5&"")),"Propelld",IF(ISNUMBER(SEARCH("vidyalakshmi",LOWER(W5&"")),"PM Vidyalakshmi","—")))))))))) | U5: =IF(A5="","",TRIM('01_Master_Data'!AA5&"")) | V5: =IF(A5="","",TRIM('01_Master_Data'!AG5&"")) | W5: =IF(A5="","",TRIM('01_Master_Data'!AH5&"")) | X5: =IF(A5="","",IF(OR(LOWER(H5)="refund",LOWER(U5)="refund case"),"Refund",IF(OR(LOWER(H5)="dnp",LOWER(U5)="dnp"),"DNP",IF(OR(LOWER(V5)="disbursed",ISNUMBER(SEARCH("Disbursed",W5&""))),"Disbursed",IF(OR(LOWER(V5)="loan proccessed/accepted",ISNUMBER(SEARCH("sanctioned",LOWER(W5&"")))),"Sanctioned",IF(OR(LOWER(V5)="rejected",ISNUMBER(SEARCH("Not eligbile",W5&"")),ISNUMBER(SEARCH("Not eligible",W5&""))),"Rejected",IF(ISNUMBER(SEARCH("Docs Pending",W5&"")),"Documents Pending",IF(AND(LOWER(H5)="yes",LOWER(V5)="ongoing"),"Processing",IF(AND(LOWER(H5)="yes",Q5>0,OR(V5="",LOWER(V5)="not even started")),"Vendor Assigned",IF(AND(LOWER(H5)="yes",LOWER(V5)="not even started"),"Need Loan",IF(LOWER(H5)="yes","Loan Started",IF(LOWER(H5)="not sure","Interested",IF(OR(LOWER(H5)="no",LOWER(V5)="not required"),"Not Required","Unclassified"))))))))))))) | Y5: =IF(A5="","",IF(OR(X5="Sanctioned",X5="Disbursed",X5="Approved"),"Approved",IF(X5="Rejected","Rejected",IF(OR(X5="Processing",X5="Documents Pending",X5="Vendor Assigned"),"In Progress",IF(X5="Need Loan","Pending Start","—")))) | Z5: =IF(A5="","",IF(X5="Disbursed","Disbursed",IF(X5="Sanctioned","Sanctioned - Awaiting Disbursement","Not Disbursed"))) | AA5: =IF(A5="","",IF(LOWER(TRIM('01_Master_Data'!AI5&""))="yes","Need FLDG",IF(LOWER(TRIM('01_Master_Data'!AK5&""))="yes","Need Vidyalakshmi",IF(LOWER(TRIM('01_Master_Data'!AJ5&""))="yes","Need Review",IF(LOWER(J5)="critical","Critical",IF(LOWER(U5)="risk","Risk Case",IF(X5="Refund","Refund","Normal"))))))) | AB5: =IF(A5="","",IF(OR(LOWER(J5)="critical",LOWER(TRIM('01_Master_Data'!AI5&""))="yes",LOWER(TRIM('01_Master_Data'!AK5&""))="yes",LOWER(U5)="risk"),"Yes","No")) | AC5: =IF(A5="","",IF(LOWER(TRIM('01_Master_Data'!AI5&""))="yes","Yes","No")) | AD5: =IF(A5="","",IF(LOWER(TRIM('01_Master_Data'!AK5&""))="yes","Yes","No")) | AE5: =IF(A5="","",IF(LOWER(TRIM('01_Master_Data'!AJ5&""))="yes","Yes","No")) | AF5: =IF(A5="","",TRIM('01_Master_Data'!AL5&"")) | AG5: =IF(A5="","",IF(AF5="","—",IF(ISNUMBER(SEARCH("DNP",AF5)),"Unreachable / DNP",IF(ISNUMBER(SEARCH("interest",LOWER(AF5))),"High Interest / Terms",IF(OR(ISNUMBER(SEARCH("eligib",LOWER(AF5))),ISNUMBER(SEARCH("income",LOWER(AF5)))),"Eligibility / Income",IF(OR(ISNUMBER(SEARCH("start",LOWER(AF5))),ISNUMBER(SEARCH("Newer",AF5)),ISNUMBER(SEARCH("Will start",AF5))),"Process Yet to Start",IF(ISNUMBER(SEARCH("sure",LOWER(AF5))),"Undecided",IF(OR(ISNUMBER(SEARCH("reject",LOWER(AF5))),ISNUMBER(SEARCH("SBI",AF5))),"Rejected Elsewhere",IF(ISNUMBER(SEARCH("call",LOWER(AF5))),"Bank Communication",IF(OR(ISNUMBER(SEARCH("father",LOWER(AF5))),ISNUMBER(SEARCH("sister",LOWER(AF5)))),"Family / Dependency","Other")))))))))) | AH5: =IF(A5="","",'01_Master_Data'!AC5) | AI5: =IF(A5="","",IF(OR(AH5="",NOT(ISNUMBER(AH5))),"",MAX(0,'02_Configuration'!$B$82-AH5))) | AJ5: =IF(A5="","",IF(AI5="","Unknown",IF(AI5<=3,"0–3 Days",IF(AI5<=7,"4–7 Days",IF(AI5<=15,"8–15 Days",IF(AI5<=30,"16–30 Days","30+ Days")))))) | AK5: =IF(A5="","",IF(LOWER(H5)="yes","Yes","No")) | AL5: =IF(A5="","",'01_Master_Data'!T5) | AM5: =IF(A5="","",'01_Master_Data'!S5) | AN5: =IF(A5="","",'01_Master_Data'!I5) | AO5: =IF(A5="","",'01_Master_Data'!M5) | AP5: =IF(A5="","",IF(ISNUMBER(SEARCH("Icici",W5&"")),1,0)) | AQ5: =IF(A5="","",IF(ISNUMBER(SEARCH("Propelld",W5&"")),1,0)) | AR5: =IF(A5="","",IF(ISNUMBER(SEARCH("GyanDhan",W5&"")),1,0)) | AS5: =IF(A5="","",IF(ISNUMBER(SEARCH("vidyalakshmi",LOWER(W5&""))),1,0)) | AT5: =IF(A5="","",IF(ISNUMBER(SEARCH("other bank",LOWER(W5&""))),1,0)) | AU5: =IF(A5="","",IF(ISNUMBER(SEARCH("sanctioned",LOWER(W5&""))),1,0)) | AV5: =IF(A5="","",IF(ISNUMBER(SEARCH("Docs Pending",W5&"")),1,0)) | AW5: =IF(A5="","",IF(OR(X5="Rejected",ISNUMBER(SEARCH("Not eligbile",W5&""))),1,0))
A6: =IF('01_Master_Data'!B6="","",5) | B6: =IF('01_Master_Data'!B6="","",IF('01_Master_Data'!C6<>"","MOB|"&TEXT('01_Master_Data'!C6,"0"),IF('01_Master_Data'!D6<>"","PID|"&TRIM('01_Master_Data'!D6&""),""))) | C6: =IF('01_Master_Data'!B6="","",'01_Master_Data'!B6) | D6: =IF('01_Master_Data'!B6="","",'01_Master_Data'!C6) | E6: =IF('01_Master_Data'!B6="","",'01_Master_Data'!D6) | F6: =IF('01_Master_Data'!B6="","",'01_Master_Data'!E6) | G6: =IF('01_Master_Data'!B6="","",IFERROR(VLOOKUP(TRIM('01_Master_Data'!E6&""),'02_Configuration'!$A$40:$B$44,2,FALSE),UPPER(TRIM('01_Master_Data'!E6&"")))) | H6: =IF('01_Master_Data'!B6="","",IF('01_Master_Data'!U6="","",TRIM('01_Master_Data'!U6&""))) | I6: =IF('01_Master_Data'!B6="","",TRIM('01_Master_Data'!F6&"")) | J6: =IF('01_Master_Data'!B6="","",TRIM('01_Master_Data'!G6&"")) | K6: =IF('01_Master_Data'!B6="","",'01_Master_Data'!H6) | L6: =IF('01_Master_Data'!B6="","",IF(LOWER(TRIM('01_Master_Data'!V6&""))="yes",1,0)) | M6: =IF('01_Master_Data'!B6="","",IF(LOWER(TRIM('01_Master_Data'!W6&""))="yes",1,0)) | N6: =IF('01_Master_Data'!B6="","",IF(LOWER(TRIM('01_Master_Data'!X6&""))="yes",1,0)) | O6: =IF('01_Master_Data'!B6="","",IF(LOWER(TRIM('01_Master_Data'!Y6&""))="yes",1,0)) | P6: =IF('01_Master_Data'!B6="","",IF(LOWER(TRIM('01_Master_Data'!Z6&""))="yes",1,0)) | Q6: =IF(A6="","",L6+M6+N6+O6+P6) | R6: =IF(A6="","",IF(Q6>1,"Yes","No")) | S6: =IF(A6="","",TEXTJOIN(", ",TRUE,IF(L6=1,"ICICI",""),IF(M6=1,"Propelld",""),IF(N6=1,"Study4Buddy",""),IF(O6=1,"Poonawala Fincorp",""),IF(P6=1,"GyanDhan",""))) | T6: =IF(A6="","",IF(L6=1,"ICICI",IF(M6=1,"Propelld",IF(P6=1,"GyanDhan",IF(N6=1,"Study4Buddy",IF(O6=1,"Poonawala Fincorp",IF(ISNUMBER(SEARCH("GyanDhan",W6&"")),"GyanDhan",IF(ISNUMBER(SEARCH("Icici",W6&"")),"ICICI",IF(ISNUMBER(SEARCH("Propelld",W6&"")),"Propelld",IF(ISNUMBER(SEARCH("vidyalakshmi",LOWER(W6&"")),"PM Vidyalakshmi","—")))))))))) | U6: =IF(A6="","",TRIM('01_Master_Data'!AA6&"")) | V6: =IF(A6="","",TRIM('01_Master_Data'!AG6&"")) | W6: =IF(A6="","",TRIM('01_Master_Data'!AH6&"")) | X6: =IF(A6="","",IF(OR(LOWER(H6)="refund",LOWER(U6)="refund case"),"Refund",IF(OR(LOWER(H6)="dnp",LOWER(U6)="dnp"),"DNP",IF(OR(LOWER(V6)="disbursed",ISNUMBER(SEARCH("Disbursed",W6&""))),"Disbursed",IF(OR(LOWER(V6)="loan proccessed/accepted",ISNUMBER(SEARCH("sanctioned",LOWER(W6&"")))),"Sanctioned",IF(OR(LOWER(V6)="rejected",ISNUMBER(SEARCH("Not eligbile",W6&"")),ISNUMBER(SEARCH("Not eligible",W6&""))),"Rejected",IF(ISNUMBER(SEARCH("Docs Pending",W6&"")),"Documents Pending",IF(AND(LOWER(H6)="yes",LOWER(V6)="ongoing"),"Processing",IF(AND(LOWER(H6)="yes",Q6>0,OR(V6="",LOWER(V6)="not even started")),"Vendor Assigned",IF(AND(LOWER(H6)="yes",LOWER(V6)="not even started"),"Need Loan",IF(LOWER(H6)="yes","Loan Started",IF(LOWER(H6)="not sure","Interested",IF(OR(LOWER(H6)="no",LOWER(V6)="not required"),"Not Required","Unclassified"))))))))))))) | Y6: =IF(A6="","",IF(OR(X6="Sanctioned",X6="Disbursed",X6="Approved"),"Approved",IF(X6="Rejected","Rejected",IF(OR(X6="Processing",X6="Documents Pending",X6="Vendor Assigned"),"In Progress",IF(X6="Need Loan","Pending Start","—")))) | Z6: =IF(A6="","",IF(X6="Disbursed","Disbursed",IF(X6="Sanctioned","Sanctioned - Awaiting Disbursement","Not Disbursed"))) | AA6: =IF(A6="","",IF(LOWER(TRIM('01_Master_Data'!AI6&""))="yes","Need FLDG",IF(LOWER(TRIM('01_Master_Data'!AK6&""))="yes","Need Vidyalakshmi",IF(LOWER(TRIM('01_Master_Data'!AJ6&""))="yes","Need Review",IF(LOWER(J6)="critical","Critical",IF(LOWER(U6)="risk","Risk Case",IF(X6="Refund","Refund","Normal"))))))) | AB6: =IF(A6="","",IF(OR(LOWER(J6)="critical",LOWER(TRIM('01_Master_Data'!AI6&""))="yes",LOWER(TRIM('01_Master_Data'!AK6&""))="yes",LOWER(U6)="risk"),"Yes","No")) | AC6: =IF(A6="","",IF(LOWER(TRIM('01_Master_Data'!AI6&""))="yes","Yes","No")) | AD6: =IF(A6="","",IF(LOWER(TRIM('01_Master_Data'!AK6&""))="yes","Yes","No")) | AE6: =IF(A6="","",IF(LOWER(TRIM('01_Master_Data'!AJ6&""))="yes","Yes","No")) | AF6: =IF(A6="","",TRIM('01_Master_Data'!AL6&"")) | AG6: =IF(A6="","",IF(AF6="","—",IF(ISNUMBER(SEARCH("DNP",AF6)),"Unreachable / DNP",IF(ISNUMBER(SEARCH("interest",LOWER(AF6))),"High Interest / Terms",IF(OR(ISNUMBER(SEARCH("eligib",LOWER(AF6))),ISNUMBER(SEARCH("income",LOWER(AF6)))),"Eligibility / Income",IF(OR(ISNUMBER(SEARCH("start",LOWER(AF6))),ISNUMBER(SEARCH("Newer",AF6)),ISNUMBER(SEARCH("Will start",AF6))),"Process Yet to Start",IF(ISNUMBER(SEARCH("sure",LOWER(AF6))),"Undecided",IF(OR(ISNUMBER(SEARCH("reject",LOWER(AF6))),ISNUMBER(SEARCH("SBI",AF6))),"Rejected Elsewhere",IF(ISNUMBER(SEARCH("call",LOWER(AF6))),"Bank Communication",IF(OR(ISNUMBER(SEARCH("father",LOWER(AF6))),ISNUMBER(SEARCH("sister",LOWER(AF6)))),"Family / Dependency","Other")))))))))) | AH6: =IF(A6="","",'01_Master_Data'!AC6) | AI6: =IF(A6="","",IF(OR(AH6="",NOT(ISNUMBER(AH6))),"",MAX(0,'02_Configuration'!$B$82-AH6))) | AJ6: =IF(A6="","",IF(AI6="","Unknown",IF(AI6<=3,"0–3 Days",IF(AI6<=7,"4–7 Days",IF(AI6<=15,"8–15 Days",IF(AI6<=30,"16–30 Days","30+ Days")))))) | AK6: =IF(A6="","",IF(LOWER(H6)="yes","Yes","No")) | AL6: =IF(A6="","",'01_Master_Data'!T6) | AM6: =IF(A6="","",'01_Master_Data'!S6) | AN6: =IF(A6="","",'01_Master_Data'!I6) | AO6: =IF(A6="","",'01_Master_Data'!M6) | AP6: =IF(A6="","",IF(ISNUMBER(SEARCH("Icici",W6&"")),1,0)) | AQ6: =IF(A6="","",IF(ISNUMBER(SEARCH("Propelld",W6&"")),1,0)) | AR6: =IF(A6="","",IF(ISNUMBER(SEARCH("GyanDhan",W6&"")),1,0)) | AS6: =IF(A6="","",IF(ISNUMBER(SEARCH("vidyalakshmi",LOWER(W6&""))),1,0)) | AT6: =IF(A6="","",IF(ISNUMBER(SEARCH("other bank",LOWER(W6&""))),1,0)) | AU6: =IF(A6="","",IF(ISNUMBER(SEARCH("sanctioned",LOWER(W6&""))),1,0)) | AV6: =IF(A6="","",IF(ISNUMBER(SEARCH("Docs Pending",W6&"")),1,0)) | AW6: =IF(A6="","",IF(OR(X6="Rejected",ISNUMBER(SEARCH("Not eligbile",W6&""))),1,0))
A7: =IF('01_Master_Data'!B7="","",6) | B7: =IF('01_Master_Data'!B7="","",IF('01_Master_Data'!C7<>"","MOB|"&TEXT('01_Master_Data'!C7,"0"),IF('01_Master_Data'!D7<>"","PID|"&TRIM('01_Master_Data'!D7&""),""))) | C7: =IF('01_Master_Data'!B7="","",'01_Master_Data'!B7) | D7: =IF('01_Master_Data'!B7="","",'01_Master_Data'!C7) | E7: =IF('01_Master_Data'!B7="","",'01_Master_Data'!D7) | F7: =IF('01_Master_Data'!B7="","",'01_Master_Data'!E7) | G7: =IF('01_Master_Data'!B7="","",IFERROR(VLOOKUP(TRIM('01_Master_Data'!E7&""),'02_Configuration'!$A$40:$B$44,2,FALSE),UPPER(TRIM('01_Master_Data'!E7&"")))) | H7: =IF('01_Master_Data'!B7="","",IF('01_Master_Data'!U7="","",TRIM('01_Master_Data'!U7&""))) | I7: =IF('01_Master_Data'!B7="","",TRIM('01_Master_Data'!F7&"")) | J7: =IF('01_Master_Data'!B7="","",TRIM('01_Master_Data'!G7&"")) | K7: =IF('01_Master_Data'!B7="","",'01_Master_Data'!H7) | L7: =IF('01_Master_Data'!B7="","",IF(LOWER(TRIM('01_Master_Data'!V7&""))="yes",1,0)) | M7: =IF('01_Master_Data'!B7="","",IF(LOWER(TRIM('01_Master_Data'!W7&""))="yes",1,0)) | N7: =IF('01_Master_Data'!B7="","",IF(LOWER(TRIM('01_Master_Data'!X7&""))="yes",1,0)) | O7: =IF('01_Master_Data'!B7="","",IF(LOWER(TRIM('01_Master_Data'!Y7&""))="yes",1,0)) | P7: =IF('01_Master_Data'!B7="","",IF(LOWER(TRIM('01_Master_Data'!Z7&""))="yes",1,0)) | Q7: =IF(A7="","",L7+M7+N7+O7+P7) | R7: =IF(A7="","",IF(Q7>1,"Yes","No")) | S7: =IF(A7="","",TEXTJOIN(", ",TRUE,IF(L7=1,"ICICI",""),IF(M7=1,"Propelld",""),IF(N7=1,"Study4Buddy",""),IF(O7=1,"Poonawala Fincorp",""),IF(P7=1,"GyanDhan",""))) | T7: =IF(A7="","",IF(L7=1,"ICICI",IF(M7=1,"Propelld",IF(P7=1,"GyanDhan",IF(N7=1,"Study4Buddy",IF(O7=1,"Poonawala Fincorp",IF(ISNUMBER(SEARCH("GyanDhan",W7&"")),"GyanDhan",IF(ISNUMBER(SEARCH("Icici",W7&"")),"ICICI",IF(ISNUMBER(SEARCH("Propelld",W7&"")),"Propelld",IF(ISNUMBER(SEARCH("vidyalakshmi",LOWER(W7&"")),"PM Vidyalakshmi","—")))))))))) | U7: =IF(A7="","",TRIM('01_Master_Data'!AA7&"")) | V7: =IF(A7="","",TRIM('01_Master_Data'!AG7&"")) | W7: =IF(A7="","",TRIM('01_Master_Data'!AH7&"")) | X7: =IF(A7="","",IF(OR(LOWER(H7)="refund",LOWER(U7)="refund case"),"Refund",IF(OR(LOWER(H7)="dnp",LOWER(U7)="dnp"),"DNP",IF(OR(LOWER(V7)="disbursed",ISNUMBER(SEARCH("Disbursed",W7&""))),"Disbursed",IF(OR(LOWER(V7)="loan proccessed/accepted",ISNUMBER(SEARCH("sanctioned",LOWER(W7&"")))),"Sanctioned",IF(OR(LOWER(V7)="rejected",ISNUMBER(SEARCH("Not eligbile",W7&"")),ISNUMBER(SEARCH("Not eligible",W7&""))),"Rejected",IF(ISNUMBER(SEARCH("Docs Pending",W7&"")),"Documents Pending",IF(AND(LOWER(H7)="yes",LOWER(V7)="ongoing"),"Processing",IF(AND(LOWER(H7)="yes",Q7>0,OR(V7="",LOWER(V7)="not even started")),"Vendor Assigned",IF(AND(LOWER(H7)="yes",LOWER(V7)="not even started"),"Need Loan",IF(LOWER(H7)="yes","Loan Started",IF(LOWER(H7)="not sure","Interested",IF(OR(LOWER(H7)="no",LOWER(V7)="not required"),"Not Required","Unclassified"))))))))))))) | Y7: =IF(A7="","",IF(OR(X7="Sanctioned",X7="Disbursed",X7="Approved"),"Approved",IF(X7="Rejected","Rejected",IF(OR(X7="Processing",X7="Documents Pending",X7="Vendor Assigned"),"In Progress",IF(X7="Need Loan","Pending Start","—")))) | Z7: =IF(A7="","",IF(X7="Disbursed","Disbursed",IF(X7="Sanctioned","Sanctioned - Awaiting Disbursement","Not Disbursed"))) | AA7: =IF(A7="","",IF(LOWER(TRIM('01_Master_Data'!AI7&""))="yes","Need FLDG",IF(LOWER(TRIM('01_Master_Data'!AK7&""))="yes","Need Vidyalakshmi",IF(LOWER(TRIM('01_Master_Data'!AJ7&""))="yes","Need Review",IF(LOWER(J7)="critical","Critical",IF(LOWER(U7)="risk","Risk Case",IF(X7="Refund","Refund","Normal"))))))) | AB7: =IF(A7="","",IF(OR(LOWER(J7)="critical",LOWER(TRIM('01_Master_Data'!AI7&""))="yes",LOWER(TRIM('01_Master_Data'!AK7&""))="yes",LOWER(U7)="risk"),"Yes","No")) | AC7: =IF(A7="","",IF(LOWER(TRIM('01_Master_Data'!AI7&""))="yes","Yes","No")) | AD7: =IF(A7="","",IF(LOWER(TRIM('01_Master_Data'!AK7&""))="yes","Yes","No")) | AE7: =IF(A7="","",IF(LOWER(TRIM('01_Master_Data'!AJ7&""))="yes","Yes","No")) | AF7: =IF(A7="","",TRIM('01_Master_Data'!AL7&"")) | AG7: =IF(A7="","",IF(AF7="","—",IF(ISNUMBER(SEARCH("DNP",AF7)),"Unreachable / DNP",IF(ISNUMBER(SEARCH("interest",LOWER(AF7))),"High Interest / Terms",IF(OR(ISNUMBER(SEARCH("eligib",LOWER(AF7))),ISNUMBER(SEARCH("income",LOWER(AF7)))),"Eligibility / Income",IF(OR(ISNUMBER(SEARCH("start",LOWER(AF7))),ISNUMBER(SEARCH("Newer",AF7)),ISNUMBER(SEARCH("Will start",AF7))),"Process Yet to Start",IF(ISNUMBER(SEARCH("sure",LOWER(AF7))),"Undecided",IF(OR(ISNUMBER(SEARCH("reject",LOWER(AF7))),ISNUMBER(SEARCH("SBI",AF7))),"Rejected Elsewhere",IF(ISNUMBER(SEARCH("call",LOWER(AF7))),"Bank Communication",IF(OR(ISNUMBER(SEARCH("father",LOWER(AF7))),ISNUMBER(SEARCH("sister",LOWER(AF7)))),"Family / Dependency","Other")))))))))) | AH7: =IF(A7="","",'01_Master_Data'!AC7) | AI7: =IF(A7="","",IF(OR(AH7="",NOT(ISNUMBER(AH7))),"",MAX(0,'02_Configuration'!$B$82-AH7))) | AJ7: =IF(A7="","",IF(AI7="","Unknown",IF(AI7<=3,"0–3 Days",IF(AI7<=7,"4–7 Days",IF(AI7<=15,"8–15 Days",IF(AI7<=30,"16–30 Days","30+ Days")))))) | AK7: =IF(A7="","",IF(LOWER(H7)="yes","Yes","No")) | AL7: =IF(A7="","",'01_Master_Data'!T7) | AM7: =IF(A7="","",'01_Master_Data'!S7) | AN7: =IF(A7="","",'01_Master_Data'!I7) | AO7: =IF(A7="","",'01_Master_Data'!M7) | AP7: =IF(A7="","",IF(ISNUMBER(SEARCH("Icici",W7&"")),1,0)) | AQ7: =IF(A7="","",IF(ISNUMBER(SEARCH("Propelld",W7&"")),1,0)) | AR7: =IF(A7="","",IF(ISNUMBER(SEARCH("GyanDhan",W7&"")),1,0)) | AS7: =IF(A7="","",IF(ISNUMBER(SEARCH("vidyalakshmi",LOWER(W7&""))),1,0)) | AT7: =IF(A7="","",IF(ISNUMBER(SEARCH("other bank",LOWER(W7&""))),1,0)) | AU7: =IF(A7="","",IF(ISNUMBER(SEARCH("sanctioned",LOWER(W7&""))),1,0)) | AV7: =IF(A7="","",IF(ISNUMBER(SEARCH("Docs Pending",W7&"")),1,0)) | AW7: =IF(A7="","",IF(OR(X7="Rejected",ISNUMBER(SEARCH("Not eligbile",W7&""))),1,0))
A8: =IF('01_Master_Data'!B8="","",7) | B8: =IF('01_Master_Data'!B8="","",IF('01_Master_Data'!C8<>"","MOB|"&TEXT('01_Master_Data'!C8,"0"),IF('01_Master_Data'!D8<>"","PID|"&TRIM('01_Master_Data'!D8&""),""))) | C8: =IF('01_Master_Data'!B8="","",'01_Master_Data'!B8) | D8: =IF('01_Master_Data'!B8="","",'01_Master_Data'!C8) | E8: =IF('01_Master_Data'!B8="","",'01_Master_Data'!D8) | F8: =IF('01_Master_Data'!B8="","",'01_Master_Data'!E8) | G8: =IF('01_Master_Data'!B8="","",IFERROR(VLOOKUP(TRIM('01_Master_Data'!E8&""),'02_Configuration'!$A$40:$B$44,2,FALSE),UPPER(TRIM('01_Master_Data'!E8&"")))) | H8: =IF('01_Master_Data'!B8="","",IF('01_Master_Data'!U8="","",TRIM('01_Master_Data'!U8&""))) | I8: =IF('01_Master_Data'!B8="","",TRIM('01_Master_Data'!F8&"")) | J8: =IF('01_Master_Data'!B8="","",TRIM('01_Master_Data'!G8&"")) | K8: =IF('01_Master_Data'!B8="","",'01_Master_Data'!H8) | L8: =IF('01_Master_Data'!B8="","",IF(LOWER(TRIM('01_Master_Data'!V8&""))="yes",1,0)) | M8: =IF('01_Master_Data'!B8="","",IF(LOWER(TRIM('01_Master_Data'!W8&""))="yes",1,0)) | N8: =IF('01_Master_Data'!B8="","",IF(LOWER(TRIM('01_Master_Data'!X8&""))="yes",1,0)) | O8: =IF('01_Master_Data'!B8="","",IF(LOWER(TRIM('01_Master_Data'!Y8&""))="yes",1,0)) | P8: =IF('01_Master_Data'!B8="","",IF(LOWER(TRIM('01_Master_Data'!Z8&""))="yes",1,0)) | Q8: =IF(A8="","",L8+M8+N8+O8+P8) | R8: =IF(A8="","",IF(Q8>1,"Yes","No")) | S8: =IF(A8="","",TEXTJOIN(", ",TRUE,IF(L8=1,"ICICI",""),IF(M8=1,"Propelld",""),IF(N8=1,"Study4Buddy",""),IF(O8=1,"Poonawala Fincorp",""),IF(P8=1,"GyanDhan",""))) | T8: =IF(A8="","",IF(L8=1,"ICICI",IF(M8=1,"Propelld",IF(P8=1,"GyanDhan",IF(N8=1,"Study4Buddy",IF(O8=1,"Poonawala Fincorp",IF(ISNUMBER(SEARCH("GyanDhan",W8&"")),"GyanDhan",IF(ISNUMBER(SEARCH("Icici",W8&"")),"ICICI",IF(ISNUMBER(SEARCH("Propelld",W8&"")),"Propelld",IF(ISNUMBER(SEARCH("vidyalakshmi",LOWER(W8&"")),"PM Vidyalakshmi","—")))))))))) | U8: =IF(A8="","",TRIM('01_Master_Data'!AA8&"")) | V8: =IF(A8="","",TRIM('01_Master_Data'!AG8&"")) | W8: =IF(A8="","",TRIM('01_Master_Data'!AH8&"")) | X8: =IF(A8="","",IF(OR(LOWER(H8)="refund",LOWER(U8)="refund case"),"Refund",IF(OR(LOWER(H8)="dnp",LOWER(U8)="dnp"),"DNP",IF(OR(LOWER(V8)="disbursed",ISNUMBER(SEARCH("Disbursed",W8&""))),"Disbursed",IF(OR(LOWER(V8)="loan proccessed/accepted",ISNUMBER(SEARCH("sanctioned",LOWER(W8&"")))),"Sanctioned",IF(OR(LOWER(V8)="rejected",ISNUMBER(SEARCH("Not eligbile",W8&"")),ISNUMBER(SEARCH("Not eligible",W8&""))),"Rejected",IF(ISNUMBER(SEARCH("Docs Pending",W8&"")),"Documents Pending",IF(AND(LOWER(H8)="yes",LOWER(V8)="ongoing"),"Processing",IF(AND(LOWER(H8)="yes",Q8>0,OR(V8="",LOWER(V8)="not even started")),"Vendor Assigned",IF(AND(LOWER(H8)="yes",LOWER(V8)="not even started"),"Need Loan",IF(LOWER(H8)="yes","Loan Started",IF(LOWER(H8)="not sure","Interested",IF(OR(LOWER(H8)="no",LOWER(V8)="not required"),"Not Required","Unclassified"))))))))))))) | Y8: =IF(A8="","",IF(OR(X8="Sanctioned",X8="Disbursed",X8="Approved"),"Approved",IF(X8="Rejected","Rejected",IF(OR(X8="Processing",X8="Documents Pending",X8="Vendor Assigned"),"In Progress",IF(X8="Need Loan","Pending Start","—")))) | Z8: =IF(A8="","",IF(X8="Disbursed","Disbursed",IF(X8="Sanctioned","Sanctioned - Awaiting Disbursement","Not Disbursed"))) | AA8: =IF(A8="","",IF(LOWER(TRIM('01_Master_Data'!AI8&""))="yes","Need FLDG",IF(LOWER(TRIM('01_Master_Data'!AK8&""))="yes","Need Vidyalakshmi",IF(LOWER(TRIM('01_Master_Data'!AJ8&""))="yes","Need Review",IF(LOWER(J8)="critical","Critical",IF(LOWER(U8)="risk","Risk Case",IF(X8="Refund","Refund","Normal"))))))) | AB8: =IF(A8="","",IF(OR(LOWER(J8)="critical",LOWER(TRIM('01_Master_Data'!AI8&""))="yes",LOWER(TRIM('01_Master_Data'!AK8&""))="yes",LOWER(U8)="risk"),"Yes","No")) | AC8: =IF(A8="","",IF(LOWER(TRIM('01_Master_Data'!AI8&""))="yes","Yes","No")) | AD8: =IF(A8="","",IF(LOWER(TRIM('01_Master_Data'!AK8&""))="yes","Yes","No")) | AE8: =IF(A8="","",IF(LOWER(TRIM('01_Master_Data'!AJ8&""))="yes","Yes","No")) | AF8: =IF(A8="","",TRIM('01_Master_Data'!AL8&"")) | AG8: =IF(A8="","",IF(AF8="","—",IF(ISNUMBER(SEARCH("DNP",AF8)),"Unreachable / DNP",IF(ISNUMBER(SEARCH("interest",LOWER(AF8))),"High Interest / Terms",IF(OR(ISNUMBER(SEARCH("eligib",LOWER(AF8))),ISNUMBER(SEARCH("income",LOWER(AF8)))),"Eligibility / Income",IF(OR(ISNUMBER(SEARCH("start",LOWER(AF8))),ISNUMBER(SEARCH("Newer",AF8)),ISNUMBER(SEARCH("Will start",AF8))),"Process Yet to Start",IF(ISNUMBER(SEARCH("sure",LOWER(AF8))),"Undecided",IF(OR(ISNUMBER(SEARCH("reject",LOWER(AF8))),ISNUMBER(SEARCH("SBI",AF8))),"Rejected Elsewhere",IF(ISNUMBER(SEARCH("call",LOWER(AF8))),"Bank Communication",IF(OR(ISNUMBER(SEARCH("father",LOWER(AF8))),ISNUMBER(SEARCH("sister",LOWER(AF8)))),"Family / Dependency","Other")))))))))) | AH8: =IF(A8="","",'01_Master_Data'!AC8) | AI8: =IF(A8="","",IF(OR(AH8="",NOT(ISNUMBER(AH8))),"",MAX(0,'02_Configuration'!$B$82-AH8))) | AJ8: =IF(A8="","",IF(AI8="","Unknown",IF(AI8<=3,"0–3 Days",IF(AI8<=7,"4–7 Days",IF(AI8<=15,"8–15 Days",IF(AI8<=30,"16–30 Days","30+ Days")))))) | AK8: =IF(A8="","",IF(LOWER(H8)="yes","Yes","No")) | AL8: =IF(A8="","",'01_Master_Data'!T8) | AM8: =IF(A8="","",'01_Master_Data'!S8) | AN8: =IF(A8="","",'01_Master_Data'!I8) | AO8: =IF(A8="","",'01_Master_Data'!M8) | AP8: =IF(A8="","",IF(ISNUMBER(SEARCH("Icici",W8&"")),1,0)) | AQ8: =IF(A8="","",IF(ISNUMBER(SEARCH("Propelld",W8&"")),1,0)) | AR8: =IF(A8="","",IF(ISNUMBER(SEARCH("GyanDhan",W8&"")),1,0)) | AS8: =IF(A8="","",IF(ISNUMBER(SEARCH("vidyalakshmi",LOWER(W8&""))),1,0)) | AT8: =IF(A8="","",IF(ISNUMBER(SEARCH("other bank",LOWER(W8&""))),1,0)) | AU8: =IF(A8="","",IF(ISNUMBER(SEARCH("sanctioned",LOWER(W8&""))),1,0)) | AV8: =IF(A8="","",IF(ISNUMBER(SEARCH("Docs Pending",W8&"")),1,0)) | AW8: =IF(A8="","",IF(OR(X8="Rejected",ISNUMBER(SEARCH("Not eligbile",W8&""))),1,0))
A9: =IF('01_Master_Data'!B9="","",8) | B9: =IF('01_Master_Data'!B9="","",IF('01_Master_Data'!C9<>"","MOB|"&TEXT('01_Master_Data'!C9,"0"),IF('01_Master_Data'!D9<>"","PID|"&TRIM('01_Master_Data'!D9&""),""))) | C9: =IF('01_Master_Data'!B9="","",'01_Master_Data'!B9) | D9: =IF('01_Master_Data'!B9="","",'01_Master_Data'!C9) | E9: =IF('01_Master_Data'!B9="","",'01_Master_Data'!D9) | F9: =IF('01_Master_Data'!B9="","",'01_Master_Data'!E9) | G9: =IF('01_Master_Data'!B9="","",IFERROR(VLOOKUP(TRIM('01_Master_Data'!E9&""),'02_Configuration'!$A$40:$B$44,2,FALSE),UPPER(TRIM('01_Master_Data'!E9&"")))) | H9: =IF('01_Master_Data'!B9="","",IF('01_Master_Data'!U9="","",TRIM('01_Master_Data'!U9&""))) | I9: =IF('01_Master_Data'!B9="","",TRIM('01_Master_Data'!F9&"")) | J9: =IF('01_Master_Data'!B9="","",TRIM('01_Master_Data'!G9&"")) | K9: =IF('01_Master_Data'!B9="","",'01_Master_Data'!H9) | L9: =IF('01_Master_Data'!B9="","",IF(LOWER(TRIM('01_Master_Data'!V9&""))="yes",1,0)) | M9: =IF('01_Master_Data'!B9="","",IF(LOWER(TRIM('01_Master_Data'!W9&""))="yes",1,0)) | N9: =IF('01_Master_Data'!B9="","",IF(LOWER(TRIM('01_Master_Data'!X9&""))="yes",1,0)) | O9: =IF('01_Master_Data'!B9="","",IF(LOWER(TRIM('01_Master_Data'!Y9&""))="yes",1,0)) | P9: =IF('01_Master_Data'!B9="","",IF(LOWER(TRIM('01_Master_Data'!Z9&""))="yes",1,0)) | Q9: =IF(A9="","",L9+M9+N9+O9+P9) | R9: =IF(A9="","",IF(Q9>1,"Yes","No")) | S9: =IF(A9="","",TEXTJOIN(", ",TRUE,IF(L9=1,"ICICI",""),IF(M9=1,"Propelld",""),IF(N9=1,"Study4Buddy",""),IF(O9=1,"Poonawala Fincorp",""),IF(P9=1,"GyanDhan",""))) | T9: =IF(A9="","",IF(L9=1,"ICICI",IF(M9=1,"Propelld",IF(P9=1,"GyanDhan",IF(N9=1,"Study4Buddy",IF(O9=1,"Poonawala Fincorp",IF(ISNUMBER(SEARCH("GyanDhan",W9&"")),"GyanDhan",IF(ISNUMBER(SEARCH("Icici",W9&"")),"ICICI",IF(ISNUMBER(SEARCH("Propelld",W9&"")),"Propelld",IF(ISNUMBER(SEARCH("vidyalakshmi",LOWER(W9&"")),"PM Vidyalakshmi","—")))))))))) | U9: =IF(A9="","",TRIM('01_Master_Data'!AA9&"")) | V9: =IF(A9="","",TRIM('01_Master_Data'!AG9&"")) | W9: =IF(A9="","",TRIM('01_Master_Data'!AH9&"")) | X9: =IF(A9="","",IF(OR(LOWER(H9)="refund",LOWER(U9)="refund case"),"Refund",IF(OR(LOWER(H9)="dnp",LOWER(U9)="dnp"),"DNP",IF(OR(LOWER(V9)="disbursed",ISNUMBER(SEARCH("Disbursed",W9&""))),"Disbursed",IF(OR(LOWER(V9)="loan proccessed/accepted",ISNUMBER(SEARCH("sanctioned",LOWER(W9&"")))),"Sanctioned",IF(OR(LOWER(V9)="rejected",ISNUMBER(SEARCH("Not eligbile",W9&"")),ISNUMBER(SEARCH("Not eligible",W9&""))),"Rejected",IF(ISNUMBER(SEARCH("Docs Pending",W9&"")),"Documents Pending",IF(AND(LOWER(H9)="yes",LOWER(V9)="ongoing"),"Processing",IF(AND(LOWER(H9)="yes",Q9>0,OR(V9="",LOWER(V9)="not even started")),"Vendor Assigned",IF(AND(LOWER(H9)="yes",LOWER(V9)="not even started"),"Need Loan",IF(LOWER(H9)="yes","Loan Started",IF(LOWER(H9)="not sure","Interested",IF(OR(LOWER(H9)="no",LOWER(V9)="not required"),"Not Required","Unclassified"))))))))))))) | Y9: =IF(A9="","",IF(OR(X9="Sanctioned",X9="Disbursed",X9="Approved"),"Approved",IF(X9="Rejected","Rejected",IF(OR(X9="Processing",X9="Documents Pending",X9="Vendor Assigned"),"In Progress",IF(X9="Need Loan","Pending Start","—")))) | Z9: =IF(A9="","",IF(X9="Disbursed","Disbursed",IF(X9="Sanctioned","Sanctioned - Awaiting Disbursement","Not Disbursed"))) | AA9: =IF(A9="","",IF(LOWER(TRIM('01_Master_Data'!AI9&""))="yes","Need FLDG",IF(LOWER(TRIM('01_Master_Data'!AK9&""))="yes","Need Vidyalakshmi",IF(LOWER(TRIM('01_Master_Data'!AJ9&""))="yes","Need Review",IF(LOWER(J9)="critical","Critical",IF(LOWER(U9)="risk","Risk Case",IF(X9="Refund","Refund","Normal"))))))) | AB9: =IF(A9="","",IF(OR(LOWER(J9)="critical",LOWER(TRIM('01_Master_Data'!AI9&""))="yes",LOWER(TRIM('01_Master_Data'!AK9&""))="yes",LOWER(U9)="risk"),"Yes","No")) | AC9: =IF(A9="","",IF(LOWER(TRIM('01_Master_Data'!AI9&""))="yes","Yes","No")) | AD9: =IF(A9="","",IF(LOWER(TRIM('01_Master_Data'!AK9&""))="yes","Yes","No")) | AE9: =IF(A9="","",IF(LOWER(TRIM('01_Master_Data'!AJ9&""))="yes","Yes","No")) | AF9: =IF(A9="","",TRIM('01_Master_Data'!AL9&"")) | AG9: =IF(A9="","",IF(AF9="","—",IF(ISNUMBER(SEARCH("DNP",AF9)),"Unreachable / DNP",IF(ISNUMBER(SEARCH("interest",LOWER(AF9))),"High Interest / Terms",IF(OR(ISNUMBER(SEARCH("eligib",LOWER(AF9))),ISNUMBER(SEARCH("income",LOWER(AF9)))),"Eligibility / Income",IF(OR(ISNUMBER(SEARCH("start",LOWER(AF9))),ISNUMBER(SEARCH("Newer",AF9)),ISNUMBER(SEARCH("Will start",AF9))),"Process Yet to Start",IF(ISNUMBER(SEARCH("sure",LOWER(AF9))),"Undecided",IF(OR(ISNUMBER(SEARCH("reject",LOWER(AF9))),ISNUMBER(SEARCH("SBI",AF9))),"Rejected Elsewhere",IF(ISNUMBER(SEARCH("call",LOWER(AF9))),"Bank Communication",IF(OR(ISNUMBER(SEARCH("father",LOWER(AF9))),ISNUMBER(SEARCH("sister",LOWER(AF9)))),"Family / Dependency","Other")))))))))) | AH9: =IF(A9="","",'01_Master_Data'!AC9) | AI9: =IF(A9="","",IF(OR(AH9="",NOT(ISNUMBER(AH9))),"",MAX(0,'02_Configuration'!$B$82-AH9))) | AJ9: =IF(A9="","",IF(AI9="","Unknown",IF(AI9<=3,"0–3 Days",IF(AI9<=7,"4–7 Days",IF(AI9<=15,"8–15 Days",IF(AI9<=30,"16–30 Days","30+ Days")))))) | AK9: =IF(A9="","",IF(LOWER(H9)="yes","Yes","No")) | AL9: =IF(A9="","",'01_Master_Data'!T9) | AM9: =IF(A9="","",'01_Master_Data'!S9) | AN9: =IF(A9="","",'01_Master_Data'!I9) | AO9: =IF(A9="","",'01_Master_Data'!M9) | AP9: =IF(A9="","",IF(ISNUMBER(SEARCH("Icici",W9&"")),1,0)) | AQ9: =IF(A9="","",IF(ISNUMBER(SEARCH("Propelld",W9&"")),1,0)) | AR9: =IF(A9="","",IF(ISNUMBER(SEARCH("GyanDhan",W9&"")),1,0)) | AS9: =IF(A9="","",IF(ISNUMBER(SEARCH("vidyalakshmi",LOWER(W9&""))),1,0)) | AT9: =IF(A9="","",IF(ISNUMBER(SEARCH("other bank",LOWER(W9&""))),1,0)) | AU9: =IF(A9="","",IF(ISNUMBER(SEARCH("sanctioned",LOWER(W9&""))),1,0)) | AV9: =IF(A9="","",IF(ISNUMBER(SEARCH("Docs Pending",W9&"")),1,0)) | AW9: =IF(A9="","",IF(OR(X9="Rejected",ISNUMBER(SEARCH("Not eligbile",W9&""))),1,0))
A10: =IF('01_Master_Data'!B10="","",9) | B10: =IF('01_Master_Data'!B10="","",IF('01_Master_Data'!C10<>"","MOB|"&TEXT('01_Master_Data'!C10,"0"),IF('01_Master_Data'!D10<>"","PID|"&TRIM('01_Master_Data'!D10&""),""))) | C10: =IF('01_Master_Data'!B10="","",'01_Master_Data'!B10) | D10: =IF('01_Master_Data'!B10="","",'01_Master_Data'!C10) | E10: =IF('01_Master_Data'!B10="","",'01_Master_Data'!D10) | F10: =IF('01_Master_Data'!B10="","",'01_Master_Data'!E10) | G10: =IF('01_Master_Data'!B10="","",IFERROR(VLOOKUP(TRIM('01_Master_Data'!E10&""),'02_Configuration'!$A$40:$B$44,2,FALSE),UPPER(TRIM('01_Master_Data'!E10&"")))) | H10: =IF('01_Master_Data'!B10="","",IF('01_Master_Data'!U10="","",TRIM('01_Master_Data'!U10&""))) | I10: =IF('01_Master_Data'!B10="","",TRIM('01_Master_Data'!F10&"")) | J10: =IF('01_Master_Data'!B10="","",TRIM('01_Master_Data'!G10&"")) | K10: =IF('01_Master_Data'!B10="","",'01_Master_Data'!H10) | L10: =IF('01_Master_Data'!B10="","",IF(LOWER(TRIM('01_Master_Data'!V10&""))="yes",1,0)) | M10: =IF('01_Master_Data'!B10="","",IF(LOWER(TRIM('01_Master_Data'!W10&""))="yes",1,0)) | N10: =IF('01_Master_Data'!B10="","",IF(LOWER(TRIM('01_Master_Data'!X10&""))="yes",1,0)) | O10: =IF('01_Master_Data'!B10="","",IF(LOWER(TRIM('01_Master_Data'!Y10&""))="yes",1,0)) | P10: =IF('01_Master_Data'!B10="","",IF(LOWER(TRIM('01_Master_Data'!Z10&""))="yes",1,0)) | Q10: =IF(A10="","",L10+M10+N10+O10+P10) | R10: =IF(A10="","",IF(Q10>1,"Yes","No")) | S10: =IF(A10="","",TEXTJOIN(", ",TRUE,IF(L10=1,"ICICI",""),IF(M10=1,"Propelld",""),IF(N10=1,"Study4Buddy",""),IF(O10=1,"Poonawala Fincorp",""),IF(P10=1,"GyanDhan",""))) | T10: =IF(A10="","",IF(L10=1,"ICICI",IF(M10=1,"Propelld",IF(P10=1,"GyanDhan",IF(N10=1,"Study4Buddy",IF(O10=1,"Poonawala Fincorp",IF(ISNUMBER(SEARCH("GyanDhan",W10&"")),"GyanDhan",IF(ISNUMBER(SEARCH("Icici",W10&"")),"ICICI",IF(ISNUMBER(SEARCH("Propelld",W10&"")),"Propelld",IF(ISNUMBER(SEARCH("vidyalakshmi",LOWER(W10&"")),"PM Vidyalakshmi","—")))))))))) | U10: =IF(A10="","",TRIM('01_Master_Data'!AA10&"")) | V10: =IF(A10="","",TRIM('01_Master_Data'!AG10&"")) | W10: =IF(A10="","",TRIM('01_Master_Data'!AH10&"")) | X10: =IF(A10="","",IF(OR(LOWER(H10)="refund",LOWER(U10)="refund case"),"Refund",IF(OR(LOWER(H10)="dnp",LOWER(U10)="dnp"),"DNP",IF(OR(LOWER(V10)="disbursed",ISNUMBER(SEARCH("Disbursed",W10&""))),"Disbursed",IF(OR(LOWER(V10)="loan proccessed/accepted",ISNUMBER(SEARCH("sanctioned",LOWER(W10&"")))),"Sanctioned",IF(OR(LOWER(V10)="rejected",ISNUMBER(SEARCH("Not eligbile",W10&"")),ISNUMBER(SEARCH("Not eligible",W10&""))),"Rejected",IF(ISNUMBER(SEARCH("Docs Pending",W10&"")),"Documents Pending",IF(AND(LOWER(H10)="yes",LOWER(V10)="ongoing"),"Processing",IF(AND(LOWER(H10)="yes",Q10>0,OR(V10="",LOWER(V10)="not even started")),"Vendor Assigned",IF(AND(LOWER(H10)="yes",LOWER(V10)="not even started"),"Need Loan",IF(LOWER(H10)="yes","Loan Started",IF(LOWER(H10)="not sure","Interested",IF(OR(LOWER(H10)="no",LOWER(V10)="not required"),"Not Required","Unclassified"))))))))))))) | Y10: =IF(A10="","",IF(OR(X10="Sanctioned",X10="Disbursed",X10="Approved"),"Approved",IF(X10="Rejected","Rejected",IF(OR(X10="Processing",X10="Documents Pending",X10="Vendor Assigned"),"In Progress",IF(X10="Need Loan","Pending Start","—")))) | Z10: =IF(A10="","",IF(X10="Disbursed","Disbursed",IF(X10="Sanctioned","Sanctioned - Awaiting Disbursement","Not Disbursed"))) | AA10: =IF(A10="","",IF(LOWER(TRIM('01_Master_Data'!AI10&""))="yes","Need FLDG",IF(LOWER(TRIM('01_Master_Data'!AK10&""))="yes","Need Vidyalakshmi",IF(LOWER(TRIM('01_Master_Data'!AJ10&""))="yes","Need Review",IF(LOWER(J10)="critical","Critical",IF(LOWER(U10)="risk","Risk Case",IF(X10="Refund","Refund","Normal"))))))) | AB10: =IF(A10="","",IF(OR(LOWER(J10)="critical",LOWER(TRIM('01_Master_Data'!AI10&""))="yes",LOWER(TRIM('01_Master_Data'!AK10&""))="yes",LOWER(U10)="risk"),"Yes","No")) | AC10: =IF(A10="","",IF(LOWER(TRIM('01_Master_Data'!AI10&""))="yes","Yes","No")) | AD10: =IF(A10="","",IF(LOWER(TRIM('01_Master_Data'!AK10&""))="yes","Yes","No")) | AE10: =IF(A10="","",IF(LOWER(TRIM('01_Master_Data'!AJ10&""))="yes","Yes","No")) | AF10: =IF(A10="","",TRIM('01_Master_Data'!AL10&"")) | AG10: =IF(A10="","",IF(AF10="","—",IF(ISNUMBER(SEARCH("DNP",AF10)),"Unreachable / DNP",IF(ISNUMBER(SEARCH("interest",LOWER(AF10))),"High Interest / Terms",IF(OR(ISNUMBER(SEARCH("eligib",LOWER(AF10))),ISNUMBER(SEARCH("income",LOWER(AF10)))),"Eligibility / Income",IF(OR(ISNUMBER(SEARCH("start",LOWER(AF10))),ISNUMBER(SEARCH("Newer",AF10)),ISNUMBER(SEARCH("Will start",AF10))),"Process Yet to Start",IF(ISNUMBER(SEARCH("sure",LOWER(AF10))),"Undecided",IF(OR(ISNUMBER(SEARCH("reject",LOWER(AF10))),ISNUMBER(SEARCH("SBI",AF10))),"Rejected Elsewhere",IF(ISNUMBER(SEARCH("call",LOWER(AF10))),"Bank Communication",IF(OR(ISNUMBER(SEARCH("father",LOWER(AF10))),ISNUMBER(SEARCH("sister",LOWER(AF10)))),"Family / Dependency","Other")))))))))) | AH10: =IF(A10="","",'01_Master_Data'!AC10) | AI10: =IF(A10="","",IF(OR(AH10="",NOT(ISNUMBER(AH10))),"",MAX(0,'02_Configuration'!$B$82-AH10))) | AJ10: =IF(A10="","",IF(AI10="","Unknown",IF(AI10<=3,"0–3 Days",IF(AI10<=7,"4–7 Days",IF(AI10<=15,"8–15 Days",IF(AI10<=30,"16–30 Days","30+ Days")))))) | AK10: =IF(A10="","",IF(LOWER(H10)="yes","Yes","No")) | AL10: =IF(A10="","",'01_Master_Data'!T10) | AM10: =IF(A10="","",'01_Master_Data'!S10) | AN10: =IF(A10="","",'01_Master_Data'!I10) | AO10: =IF(A10="","",'01_Master_Data'!M10) | AP10: =IF(A10="","",IF(ISNUMBER(SEARCH("Icici",W10&"")),1,0)) | AQ10: =IF(A10="","",IF(ISNUMBER(SEARCH("Propelld",W10&"")),1,0)) | AR10: =IF(A10="","",IF(ISNUMBER(SEARCH("GyanDhan",W10&"")),1,0)) | AS10: =IF(A10="","",IF(ISNUMBER(SEARCH("vidyalakshmi",LOWER(W10&""))),1,0)) | AT10: =IF(A10="","",IF(ISNUMBER(SEARCH("other bank",LOWER(W10&""))),1,0)) | AU10: =IF(A10="","",IF(ISNUMBER(SEARCH("sanctioned",LOWER(W10&""))),1,0)) | AV10: =IF(A10="","",IF(ISNUMBER(SEARCH("Docs Pending",W10&"")),1,0)) | AW10: =IF(A10="","",IF(OR(X10="Rejected",ISNUMBER(SEARCH("Not eligbile",W10&""))),1,0))
A11: =IF('01_Master_Data'!B11="","",10) | B11: =IF('01_Master_Data'!B11="","",IF('01_Master_Data'!C11<>"","MOB|"&TEXT('01_Master_Data'!C11,"0"),IF('01_Master_Data'!D11<>"","PID|"&TRIM('01_Master_Data'!D11&""),""))) | C11: =IF('01_Master_Data'!B11="","",'01_Master_Data'!B11) | D11: =IF('01_Master_Data'!B11="","",'01_Master_Data'!C11) | E11: =IF('01_Master_Data'!B11="","",'01_Master_Data'!D11) | F11: =IF('01_Master_Data'!B11="","",'01_Master_Data'!E11) | G11: =IF('01_Master_Data'!B11="","",IFERROR(VLOOKUP(TRIM('01_Master_Data'!E11&""),'02_Configuration'!$A$40:$B$44,2,FALSE),UPPER(TRIM('01_Master_Data'!E11&"")))) | H11: =IF('01_Master_Data'!B11="","",IF('01_Master_Data'!U11="","",TRIM('01_Master_Data'!U11&""))) | I11: =IF('01_Master_Data'!B11="","",TRIM('01_Master_Data'!F11&"")) | J11: =IF('01_Master_Data'!B11="","",TRIM('01_Master_Data'!G11&"")) | K11: =IF('01_Master_Data'!B11="","",'01_Master_Data'!H11) | L11: =IF('01_Master_Data'!B11="","",IF(LOWER(TRIM('01_Master_Data'!V11&""))="yes",1,0)) | M11: =IF('01_Master_Data'!B11="","",IF(LOWER(TRIM('01_Master_Data'!W11&""))="yes",1,0)) | N11: =IF('01_Master_Data'!B11="","",IF(LOWER(TRIM('01_Master_Data'!X11&""))="yes",1,0)) | O11: =IF('01_Master_Data'!B11="","",IF(LOWER(TRIM('01_Master_Data'!Y11&""))="yes",1,0)) | P11: =IF('01_Master_Data'!B11="","",IF(LOWER(TRIM('01_Master_Data'!Z11&""))="yes",1,0)) | Q11: =IF(A11="","",L11+M11+N11+O11+P11) | R11: =IF(A11="","",IF(Q11>1,"Yes","No")) | S11: =IF(A11="","",TEXTJOIN(", ",TRUE,IF(L11=1,"ICICI",""),IF(M11=1,"Propelld",""),IF(N11=1,"Study4Buddy",""),IF(O11=1,"Poonawala Fincorp",""),IF(P11=1,"GyanDhan",""))) | T11: =IF(A11="","",IF(L11=1,"ICICI",IF(M11=1,"Propelld",IF(P11=1,"GyanDhan",IF(N11=1,"Study4Buddy",IF(O11=1,"Poonawala Fincorp",IF(ISNUMBER(SEARCH("GyanDhan",W11&"")),"GyanDhan",IF(ISNUMBER(SEARCH("Icici",W11&"")),"ICICI",IF(ISNUMBER(SEARCH("Propelld",W11&"")),"Propelld",IF(ISNUMBER(SEARCH("vidyalakshmi",LOWER(W11&"")),"PM Vidyalakshmi","—")))))))))) | U11: =IF(A11="","",TRIM('01_Master_Data'!AA11&"")) | V11: =IF(A11="","",TRIM('01_Master_Data'!AG11&"")) | W11: =IF(A11="","",TRIM('01_Master_Data'!AH11&"")) | X11: =IF(A11="","",IF(OR(LOWER(H11)="refund",LOWER(U11)="refund case"),"Refund",IF(OR(LOWER(H11)="dnp",LOWER(U11)="dnp"),"DNP",IF(OR(LOWER(V11)="disbursed",ISNUMBER(SEARCH("Disbursed",W11&""))),"Disbursed",IF(OR(LOWER(V11)="loan proccessed/accepted",ISNUMBER(SEARCH("sanctioned",LOWER(W11&"")))),"Sanctioned",IF(OR(LOWER(V11)="rejected",ISNUMBER(SEARCH("Not eligbile",W11&"")),ISNUMBER(SEARCH("Not eligible",W11&""))),"Rejected",IF(ISNUMBER(SEARCH("Docs Pending",W11&"")),"Documents Pending",IF(AND(LOWER(H11)="yes",LOWER(V11)="ongoing"),"Processing",IF(AND(LOWER(H11)="yes",Q11>0,OR(V11="",LOWER(V11)="not even started")),"Vendor Assigned",IF(AND(LOWER(H11)="yes",LOWER(V11)="not even started"),"Need Loan",IF(LOWER(H11)="yes","Loan Started",IF(LOWER(H11)="not sure","Interested",IF(OR(LOWER(H11)="no",LOWER(V11)="not required"),"Not Required","Unclassified"))))))))))))) | Y11: =IF(A11="","",IF(OR(X11="Sanctioned",X11="Disbursed",X11="Approved"),"Approved",IF(X11="Rejected","Rejected",IF(OR(X11="Processing",X11="Documents Pending",X11="Vendor Assigned"),"In Progress",IF(X11="Need Loan","Pending Start","—")))) | Z11: =IF(A11="","",IF(X11="Disbursed","Disbursed",IF(X11="Sanctioned","Sanctioned - Awaiting Disbursement","Not Disbursed"))) | AA11: =IF(A11="","",IF(LOWER(TRIM('01_Master_Data'!AI11&""))="yes","Need FLDG",IF(LOWER(TRIM('01_Master_Data'!AK11&""))="yes","Need Vidyalakshmi",IF(LOWER(TRIM('01_Master_Data'!AJ11&""))="yes","Need Review",IF(LOWER(J11)="critical","Critical",IF(LOWER(U11)="risk","Risk Case",IF(X11="Refund","Refund","Normal"))))))) | AB11: =IF(A11="","",IF(OR(LOWER(J11)="critical",LOWER(TRIM('01_Master_Data'!AI11&""))="yes",LOWER(TRIM('01_Master_Data'!AK11&""))="yes",LOWER(U11)="risk"),"Yes","No")) | AC11: =IF(A11="","",IF(LOWER(TRIM('01_Master_Data'!AI11&""))="yes","Yes","No")) | AD11: =IF(A11="","",IF(LOWER(TRIM('01_Master_Data'!AK11&""))="yes","Yes","No")) | AE11: =IF(A11="","",IF(LOWER(TRIM('01_Master_Data'!AJ11&""))="yes","Yes","No")) | AF11: =IF(A11="","",TRIM('01_Master_Data'!AL11&"")) | AG11: =IF(A11="","",IF(AF11="","—",IF(ISNUMBER(SEARCH("DNP",AF11)),"Unreachable / DNP",IF(ISNUMBER(SEARCH("interest",LOWER(AF11))),"High Interest / Terms",IF(OR(ISNUMBER(SEARCH("eligib",LOWER(AF11))),ISNUMBER(SEARCH("income",LOWER(AF11)))),"Eligibility / Income",IF(OR(ISNUMBER(SEARCH("start",LOWER(AF11))),ISNUMBER(SEARCH("Newer",AF11)),ISNUMBER(SEARCH("Will start",AF11))),"Process Yet to Start",IF(ISNUMBER(SEARCH("sure",LOWER(AF11))),"Undecided",IF(OR(ISNUMBER(SEARCH("reject",LOWER(AF11))),ISNUMBER(SEARCH("SBI",AF11))),"Rejected Elsewhere",IF(ISNUMBER(SEARCH("call",LOWER(AF11))),"Bank Communication",IF(OR(ISNUMBER(SEARCH("father",LOWER(AF11))),ISNUMBER(SEARCH("sister",LOWER(AF11)))),"Family / Dependency","Other")))))))))) | AH11: =IF(A11="","",'01_Master_Data'!AC11) | AI11: =IF(A11="","",IF(OR(AH11="",NOT(ISNUMBER(AH11))),"",MAX(0,'02_Configuration'!$B$82-AH11))) | AJ11: =IF(A11="","",IF(AI11="","Unknown",IF(AI11<=3,"0–3 Days",IF(AI11<=7,"4–7 Days",IF(AI11<=15,"8–15 Days",IF(AI11<=30,"16–30 Days","30+ Days")))))) | AK11: =IF(A11="","",IF(LOWER(H11)="yes","Yes","No")) | AL11: =IF(A11="","",'01_Master_Data'!T11) | AM11: =IF(A11="","",'01_Master_Data'!S11) | AN11: =IF(A11="","",'01_Master_Data'!I11) | AO11: =IF(A11="","",'01_Master_Data'!M11) | AP11: =IF(A11="","",IF(ISNUMBER(SEARCH("Icici",W11&"")),1,0)) | AQ11: =IF(A11="","",IF(ISNUMBER(SEARCH("Propelld",W11&"")),1,0)) | AR11: =IF(A11="","",IF(ISNUMBER(SEARCH("GyanDhan",W11&"")),1,0)) | AS11: =IF(A11="","",IF(ISNUMBER(SEARCH("vidyalakshmi",LOWER(W11&""))),1,0)) | AT11: =IF(A11="","",IF(ISNUMBER(SEARCH("other bank",LOWER(W11&""))),1,0)) | AU11: =IF(A11="","",IF(ISNUMBER(SEARCH("sanctioned",LOWER(W11&""))),1,0)) | AV11: =IF(A11="","",IF(ISNUMBER(SEARCH("Docs Pending",W11&"")),1,0)) | AW11: =IF(A11="","",IF(OR(X11="Rejected",ISNUMBER(SEARCH("Not eligbile",W11&""))),1,0))
A12: =IF('01_Master_Data'!B12="","",11) | B12: =IF('01_Master_Data'!B12="","",IF('01_Master_Data'!C12<>"","MOB|"&TEXT('01_Master_Data'!C12,"0"),IF('01_Master_Data'!D12<>"","PID|"&TRIM('01_Master_Data'!D12&""),""))) | C12: =IF('01_Master_Data'!B12="","",'01_Master_Data'!B12) | D12: =IF('01_Master_Data'!B12="","",'01_Master_Data'!C12) | E12: =IF('01_Master_Data'!B12="","",'01_Master_Data'!D12) | F12: =IF('01_Master_Data'!B12="","",'01_Master_Data'!E12) | G12: =IF('01_Master_Data'!B12="","",IFERROR(VLOOKUP(TRIM('01_Master_Data'!E12&""),'02_Configuration'!$A$40:$B$44,2,FALSE),UPPER(TRIM('01_Master_Data'!E12&"")))) | H12: =IF('01_Master_Data'!B12="","",IF('01_Master_Data'!U12="","",TRIM('01_Master_Data'!U12&""))) | I12: =IF('01_Master_Data'!B12="","",TRIM('01_Master_Data'!F12&"")) | J12: =IF('01_Master_Data'!B12="","",TRIM('01_Master_Data'!G12&"")) | K12: =IF('01_Master_Data'!B12="","",'01_Master_Data'!H12) | L12: =IF('01_Master_Data'!B12="","",IF(LOWER(TRIM('01_Master_Data'!V12&""))="yes",1,0)) | M12: =IF('01_Master_Data'!B12="","",IF(LOWER(TRIM('01_Master_Data'!W12&""))="yes",1,0)) | N12: =IF('01_Master_Data'!B12="","",IF(LOWER(TRIM('01_Master_Data'!X12&""))="yes",1,0)) | O12: =IF('01_Master_Data'!B12="","",IF(LOWER(TRIM('01_Master_Data'!Y12&""))="yes",1,0)) | P12: =IF('01_Master_Data'!B12="","",IF(LOWER(TRIM('01_Master_Data'!Z12&""))="yes",1,0)) | Q12: =IF(A12="","",L12+M12+N12+O12+P12) | R12: =IF(A12="","",IF(Q12>1,"Yes","No")) | S12: =IF(A12="","",TEXTJOIN(", ",TRUE,IF(L12=1,"ICICI",""),IF(M12=1,"Propelld",""),IF(N12=1,"Study4Buddy",""),IF(O12=1,"Poonawala Fincorp",""),IF(P12=1,"GyanDhan",""))) | T12: =IF(A12="","",IF(L12=1,"ICICI",IF(M12=1,"Propelld",IF(P12=1,"GyanDhan",IF(N12=1,"Study4Buddy",IF(O12=1,"Poonawala Fincorp",IF(ISNUMBER(SEARCH("GyanDhan",W12&"")),"GyanDhan",IF(ISNUMBER(SEARCH("Icici",W12&"")),"ICICI",IF(ISNUMBER(SEARCH("Propelld",W12&"")),"Propelld",IF(ISNUMBER(SEARCH("vidyalakshmi",LOWER(W12&"")),"PM Vidyalakshmi","—")))))))))) | U12: =IF(A12="","",TRIM('01_Master_Data'!AA12&"")) | V12: =IF(A12="","",TRIM('01_Master_Data'!AG12&"")) | W12: =IF(A12="","",TRIM('01_Master_Data'!AH12&"")) | X12: =IF(A12="","",IF(OR(LOWER(H12)="refund",LOWER(U12)="refund case"),"Refund",IF(OR(LOWER(H12)="dnp",LOWER(U12)="dnp"),"DNP",IF(OR(LOWER(V12)="disbursed",ISNUMBER(SEARCH("Disbursed",W12&""))),"Disbursed",IF(OR(LOWER(V12)="loan proccessed/accepted",ISNUMBER(SEARCH("sanctioned",LOWER(W12&"")))),"Sanctioned",IF(OR(LOWER(V12)="rejected",ISNUMBER(SEARCH("Not eligbile",W12&"")),ISNUMBER(SEARCH("Not eligible",W12&""))),"Rejected",IF(ISNUMBER(SEARCH("Docs Pending",W12&"")),"Documents Pending",IF(AND(LOWER(H12)="yes",LOWER(V12)="ongoing"),"Processing",IF(AND(LOWER(H12)="yes",Q12>0,OR(V12="",LOWER(V12)="not even started")),"Vendor Assigned",IF(AND(LOWER(H12)="yes",LOWER(V12)="not even started"),"Need Loan",IF(LOWER(H12)="yes","Loan Started",IF(LOWER(H12)="not sure","Interested",IF(OR(LOWER(H12)="no",LOWER(V12)="not required"),"Not Required","Unclassified"))))))))))))) | Y12: =IF(A12="","",IF(OR(X12="Sanctioned",X12="Disbursed",X12="Approved"),"Approved",IF(X12="Rejected","Rejected",IF(OR(X12="Processing",X12="Documents Pending",X12="Vendor Assigned"),"In Progress",IF(X12="Need Loan","Pending Start","—")))) | Z12: =IF(A12="","",IF(X12="Disbursed","Disbursed",IF(X12="Sanctioned","Sanctioned - Awaiting Disbursement","Not Disbursed"))) | AA12: =IF(A12="","",IF(LOWER(TRIM('01_Master_Data'!AI12&""))="yes","Need FLDG",IF(LOWER(TRIM('01_Master_Data'!AK12&""))="yes","Need Vidyalakshmi",IF(LOWER(TRIM('01_Master_Data'!AJ12&""))="yes","Need Review",IF(LOWER(J12)="critical","Critical",IF(LOWER(U12)="risk","Risk Case",IF(X12="Refund","Refund","Normal"))))))) | AB12: =IF(A12="","",IF(OR(LOWER(J12)="critical",LOWER(TRIM('01_Master_Data'!AI12&""))="yes",LOWER(TRIM('01_Master_Data'!AK12&""))="yes",LOWER(U12)="risk"),"Yes","No")) | AC12: =IF(A12="","",IF(LOWER(TRIM('01_Master_Data'!AI12&""))="yes","Yes","No")) | AD12: =IF(A12="","",IF(LOWER(TRIM('01_Master_Data'!AK12&""))="yes","Yes","No")) | AE12: =IF(A12="","",IF(LOWER(TRIM('01_Master_Data'!AJ12&""))="yes","Yes","No")) | AF12: =IF(A12="","",TRIM('01_Master_Data'!AL12&"")) | AG12: =IF(A12="","",IF(AF12="","—",IF(ISNUMBER(SEARCH("DNP",AF12)),"Unreachable / DNP",IF(ISNUMBER(SEARCH("interest",LOWER(AF12))),"High Interest / Terms",IF(OR(ISNUMBER(SEARCH("eligib",LOWER(AF12))),ISNUMBER(SEARCH("income",LOWER(AF12)))),"Eligibility / Income",IF(OR(ISNUMBER(SEARCH("start",LOWER(AF12))),ISNUMBER(SEARCH("Newer",AF12)),ISNUMBER(SEARCH("Will start",AF12))),"Process Yet to Start",IF(ISNUMBER(SEARCH("sure",LOWER(AF12))),"Undecided",IF(OR(ISNUMBER(SEARCH("reject",LOWER(AF12))),ISNUMBER(SEARCH("SBI",AF12))),"Rejected Elsewhere",IF(ISNUMBER(SEARCH("call",LOWER(AF12))),"Bank Communication",IF(OR(ISNUMBER(SEARCH("father",LOWER(AF12))),ISNUMBER(SEARCH("sister",LOWER(AF12)))),"Family / Dependency","Other")))))))))) | AH12: =IF(A12="","",'01_Master_Data'!AC12) | AI12: =IF(A12="","",IF(OR(AH12="",NOT(ISNUMBER(AH12))),"",MAX(0,'02_Configuration'!$B$82-AH12))) | AJ12: =IF(A12="","",IF(AI12="","Unknown",IF(AI12<=3,"0–3 Days",IF(AI12<=7,"4–7 Days",IF(AI12<=15,"8–15 Days",IF(AI12<=30,"16–30 Days","30+ Days")))))) | AK12: =IF(A12="","",IF(LOWER(H12)="yes","Yes","No")) | AL12: =IF(A12="","",'01_Master_Data'!T12) | AM12: =IF(A12="","",'01_Master_Data'!S12) | AN12: =IF(A12="","",'01_Master_Data'!I12) | AO12: =IF(A12="","",'01_Master_Data'!M12) | AP12: =IF(A12="","",IF(ISNUMBER(SEARCH("Icici",W12&"")),1,0)) | AQ12: =IF(A12="","",IF(ISNUMBER(SEARCH("Propelld",W12&"")),1,0)) | AR12: =IF(A12="","",IF(ISNUMBER(SEARCH("GyanDhan",W12&"")),1,0)) | AS12: =IF(A12="","",IF(ISNUMBER(SEARCH("vidyalakshmi",LOWER(W12&""))),1,0)) | AT12: =IF(A12="","",IF(ISNUMBER(SEARCH("other bank",LOWER(W12&""))),1,0)) | AU12: =IF(A12="","",IF(ISNUMBER(SEARCH("sanctioned",LOWER(W12&""))),1,0)) | AV12: =IF(A12="","",IF(ISNUMBER(SEARCH("Docs Pending",W12&"")),1,0)) | AW12: =IF(A12="","",IF(OR(X12="Rejected",ISNUMBER(SEARCH("Not eligbile",W12&""))),1,0))
A13: =IF('01_Master_Data'!B13="","",12) | B13: =IF('01_Master_Data'!B13="","",IF('01_Master_Data'!C13<>"","MOB|"&TEXT('01_Master_Data'!C13,"0"),IF('01_Master_Data'!D13<>"","PID|"&TRIM('01_Master_Data'!D13&""),""))) | C13: =IF('01_Master_Data'!B13="","",'01_Master_Data'!B13) | D13: =IF('01_Master_Data'!B13="","",'01_Master_Data'!C13) | E13: =IF('01_Master_Data'!B13="","",'01_Master_Data'!D13) | F13: =IF('01_Master_Data'!B13="","",'01_Master_Data'!E13) | G13: =IF('01_Master_Data'!B13="","",IFERROR(VLOOKUP(TRIM('01_Master_Data'!E13&""),'02_Configuration'!$A$40:$B$44,2,FALSE),UPPER(TRIM('01_Master_Data'!E13&"")))) | H13: =IF('01_Master_Data'!B13="","",IF('01_Master_Data'!U13="","",TRIM('01_Master_Data'!U13&""))) | I13: =IF('01_Master_Data'!B13="","",TRIM('01_Master_Data'!F13&"")) | J13: =IF('01_Master_Data'!B13="","",TRIM('01_Master_Data'!G13&"")) | K13: =IF('01_Master_Data'!B13="","",'01_Master_Data'!H13) | L13: =IF('01_Master_Data'!B13="","",IF(LOWER(TRIM('01_Master_Data'!V13&""))="yes",1,0)) | M13: =IF('01_Master_Data'!B13="","",IF(LOWER(TRIM('01_Master_Data'!W13&""))="yes",1,0)) | N13: =IF('01_Master_Data'!B13="","",IF(LOWER(TRIM('01_Master_Data'!X13&""))="yes",1,0)) | O13: =IF('01_Master_Data'!B13="","",IF(LOWER(TRIM('01_Master_Data'!Y13&""))="yes",1,0)) | P13: =IF('01_Master_Data'!B13="","",IF(LOWER(TRIM('01_Master_Data'!Z13&""))="yes",1,0)) | Q13: =IF(A13="","",L13+M13+N13+O13+P13) | R13: =IF(A13="","",IF(Q13>1,"Yes","No")) | S13: =IF(A13="","",TEXTJOIN(", ",TRUE,IF(L13=1,"ICICI",""),IF(M13=1,"Propelld",""),IF(N13=1,"Study4Buddy",""),IF(O13=1,"Poonawala Fincorp",""),IF(P13=1,"GyanDhan",""))) | T13: =IF(A13="","",IF(L13=1,"ICICI",IF(M13=1,"Propelld",IF(P13=1,"GyanDhan",IF(N13=1,"Study4Buddy",IF(O13=1,"Poonawala Fincorp",IF(ISNUMBER(SEARCH("GyanDhan",W13&"")),"GyanDhan",IF(ISNUMBER(SEARCH("Icici",W13&"")),"ICICI",IF(ISNUMBER(SEARCH("Propelld",W13&"")),"Propelld",IF(ISNUMBER(SEARCH("vidyalakshmi",LOWER(W13&"")),"PM Vidyalakshmi","—")))))))))) | U13: =IF(A13="","",TRIM('01_Master_Data'!AA13&"")) | V13: =IF(A13="","",TRIM('01_Master_Data'!AG13&"")) | W13: =IF(A13="","",TRIM('01_Master_Data'!AH13&"")) | X13: =IF(A13="","",IF(OR(LOWER(H13)="refund",LOWER(U13)="refund case"),"Refund",IF(OR(LOWER(H13)="dnp",LOWER(U13)="dnp"),"DNP",IF(OR(LOWER(V13)="disbursed",ISNUMBER(SEARCH("Disbursed",W13&""))),"Disbursed",IF(OR(LOWER(V13)="loan proccessed/accepted",ISNUMBER(SEARCH("sanctioned",LOWER(W13&"")))),"Sanctioned",IF(OR(LOWER(V13)="rejected",ISNUMBER(SEARCH("Not eligbile",W13&"")),ISNUMBER(SEARCH("Not eligible",W13&""))),"Rejected",IF(ISNUMBER(SEARCH("Docs Pending",W13&"")),"Documents Pending",IF(AND(LOWER(H13)="yes",LOWER(V13)="ongoing"),"Processing",IF(AND(LOWER(H13)="yes",Q13>0,OR(V13="",LOWER(V13)="not even started")),"Vendor Assigned",IF(AND(LOWER(H13)="yes",LOWER(V13)="not even started"),"Need Loan",IF(LOWER(H13)="yes","Loan Started",IF(LOWER(H13)="not sure","Interested",IF(OR(LOWER(H13)="no",LOWER(V13)="not required"),"Not Required","Unclassified"))))))))))))) | Y13: =IF(A13="","",IF(OR(X13="Sanctioned",X13="Disbursed",X13="Approved"),"Approved",IF(X13="Rejected","Rejected",IF(OR(X13="Processing",X13="Documents Pending",X13="Vendor Assigned"),"In Progress",IF(X13="Need Loan","Pending Start","—")))) | Z13: =IF(A13="","",IF(X13="Disbursed","Disbursed",IF(X13="Sanctioned","Sanctioned - Awaiting Disbursement","Not Disbursed"))) | AA13: =IF(A13="","",IF(LOWER(TRIM('01_Master_Data'!AI13&""))="yes","Need FLDG",IF(LOWER(TRIM('01_Master_Data'!AK13&""))="yes","Need Vidyalakshmi",IF(LOWER(TRIM('01_Master_Data'!AJ13&""))="yes","Need Review",IF(LOWER(J13)="critical","Critical",IF(LOWER(U13)="risk","Risk Case",IF(X13="Refund","Refund","Normal"))))))) | AB13: =IF(A13="","",IF(OR(LOWER(J13)="critical",LOWER(TRIM('01_Master_Data'!AI13&""))="yes",LOWER(TRIM('01_Master_Data'!AK13&""))="yes",LOWER(U13)="risk"),"Yes","No")) | AC13: =IF(A13="","",IF(LOWER(TRIM('01_Master_Data'!AI13&""))="yes","Yes","No")) | AD13: =IF(A13="","",IF(LOWER(TRIM('01_Master_Data'!AK13&""))="yes","Yes","No")) | AE13: =IF(A13="","",IF(LOWER(TRIM('01_Master_Data'!AJ13&""))="yes","Yes","No")) | AF13: =IF(A13="","",TRIM('01_Master_Data'!AL13&"")) | AG13: =IF(A13="","",IF(AF13="","—",IF(ISNUMBER(SEARCH("DNP",AF13)),"Unreachable / DNP",IF(ISNUMBER(SEARCH("interest",LOWER(AF13))),"High Interest / Terms",IF(OR(ISNUMBER(SEARCH("eligib",LOWER(AF13))),ISNUMBER(SEARCH("income",LOWER(AF13)))),"Eligibility / Income",IF(OR(ISNUMBER(SEARCH("start",LOWER(AF13))),ISNUMBER(SEARCH("Newer",AF13)),ISNUMBER(SEARCH("Will start",AF13))),"Process Yet to Start",IF(ISNUMBER(SEARCH("sure",LOWER(AF13))),"Undecided",IF(OR(ISNUMBER(SEARCH("reject",LOWER(AF13))),ISNUMBER(SEARCH("SBI",AF13))),"Rejected Elsewhere",IF(ISNUMBER(SEARCH("call",LOWER(AF13))),"Bank Communication",IF(OR(ISNUMBER(SEARCH("father",LOWER(AF13))),ISNUMBER(SEARCH("sister",LOWER(AF13)))),"Family / Dependency","Other")))))))))) | AH13: =IF(A13="","",'01_Master_Data'!AC13) | AI13: =IF(A13="","",IF(OR(AH13="",NOT(ISNUMBER(AH13))),"",MAX(0,'02_Configuration'!$B$82-AH13))) | AJ13: =IF(A13="","",IF(AI13="","Unknown",IF(AI13<=3,"0–3 Days",IF(AI13<=7,"4–7 Days",IF(AI13<=15,"8–15 Days",IF(AI13<=30,"16–30 Days","30+ Days")))))) | AK13: =IF(A13="","",IF(LOWER(H13)="yes","Yes","No")) | AL13: =IF(A13="","",'01_Master_Data'!T13) | AM13: =IF(A13="","",'01_Master_Data'!S13) | AN13: =IF(A13="","",'01_Master_Data'!I13) | AO13: =IF(A13="","",'01_Master_Data'!M13) | AP13: =IF(A13="","",IF(ISNUMBER(SEARCH("Icici",W13&"")),1,0)) | AQ13: =IF(A13="","",IF(ISNUMBER(SEARCH("Propelld",W13&"")),1,0)) | AR13: =IF(A13="","",IF(ISNUMBER(SEARCH("GyanDhan",W13&"")),1,0)) | AS13: =IF(A13="","",IF(ISNUMBER(SEARCH("vidyalakshmi",LOWER(W13&""))),1,0)) | AT13: =IF(A13="","",IF(ISNUMBER(SEARCH("other bank",LOWER(W13&""))),1,0)) | AU13: =IF(A13="","",IF(ISNUMBER(SEARCH("sanctioned",LOWER(W13&""))),1,0)) | AV13: =IF(A13="","",IF(ISNUMBER(SEARCH("Docs Pending",W13&"")),1,0)) | AW13: =IF(A13="","",IF(OR(X13="Rejected",ISNUMBER(SEARCH("Not eligbile",W13&""))),1,0))
A14: =IF('01_Master_Data'!B14="","",13) | B14: =IF('01_Master_Data'!B14="","",IF('01_Master_Data'!C14<>"","MOB|"&TEXT('01_Master_Data'!C14,"0"),IF('01_Master_Data'!D14<>"","PID|"&TRIM('01_Master_Data'!D14&""),""))) | C14: =IF('01_Master_Data'!B14="","",'01_Master_Data'!B14) | D14: =IF('01_Master_Data'!B14="","",'01_Master_Data'!C14) | E14: =IF('01_Master_Data'!B14="","",'01_Master_Data'!D14) | F14: =IF('01_Master_Data'!B14="","",'01_Master_Data'!E14) | G14: =IF('01_Master_Data'!B14="","",IFERROR(VLOOKUP(TRIM('01_Master_Data'!E14&""),'02_Configuration'!$A$40:$B$44,2,FALSE),UPPER(TRIM('01_Master_Data'!E14&"")))) | H14: =IF('01_Master_Data'!B14="","",IF('01_Master_Data'!U14="","",TRIM('01_Master_Data'!U14&""))) | I14: =IF('01_Master_Data'!B14="","",TRIM('01_Master_Data'!F14&"")) | J14: =IF('01_Master_Data'!B14="","",TRIM('01_Master_Data'!G14&"")) | K14: =IF('01_Master_Data'!B14="","",'01_Master_Data'!H14) | L14: =IF('01_Master_Data'!B14="","",IF(LOWER(TRIM('01_Master_Data'!V14&""))="yes",1,0)) | M14: =IF('01_Master_Data'!B14="","",IF(LOWER(TRIM('01_Master_Data'!W14&""))="yes",1,0)) | N14: =IF('01_Master_Data'!B14="","",IF(LOWER(TRIM('01_Master_Data'!X14&""))="yes",1,0)) | O14: =IF('01_Master_Data'!B14="","",IF(LOWER(TRIM('01_Master_Data'!Y14&""))="yes",1,0)) | P14: =IF('01_Master_Data'!B14="","",IF(LOWER(TRIM('01_Master_Data'!Z14&""))="yes",1,0)) | Q14: =IF(A14="","",L14+M14+N14+O14+P14) | R14: =IF(A14="","",IF(Q14>1,"Yes","No")) | S14: =IF(A14="","",TEXTJOIN(", ",TRUE,IF(L14=1,"ICICI",""),IF(M14=1,"Propelld",""),IF(N14=1,"Study4Buddy",""),IF(O14=1,"Poonawala Fincorp",""),IF(P14=1,"GyanDhan",""))) | T14: =IF(A14="","",IF(L14=1,"ICICI",IF(M14=1,"Propelld",IF(P14=1,"GyanDhan",IF(N14=1,"Study4Buddy",IF(O14=1,"Poonawala Fincorp",IF(ISNUMBER(SEARCH("GyanDhan",W14&"")),"GyanDhan",IF(ISNUMBER(SEARCH("Icici",W14&"")),"ICICI",IF(ISNUMBER(SEARCH("Propelld",W14&"")),"Propelld",IF(ISNUMBER(SEARCH("vidyalakshmi",LOWER(W14&"")),"PM Vidyalakshmi","—")))))))))) | U14: =IF(A14="","",TRIM('01_Master_Data'!AA14&"")) | V14: =IF(A14="","",TRIM('01_Master_Data'!AG14&"")) | W14: =IF(A14="","",TRIM('01_Master_Data'!AH14&"")) | X14: =IF(A14="","",IF(OR(LOWER(H14)="refund",LOWER(U14)="refund case"),"Refund",IF(OR(LOWER(H14)="dnp",LOWER(U14)="dnp"),"DNP",IF(OR(LOWER(V14)="disbursed",ISNUMBER(SEARCH("Disbursed",W14&""))),"Disbursed",IF(OR(LOWER(V14)="loan proccessed/accepted",ISNUMBER(SEARCH("sanctioned",LOWER(W14&"")))),"Sanctioned",IF(OR(LOWER(V14)="rejected",ISNUMBER(SEARCH("Not eligbile",W14&"")),ISNUMBER(SEARCH("Not eligible",W14&""))),"Rejected",IF(ISNUMBER(SEARCH("Docs Pending",W14&"")),"Documents Pending",IF(AND(LOWER(H14)="yes",LOWER(V14)="ongoing"),"Processing",IF(AND(LOWER(H14)="yes",Q14>0,OR(V14="",LOWER(V14)="not even started")),"Vendor Assigned",IF(AND(LOWER(H14)="yes",LOWER(V14)="not even started"),"Need Loan",IF(LOWER(H14)="yes","Loan Started",IF(LOWER(H14)="not sure","Interested",IF(OR(LOWER(H14)="no",LOWER(V14)="not required"),"Not Required","Unclassified"))))))))))))) | Y14: =IF(A14="","",IF(OR(X14="Sanctioned",X14="Disbursed",X14="Approved"),"Approved",IF(X14="Rejected","Rejected",IF(OR(X14="Processing",X14="Documents Pending",X14="Vendor Assigned"),"In Progress",IF(X14="Need Loan","Pending Start","—")))) | Z14: =IF(A14="","",IF(X14="Disbursed","Disbursed",IF(X14="Sanctioned","Sanctioned - Awaiting Disbursement","Not Disbursed"))) | AA14: =IF(A14="","",IF(LOWER(TRIM('01_Master_Data'!AI14&""))="yes","Need FLDG",IF(LOWER(TRIM('01_Master_Data'!AK14&""))="yes","Need Vidyalakshmi",IF(LOWER(TRIM('01_Master_Data'!AJ14&""))="yes","Need Review",IF(LOWER(J14)="critical","Critical",IF(LOWER(U14)="risk","Risk Case",IF(X14="Refund","Refund","Normal"))))))) | AB14: =IF(A14="","",IF(OR(LOWER(J14)="critical",LOWER(TRIM('01_Master_Data'!AI14&""))="yes",LOWER(TRIM('01_Master_Data'!AK14&""))="yes",LOWER(U14)="risk"),"Yes","No")) | AC14: =IF(A14="","",IF(LOWER(TRIM('01_Master_Data'!AI14&""))="yes","Yes","No")) | AD14: =IF(A14="","",IF(LOWER(TRIM('01_Master_Data'!AK14&""))="yes","Yes","No")) | AE14: =IF(A14="","",IF(LOWER(TRIM('01_Master_Data'!AJ14&""))="yes","Yes","No")) | AF14: =IF(A14="","",TRIM('01_Master_Data'!AL14&"")) | AG14: =IF(A14="","",IF(AF14="","—",IF(ISNUMBER(SEARCH("DNP",AF14)),"Unreachable / DNP",IF(ISNUMBER(SEARCH("interest",LOWER(AF14))),"High Interest / Terms",IF(OR(ISNUMBER(SEARCH("eligib",LOWER(AF14))),ISNUMBER(SEARCH("income",LOWER(AF14)))),"Eligibility / Income",IF(OR(ISNUMBER(SEARCH("start",LOWER(AF14))),ISNUMBER(SEARCH("Newer",AF14)),ISNUMBER(SEARCH("Will start",AF14))),"Process Yet to Start",IF(ISNUMBER(SEARCH("sure",LOWER(AF14))),"Undecided",IF(OR(ISNUMBER(SEARCH("reject",LOWER(AF14))),ISNUMBER(SEARCH("SBI",AF14))),"Rejected Elsewhere",IF(ISNUMBER(SEARCH("call",LOWER(AF14))),"Bank Communication",IF(OR(ISNUMBER(SEARCH("father",LOWER(AF14))),ISNUMBER(SEARCH("sister",LOWER(AF14)))),"Family / Dependency","Other")))))))))) | AH14: =IF(A14="","",'01_Master_Data'!AC14) | AI14: =IF(A14="","",IF(OR(AH14="",NOT(ISNUMBER(AH14))),"",MAX(0,'02_Configuration'!$B$82-AH14))) | AJ14: =IF(A14="","",IF(AI14="","Unknown",IF(AI14<=3,"0–3 Days",IF(AI14<=7,"4–7 Days",IF(AI14<=15,"8–15 Days",IF(AI14<=30,"16–30 Days","30+ Days")))))) | AK14: =IF(A14="","",IF(LOWER(H14)="yes","Yes","No")) | AL14: =IF(A14="","",'01_Master_Data'!T14) | AM14: =IF(A14="","",'01_Master_Data'!S14) | AN14: =IF(A14="","",'01_Master_Data'!I14) | AO14: =IF(A14="","",'01_Master_Data'!M14) | AP14: =IF(A14="","",IF(ISNUMBER(SEARCH("Icici",W14&"")),1,0)) | AQ14: =IF(A14="","",IF(ISNUMBER(SEARCH("Propelld",W14&"")),1,0)) | AR14: =IF(A14="","",IF(ISNUMBER(SEARCH("GyanDhan",W14&"")),1,0)) | AS14: =IF(A14="","",IF(ISNUMBER(SEARCH("vidyalakshmi",LOWER(W14&""))),1,0)) | AT14: =IF(A14="","",IF(ISNUMBER(SEARCH("other bank",LOWER(W14&""))),1,0)) | AU14: =IF(A14="","",IF(ISNUMBER(SEARCH("sanctioned",LOWER(W14&""))),1,0)) | AV14: =IF(A14="","",IF(ISNUMBER(SEARCH("Docs Pending",W14&"")),1,0)) | AW14: =IF(A14="","",IF(OR(X14="Rejected",ISNUMBER(SEARCH("Not eligbile",W14&""))),1,0))
A15: =IF('01_Master_Data'!B15="","",14) | B15: =IF('01_Master_Data'!B15="","",IF('01_Master_Data'!C15<>"","MOB|"&TEXT('01_Master_Data'!C15,"0"),IF('01_Master_Data'!D15<>"","PID|"&TRIM('01_Master_Data'!D15&""),""))) | C15: =IF('01_Master_Data'!B15="","",'01_Master_Data'!B15) | D15: =IF('01_Master_Data'!B15="","",'01_Master_Data'!C15) | E15: =IF('01_Master_Data'!B15="","",'01_Master_Data'!D15) | F15: =IF('01_Master_Data'!B15="","",'01_Master_Data'!E15) | G15: =IF('01_Master_Data'!B15="","",IFERROR(VLOOKUP(TRIM('01_Master_Data'!E15&""),'02_Configuration'!$A$40:$B$44,2,FALSE),UPPER(TRIM('01_Master_Data'!E15&"")))) | H15: =IF('01_Master_Data'!B15="","",IF('01_Master_Data'!U15="","",TRIM('01_Master_Data'!U15&""))) | I15: =IF('01_Master_Data'!B15="","",TRIM('01_Master_Data'!F15&"")) | J15: =IF('01_Master_Data'!B15="","",TRIM('01_Master_Data'!G15&"")) | K15: =IF('01_Master_Data'!B15="","",'01_Master_Data'!H15) | L15: =IF('01_Master_Data'!B15="","",IF(LOWER(TRIM('01_Master_Data'!V15&""))="yes",1,0)) | M15: =IF('01_Master_Data'!B15="","",IF(LOWER(TRIM('01_Master_Data'!W15&""))="yes",1,0)) | N15: =IF('01_Master_Data'!B15="","",IF(LOWER(TRIM('01_Master_Data'!X15&""))="yes",1,0)) | O15: =IF('01_Master_Data'!B15="","",IF(LOWER(TRIM('01_Master_Data'!Y15&""))="yes",1,0)) | P15: =IF('01_Master_Data'!B15="","",IF(LOWER(TRIM('01_Master_Data'!Z15&""))="yes",1,0)) | Q15: =IF(A15="","",L15+M15+N15+O15+P15) | R15: =IF(A15="","",IF(Q15>1,"Yes","No")) | S15: =IF(A15="","",TEXTJOIN(", ",TRUE,IF(L15=1,"ICICI",""),IF(M15=1,"Propelld",""),IF(N15=1,"Study4Buddy",""),IF(O15=1,"Poonawala Fincorp",""),IF(P15=1,"GyanDhan",""))) | T15: =IF(A15="","",IF(L15=1,"ICICI",IF(M15=1,"Propelld",IF(P15=1,"GyanDhan",IF(N15=1,"Study4Buddy",IF(O15=1,"Poonawala Fincorp",IF(ISNUMBER(SEARCH("GyanDhan",W15&"")),"GyanDhan",IF(ISNUMBER(SEARCH("Icici",W15&"")),"ICICI",IF(ISNUMBER(SEARCH("Propelld",W15&"")),"Propelld",IF(ISNUMBER(SEARCH("vidyalakshmi",LOWER(W15&"")),"PM Vidyalakshmi","—")))))))))) | U15: =IF(A15="","",TRIM('01_Master_Data'!AA15&"")) | V15: =IF(A15="","",TRIM('01_Master_Data'!AG15&"")) | W15: =IF(A15="","",TRIM('01_Master_Data'!AH15&"")) | X15: =IF(A15="","",IF(OR(LOWER(H15)="refund",LOWER(U15)="refund case"),"Refund",IF(OR(LOWER(H15)="dnp",LOWER(U15)="dnp"),"DNP",IF(OR(LOWER(V15)="disbursed",ISNUMBER(SEARCH("Disbursed",W15&""))),"Disbursed",IF(OR(LOWER(V15)="loan proccessed/accepted",ISNUMBER(SEARCH("sanctioned",LOWER(W15&"")))),"Sanctioned",IF(OR(LOWER(V15)="rejected",ISNUMBER(SEARCH("Not eligbile",W15&"")),ISNUMBER(SEARCH("Not eligible",W15&""))),"Rejected",IF(ISNUMBER(SEARCH("Docs Pending",W15&"")),"Documents Pending",IF(AND(LOWER(H15)="yes",LOWER(V15)="ongoing"),"Processing",IF(AND(LOWER(H15)="yes",Q15>0,OR(V15="",LOWER(V15)="not even started")),"Vendor Assigned",IF(AND(LOWER(H15)="yes",LOWER(V15)="not even started"),"Need Loan",IF(LOWER(H15)="yes","Loan Started",IF(LOWER(H15)="not sure","Interested",IF(OR(LOWER(H15)="no",LOWER(V15)="not required"),"Not Required","Unclassified"))))))))))))) | Y15: =IF(A15="","",IF(OR(X15="Sanctioned",X15="Disbursed",X15="Approved"),"Approved",IF(X15="Rejected","Rejected",IF(OR(X15="Processing",X15="Documents Pending",X15="Vendor Assigned"),"In Progress",IF(X15="Need Loan","Pending Start","—")))) | Z15: =IF(A15="","",IF(X15="Disbursed","Disbursed",IF(X15="Sanctioned","Sanctioned - Awaiting Disbursement","Not Disbursed"))) | AA15: =IF(A15="","",IF(LOWER(TRIM('01_Master_Data'!AI15&""))="yes","Need FLDG",IF(LOWER(TRIM('01_Master_Data'!AK15&""))="yes","Need Vidyalakshmi",IF(LOWER(TRIM('01_Master_Data'!AJ15&""))="yes","Need Review",IF(LOWER(J15)="critical","Critical",IF(LOWER(U15)="risk","Risk Case",IF(X15="Refund","Refund","Normal"))))))) | AB15: =IF(A15="","",IF(OR(LOWER(J15)="critical",LOWER(TRIM('01_Master_Data'!AI15&""))="yes",LOWER(TRIM('01_Master_Data'!AK15&""))="yes",LOWER(U15)="risk"),"Yes","No")) | AC15: =IF(A15="","",IF(LOWER(TRIM('01_Master_Data'!AI15&""))="yes","Yes","No")) | AD15: =IF(A15="","",IF(LOWER(TRIM('01_Master_Data'!AK15&""))="yes","Yes","No")) | AE15: =IF(A15="","",IF(LOWER(TRIM('01_Master_Data'!AJ15&""))="yes","Yes","No")) | AF15: =IF(A15="","",TRIM('01_Master_Data'!AL15&"")) | AG15: =IF(A15="","",IF(AF15="","—",IF(ISNUMBER(SEARCH("DNP",AF15)),"Unreachable / DNP",IF(ISNUMBER(SEARCH("interest",LOWER(AF15))),"High Interest / Terms",IF(OR(ISNUMBER(SEARCH("eligib",LOWER(AF15))),ISNUMBER(SEARCH("income",LOWER(AF15)))),"Eligibility / Income",IF(OR(ISNUMBER(SEARCH("start",LOWER(AF15))),ISNUMBER(SEARCH("Newer",AF15)),ISNUMBER(SEARCH("Will start",AF15))),"Process Yet to Start",IF(ISNUMBER(SEARCH("sure",LOWER(AF15))),"Undecided",IF(OR(ISNUMBER(SEARCH("reject",LOWER(AF15))),ISNUMBER(SEARCH("SBI",AF15))),"Rejected Elsewhere",IF(ISNUMBER(SEARCH("call",LOWER(AF15))),"Bank Communication",IF(OR(ISNUMBER(SEARCH("father",LOWER(AF15))),ISNUMBER(SEARCH("sister",LOWER(AF15)))),"Family / Dependency","Other")))))))))) | AH15: =IF(A15="","",'01_Master_Data'!AC15) | AI15: =IF(A15="","",IF(OR(AH15="",NOT(ISNUMBER(AH15))),"",MAX(0,'02_Configuration'!$B$82-AH15))) | AJ15: =IF(A15="","",IF(AI15="","Unknown",IF(AI15<=3,"0–3 Days",IF(AI15<=7,"4–7 Days",IF(AI15<=15,"8–15 Days",IF(AI15<=30,"16–30 Days","30+ Days")))))) | AK15: =IF(A15="","",IF(LOWER(H15)="yes","Yes","No")) | AL15: =IF(A15="","",'01_Master_Data'!T15) | AM15: =IF(A15="","",'01_Master_Data'!S15) | AN15: =IF(A15="","",'01_Master_Data'!I15) | AO15: =IF(A15="","",'01_Master_Data'!M15) | AP15: =IF(A15="","",IF(ISNUMBER(SEARCH("Icici",W15&"")),1,0)) | AQ15: =IF(A15="","",IF(ISNUMBER(SEARCH("Propelld",W15&"")),1,0)) | AR15: =IF(A15="","",IF(ISNUMBER(SEARCH("GyanDhan",W15&"")),1,0)) | AS15: =IF(A15="","",IF(ISNUMBER(SEARCH("vidyalakshmi",LOWER(W15&""))),1,0)) | AT15: =IF(A15="","",IF(ISNUMBER(SEARCH("other bank",LOWER(W15&""))),1,0)) | AU15: =IF(A15="","",IF(ISNUMBER(SEARCH("sanctioned",LOWER(W15&""))),1,0)) | AV15: =IF(A15="","",IF(ISNUMBER(SEARCH("Docs Pending",W15&"")),1,0)) | AW15: =IF(A15="","",IF(OR(X15="Rejected",ISNUMBER(SEARCH("Not eligbile",W15&""))),1,0))
A16: =IF('01_Master_Data'!B16="","",15) | B16: =IF('01_Master_Data'!B16="","",IF('01_Master_Data'!C16<>"","MOB|"&TEXT('01_Master_Data'!C16,"0"),IF('01_Master_Data'!D16<>"","PID|"&TRIM('01_Master_Data'!D16&""),""))) | C16: =IF('01_Master_Data'!B16="","",'01_Master_Data'!B16) | D16: =IF('01_Master_Data'!B16="","",'01_Master_Data'!C16) | E16: =IF('01_Master_Data'!B16="","",'01_Master_Data'!D16) | F16: =IF('01_Master_Data'!B16="","",'01_Master_Data'!E16) | G16: =IF('01_Master_Data'!B16="","",IFERROR(VLOOKUP(TRIM('01_Master_Data'!E16&""),'02_Configuration'!$A$40:$B$44,2,FALSE),UPPER(TRIM('01_Master_Data'!E16&"")))) | H16: =IF('01_Master_Data'!B16="","",IF('01_Master_Data'!U16="","",TRIM('01_Master_Data'!U16&""))) | I16: =IF('01_Master_Data'!B16="","",TRIM('01_Master_Data'!F16&"")) | J16: =IF('01_Master_Data'!B16="","",TRIM('01_Master_Data'!G16&"")) | K16: =IF('01_Master_Data'!B16="","",'01_Master_Data'!H16) | L16: =IF('01_Master_Data'!B16="","",IF(LOWER(TRIM('01_Master_Data'!V16&""))="yes",1,0)) | M16: =IF('01_Master_Data'!B16="","",IF(LOWER(TRIM('01_Master_Data'!W16&""))="yes",1,0)) | N16: =IF('01_Master_Data'!B16="","",IF(LOWER(TRIM('01_Master_Data'!X16&""))="yes",1,0)) | O16: =IF('01_Master_Data'!B16="","",IF(LOWER(TRIM('01_Master_Data'!Y16&""))="yes",1,0)) | P16: =IF('01_Master_Data'!B16="","",IF(LOWER(TRIM('01_Master_Data'!Z16&""))="yes",1,0)) | Q16: =IF(A16="","",L16+M16+N16+O16+P16) | R16: =IF(A16="","",IF(Q16>1,"Yes","No")) | S16: =IF(A16="","",TEXTJOIN(", ",TRUE,IF(L16=1,"ICICI",""),IF(M16=1,"Propelld",""),IF(N16=1,"Study4Buddy",""),IF(O16=1,"Poonawala Fincorp",""),IF(P16=1,"GyanDhan",""))) | T16: =IF(A16="","",IF(L16=1,"ICICI",IF(M16=1,"Propelld",IF(P16=1,"GyanDhan",IF(N16=1,"Study4Buddy",IF(O16=1,"Poonawala Fincorp",IF(ISNUMBER(SEARCH("GyanDhan",W16&"")),"GyanDhan",IF(ISNUMBER(SEARCH("Icici",W16&"")),"ICICI",IF(ISNUMBER(SEARCH("Propelld",W16&"")),"Propelld",IF(ISNUMBER(SEARCH("vidyalakshmi",LOWER(W16&"")),"PM Vidyalakshmi","—")))))))))) | U16: =IF(A16="","",TRIM('01_Master_Data'!AA16&"")) | V16: =IF(A16="","",TRIM('01_Master_Data'!AG16&"")) | W16: =IF(A16="","",TRIM('01_Master_Data'!AH16&"")) | X16: =IF(A16="","",IF(OR(LOWER(H16)="refund",LOWER(U16)="refund case"),"Refund",IF(OR(LOWER(H16)="dnp",LOWER(U16)="dnp"),"DNP",IF(OR(LOWER(V16)="disbursed",ISNUMBER(SEARCH("Disbursed",W16&""))),"Disbursed",IF(OR(LOWER(V16)="loan proccessed/accepted",ISNUMBER(SEARCH("sanctioned",LOWER(W16&"")))),"Sanctioned",IF(OR(LOWER(V16)="rejected",ISNUMBER(SEARCH("Not eligbile",W16&"")),ISNUMBER(SEARCH("Not eligible",W16&""))),"Rejected",IF(ISNUMBER(SEARCH("Docs Pending",W16&"")),"Documents Pending",IF(AND(LOWER(H16)="yes",LOWER(V16)="ongoing"),"Processing",IF(AND(LOWER(H16)="yes",Q16>0,OR(V16="",LOWER(V16)="not even started")),"Vendor Assigned",IF(AND(LOWER(H16)="yes",LOWER(V16)="not even started"),"Need Loan",IF(LOWER(H16)="yes","Loan Started",IF(LOWER(H16)="not sure","Interested",IF(OR(LOWER(H16)="no",LOWER(V16)="not required"),"Not Required","Unclassified"))))))))))))) | Y16: =IF(A16="","",IF(OR(X16="Sanctioned",X16="Disbursed",X16="Approved"),"Approved",IF(X16="Rejected","Rejected",IF(OR(X16="Processing",X16="Documents Pending",X16="Vendor Assigned"),"In Progress",IF(X16="Need Loan","Pending Start","—")))) | Z16: =IF(A16="","",IF(X16="Disbursed","Disbursed",IF(X16="Sanctioned","Sanctioned - Awaiting Disbursement","Not Disbursed"))) | AA16: =IF(A16="","",IF(LOWER(TRIM('01_Master_Data'!AI16&""))="yes","Need FLDG",IF(LOWER(TRIM('01_Master_Data'!AK16&""))="yes","Need Vidyalakshmi",IF(LOWER(TRIM('01_Master_Data'!AJ16&""))="yes","Need Review",IF(LOWER(J16)="critical","Critical",IF(LOWER(U16)="risk","Risk Case",IF(X16="Refund","Refund","Normal"))))))) | AB16: =IF(A16="","",IF(OR(LOWER(J16)="critical",LOWER(TRIM('01_Master_Data'!AI16&""))="yes",LOWER(TRIM('01_Master_Data'!AK16&""))="yes",LOWER(U16)="risk"),"Yes","No")) | AC16: =IF(A16="","",IF(LOWER(TRIM('01_Master_Data'!AI16&""))="yes","Yes","No")) | AD16: =IF(A16="","",IF(LOWER(TRIM('01_Master_Data'!AK16&""))="yes","Yes","No")) | AE16: =IF(A16="","",IF(LOWER(TRIM('01_Master_Data'!AJ16&""))="yes","Yes","No")) | AF16: =IF(A16="","",TRIM('01_Master_Data'!AL16&"")) | AG16: =IF(A16="","",IF(AF16="","—",IF(ISNUMBER(SEARCH("DNP",AF16)),"Unreachable / DNP",IF(ISNUMBER(SEARCH("interest",LOWER(AF16))),"High Interest / Terms",IF(OR(ISNUMBER(SEARCH("eligib",LOWER(AF16))),ISNUMBER(SEARCH("income",LOWER(AF16)))),"Eligibility / Income",IF(OR(ISNUMBER(SEARCH("start",LOWER(AF16))),ISNUMBER(SEARCH("Newer",AF16)),ISNUMBER(SEARCH("Will start",AF16))),"Process Yet to Start",IF(ISNUMBER(SEARCH("sure",LOWER(AF16))),"Undecided",IF(OR(ISNUMBER(SEARCH("reject",LOWER(AF16))),ISNUMBER(SEARCH("SBI",AF16))),"Rejected Elsewhere",IF(ISNUMBER(SEARCH("call",LOWER(AF16))),"Bank Communication",IF(OR(ISNUMBER(SEARCH("father",LOWER(AF16))),ISNUMBER(SEARCH("sister",LOWER(AF16)))),"Family / Dependency","Other")))))))))) | AH16: =IF(A16="","",'01_Master_Data'!AC16) | AI16: =IF(A16="","",IF(OR(AH16="",NOT(ISNUMBER(AH16))),"",MAX(0,'02_Configuration'!$B$82-AH16))) | AJ16: =IF(A16="","",IF(AI16="","Unknown",IF(AI16<=3,"0–3 Days",IF(AI16<=7,"4–7 Days",IF(AI16<=15,"8–15 Days",IF(AI16<=30,"16–30 Days","30+ Days")))))) | AK16: =IF(A16="","",IF(LOWER(H16)="yes","Yes","No")) | AL16: =IF(A16="","",'01_Master_Data'!T16) | AM16: =IF(A16="","",'01_Master_Data'!S16) | AN16: =IF(A16="","",'01_Master_Data'!I16) | AO16: =IF(A16="","",'01_Master_Data'!M16) | AP16: =IF(A16="","",IF(ISNUMBER(SEARCH("Icici",W16&"")),1,0)) | AQ16: =IF(A16="","",IF(ISNUMBER(SEARCH("Propelld",W16&"")),1,0)) | AR16: =IF(A16="","",IF(ISNUMBER(SEARCH("GyanDhan",W16&"")),1,0)) | AS16: =IF(A16="","",IF(ISNUMBER(SEARCH("vidyalakshmi",LOWER(W16&""))),1,0)) | AT16: =IF(A16="","",IF(ISNUMBER(SEARCH("other bank",LOWER(W16&""))),1,0)) | AU16: =IF(A16="","",IF(ISNUMBER(SEARCH("sanctioned",LOWER(W16&""))),1,0)) | AV16: =IF(A16="","",IF(ISNUMBER(SEARCH("Docs Pending",W16&"")),1,0)) | AW16: =IF(A16="","",IF(OR(X16="Rejected",ISNUMBER(SEARCH("Not eligbile",W16&""))),1,0))
A17: =IF('01_Master_Data'!B17="","",16) | B17: =IF('01_Master_Data'!B17="","",IF('01_Master_Data'!C17<>"","MOB|"&TEXT('01_Master_Data'!C17,"0"),IF('01_Master_Data'!D17<>"","PID|"&TRIM('01_Master_Data'!D17&""),""))) | C17: =IF('01_Master_Data'!B17="","",'01_Master_Data'!B17) | D17: =IF('01_Master_Data'!B17="","",'01_Master_Data'!C17) | E17: =IF('01_Master_Data'!B17="","",'01_Master_Data'!D17) | F17: =IF('01_Master_Data'!B17="","",'01_Master_Data'!E17) | G17: =IF('01_Master_Data'!B17="","",IFERROR(VLOOKUP(TRIM('01_Master_Data'!E17&""),'02_Configuration'!$A$40:$B$44,2,FALSE),UPPER(TRIM('01_Master_Data'!E17&"")))) | H17: =IF('01_Master_Data'!B17="","",IF('01_Master_Data'!U17="","",TRIM('01_Master_Data'!U17&""))) | I17: =IF('01_Master_Data'!B17="","",TRIM('01_Master_Data'!F17&"")) | J17: =IF('01_Master_Data'!B17="","",TRIM('01_Master_Data'!G17&"")) | K17: =IF('01_Master_Data'!B17="","",'01_Master_Data'!H17) | L17: =IF('01_Master_Data'!B17="","",IF(LOWER(TRIM('01_Master_Data'!V17&""))="yes",1,0)) | M17: =IF('01_Master_Data'!B17="","",IF(LOWER(TRIM('01_Master_Data'!W17&""))="yes",1,0)) | N17: =IF('01_Master_Data'!B17="","",IF(LOWER(TRIM('01_Master_Data'!X17&""))="yes",1,0)) | O17: =IF('01_Master_Data'!B17="","",IF(LOWER(TRIM('01_Master_Data'!Y17&""))="yes",1,0)) | P17: =IF('01_Master_Data'!B17="","",IF(LOWER(TRIM('01_Master_Data'!Z17&""))="yes",1,0)) | Q17: =IF(A17="","",L17+M17+N17+O17+P17) | R17: =IF(A17="","",IF(Q17>1,"Yes","No")) | S17: =IF(A17="","",TEXTJOIN(", ",TRUE,IF(L17=1,"ICICI",""),IF(M17=1,"Propelld",""),IF(N17=1,"Study4Buddy",""),IF(O17=1,"Poonawala Fincorp",""),IF(P17=1,"GyanDhan",""))) | T17: =IF(A17="","",IF(L17=1,"ICICI",IF(M17=1,"Propelld",IF(P17=1,"GyanDhan",IF(N17=1,"Study4Buddy",IF(O17=1,"Poonawala Fincorp",IF(ISNUMBER(SEARCH("GyanDhan",W17&"")),"GyanDhan",IF(ISNUMBER(SEARCH("Icici",W17&"")),"ICICI",IF(ISNUMBER(SEARCH("Propelld",W17&"")),"Propelld",IF(ISNUMBER(SEARCH("vidyalakshmi",LOWER(W17&"")),"PM Vidyalakshmi","—")))))))))) | U17: =IF(A17="","",TRIM('01_Master_Data'!AA17&"")) | V17: =IF(A17="","",TRIM('01_Master_Data'!AG17&"")) | W17: =IF(A17="","",TRIM('01_Master_Data'!AH17&"")) | X17: =IF(A17="","",IF(OR(LOWER(H17)="refund",LOWER(U17)="refund case"),"Refund",IF(OR(LOWER(H17)="dnp",LOWER(U17)="dnp"),"DNP",IF(OR(LOWER(V17)="disbursed",ISNUMBER(SEARCH("Disbursed",W17&""))),"Disbursed",IF(OR(LOWER(V17)="loan proccessed/accepted",ISNUMBER(SEARCH("sanctioned",LOWER(W17&"")))),"Sanctioned",IF(OR(LOWER(V17)="rejected",ISNUMBER(SEARCH("Not eligbile",W17&"")),ISNUMBER(SEARCH("Not eligible",W17&""))),"Rejected",IF(ISNUMBER(SEARCH("Docs Pending",W17&"")),"Documents Pending",IF(AND(LOWER(H17)="yes",LOWER(V17)="ongoing"),"Processing",IF(AND(LOWER(H17)="yes",Q17>0,OR(V17="",LOWER(V17)="not even started")),"Vendor Assigned",IF(AND(LOWER(H17)="yes",LOWER(V17)="not even started"),"Need Loan",IF(LOWER(H17)="yes","Loan Started",IF(LOWER(H17)="not sure","Interested",IF(OR(LOWER(H17)="no",LOWER(V17)="not required"),"Not Required","Unclassified"))))))))))))) | Y17: =IF(A17="","",IF(OR(X17="Sanctioned",X17="Disbursed",X17="Approved"),"Approved",IF(X17="Rejected","Rejected",IF(OR(X17="Processing",X17="Documents Pending",X17="Vendor Assigned"),"In Progress",IF(X17="Need Loan","Pending Start","—")))) | Z17: =IF(A17="","",IF(X17="Disbursed","Disbursed",IF(X17="Sanctioned","Sanctioned - Awaiting Disbursement","Not Disbursed"))) | AA17: =IF(A17="","",IF(LOWER(TRIM('01_Master_Data'!AI17&""))="yes","Need FLDG",IF(LOWER(TRIM('01_Master_Data'!AK17&""))="yes","Need Vidyalakshmi",IF(LOWER(TRIM('01_Master_Data'!AJ17&""))="yes","Need Review",IF(LOWER(J17)="critical","Critical",IF(LOWER(U17)="risk","Risk Case",IF(X17="Refund","Refund","Normal"))))))) | AB17: =IF(A17="","",IF(OR(LOWER(J17)="critical",LOWER(TRIM('01_Master_Data'!AI17&""))="yes",LOWER(TRIM('01_Master_Data'!AK17&""))="yes",LOWER(U17)="risk"),"Yes","No")) | AC17: =IF(A17="","",IF(LOWER(TRIM('01_Master_Data'!AI17&""))="yes","Yes","No")) | AD17: =IF(A17="","",IF(LOWER(TRIM('01_Master_Data'!AK17&""))="yes","Yes","No")) | AE17: =IF(A17="","",IF(LOWER(TRIM('01_Master_Data'!AJ17&""))="yes","Yes","No")) | AF17: =IF(A17="","",TRIM('01_Master_Data'!AL17&"")) | AG17: =IF(A17="","",IF(AF17="","—",IF(ISNUMBER(SEARCH("DNP",AF17)),"Unreachable / DNP",IF(ISNUMBER(SEARCH("interest",LOWER(AF17))),"High Interest / Terms",IF(OR(ISNUMBER(SEARCH("eligib",LOWER(AF17))),ISNUMBER(SEARCH("income",LOWER(AF17)))),"Eligibility / Income",IF(OR(ISNUMBER(SEARCH("start",LOWER(AF17))),ISNUMBER(SEARCH("Newer",AF17)),ISNUMBER(SEARCH("Will start",AF17))),"Process Yet to Start",IF(ISNUMBER(SEARCH("sure",LOWER(AF17))),"Undecided",IF(OR(ISNUMBER(SEARCH("reject",LOWER(AF17))),ISNUMBER(SEARCH("SBI",AF17))),"Rejected Elsewhere",IF(ISNUMBER(SEARCH("call",LOWER(AF17))),"Bank Communication",IF(OR(ISNUMBER(SEARCH("father",LOWER(AF17))),ISNUMBER(SEARCH("sister",LOWER(AF17)))),"Family / Dependency","Other")))))))))) | AH17: =IF(A17="","",'01_Master_Data'!AC17) | AI17: =IF(A17="","",IF(OR(AH17="",NOT(ISNUMBER(AH17))),"",MAX(0,'02_Configuration'!$B$82-AH17))) | AJ17: =IF(A17="","",IF(AI17="","Unknown",IF(AI17<=3,"0–3 Days",IF(AI17<=7,"4–7 Days",IF(AI17<=15,"8–15 Days",IF(AI17<=30,"16–30 Days","30+ Days")))))) | AK17: =IF(A17="","",IF(LOWER(H17)="yes","Yes","No")) | AL17: =IF(A17="","",'01_Master_Data'!T17) | AM17: =IF(A17="","",'01_Master_Data'!S17) | AN17: =IF(A17="","",'01_Master_Data'!I17) | AO17: =IF(A17="","",'01_Master_Data'!M17) | AP17: =IF(A17="","",IF(ISNUMBER(SEARCH("Icici",W17&"")),1,0)) | AQ17: =IF(A17="","",IF(ISNUMBER(SEARCH("Propelld",W17&"")),1,0)) | AR17: =IF(A17="","",IF(ISNUMBER(SEARCH("GyanDhan",W17&"")),1,0)) | AS17: =IF(A17="","",IF(ISNUMBER(SEARCH("vidyalakshmi",LOWER(W17&""))),1,0)) | AT17: =IF(A17="","",IF(ISNUMBER(SEARCH("other bank",LOWER(W17&""))),1,0)) | AU17: =IF(A17="","",IF(ISNUMBER(SEARCH("sanctioned",LOWER(W17&""))),1,0)) | AV17: =IF(A17="","",IF(ISNUMBER(SEARCH("Docs Pending",W17&"")),1,0)) | AW17: =IF(A17="","",IF(OR(X17="Rejected",ISNUMBER(SEARCH("Not eligbile",W17&""))),1,0))
A18: =IF('01_Master_Data'!B18="","",17) | B18: =IF('01_Master_Data'!B18="","",IF('01_Master_Data'!C18<>"","MOB|"&TEXT('01_Master_Data'!C18,"0"),IF('01_Master_Data'!D18<>"","PID|"&TRIM('01_Master_Data'!D18&""),""))) | C18: =IF('01_Master_Data'!B18="","",'01_Master_Data'!B18) | D18: =IF('01_Master_Data'!B18="","",'01_Master_Data'!C18) | E18: =IF('01_Master_Data'!B18="","",'01_Master_Data'!D18) | F18: =IF('01_Master_Data'!B18="","",'01_Master_Data'!E18) | G18: =IF('01_Master_Data'!B18="","",IFERROR(VLOOKUP(TRIM('01_Master_Data'!E18&""),'02_Configuration'!$A$40:$B$44,2,FALSE),UPPER(TRIM('01_Master_Data'!E18&"")))) | H18: =IF('01_Master_Data'!B18="","",IF('01_Master_Data'!U18="","",TRIM('01_Master_Data'!U18&""))) | I18: =IF('01_Master_Data'!B18="","",TRIM('01_Master_Data'!F18&"")) | J18: =IF('01_Master_Data'!B18="","",TRIM('01_Master_Data'!G18&"")) | K18: =IF('01_Master_Data'!B18="","",'01_Master_Data'!H18) | L18: =IF('01_Master_Data'!B18="","",IF(LOWER(TRIM('01_Master_Data'!V18&""))="yes",1,0)) | M18: =IF('01_Master_Data'!B18="","",IF(LOWER(TRIM('01_Master_Data'!W18&""))="yes",1,0)) | N18: =IF('01_Master_Data'!B18="","",IF(LOWER(TRIM('01_Master_Data'!X18&""))="yes",1,0)) | O18: =IF('01_Master_Data'!B18="","",IF(LOWER(TRIM('01_Master_Data'!Y18&""))="yes",1,0)) | P18: =IF('01_Master_Data'!B18="","",IF(LOWER(TRIM('01_Master_Data'!Z18&""))="yes",1,0)) | Q18: =IF(A18="","",L18+M18+N18+O18+P18) | R18: =IF(A18="","",IF(Q18>1,"Yes","No")) | S18: =IF(A18="","",TEXTJOIN(", ",TRUE,IF(L18=1,"ICICI",""),IF(M18=1,"Propelld",""),IF(N18=1,"Study4Buddy",""),IF(O18=1,"Poonawala Fincorp",""),IF(P18=1,"GyanDhan",""))) | T18: =IF(A18="","",IF(L18=1,"ICICI",IF(M18=1,"Propelld",IF(P18=1,"GyanDhan",IF(N18=1,"Study4Buddy",IF(O18=1,"Poonawala Fincorp",IF(ISNUMBER(SEARCH("GyanDhan",W18&"")),"GyanDhan",IF(ISNUMBER(SEARCH("Icici",W18&"")),"ICICI",IF(ISNUMBER(SEARCH("Propelld",W18&"")),"Propelld",IF(ISNUMBER(SEARCH("vidyalakshmi",LOWER(W18&"")),"PM Vidyalakshmi","—")))))))))) | U18: =IF(A18="","",TRIM('01_Master_Data'!AA18&"")) | V18: =IF(A18="","",TRIM('01_Master_Data'!AG18&"")) | W18: =IF(A18="","",TRIM('01_Master_Data'!AH18&"")) | X18: =IF(A18="","",IF(OR(LOWER(H18)="refund",LOWER(U18)="refund case"),"Refund",IF(OR(LOWER(H18)="dnp",LOWER(U18)="dnp"),"DNP",IF(OR(LOWER(V18)="disbursed",ISNUMBER(SEARCH("Disbursed",W18&""))),"Disbursed",IF(OR(LOWER(V18)="loan proccessed/accepted",ISNUMBER(SEARCH("sanctioned",LOWER(W18&"")))),"Sanctioned",IF(OR(LOWER(V18)="rejected",ISNUMBER(SEARCH("Not eligbile",W18&"")),ISNUMBER(SEARCH("Not eligible",W18&""))),"Rejected",IF(ISNUMBER(SEARCH("Docs Pending",W18&"")),"Documents Pending",IF(AND(LOWER(H18)="yes",LOWER(V18)="ongoing"),"Processing",IF(AND(LOWER(H18)="yes",Q18>0,OR(V18="",LOWER(V18)="not even started")),"Vendor Assigned",IF(AND(LOWER(H18)="yes",LOWER(V18)="not even started"),"Need Loan",IF(LOWER(H18)="yes","Loan Started",IF(LOWER(H18)="not sure","Interested",IF(OR(LOWER(H18)="no",LOWER(V18)="not required"),"Not Required","Unclassified"))))))))))))) | Y18: =IF(A18="","",IF(OR(X18="Sanctioned",X18="Disbursed",X18="Approved"),"Approved",IF(X18="Rejected","Rejected",IF(OR(X18="Processing",X18="Documents Pending",X18="Vendor Assigned"),"In Progress",IF(X18="Need Loan","Pending Start","—")))) | Z18: =IF(A18="","",IF(X18="Disbursed","Disbursed",IF(X18="Sanctioned","Sanctioned - Awaiting Disbursement","Not Disbursed"))) | AA18: =IF(A18="","",IF(LOWER(TRIM('01_Master_Data'!AI18&""))="yes","Need FLDG",IF(LOWER(TRIM('01_Master_Data'!AK18&""))="yes","Need Vidyalakshmi",IF(LOWER(TRIM('01_Master_Data'!AJ18&""))="yes","Need Review",IF(LOWER(J18)="critical","Critical",IF(LOWER(U18)="risk","Risk Case",IF(X18="Refund","Refund","Normal"))))))) | AB18: =IF(A18="","",IF(OR(LOWER(J18)="critical",LOWER(TRIM('01_Master_Data'!AI18&""))="yes",LOWER(TRIM('01_Master_Data'!AK18&""))="yes",LOWER(U18)="risk"),"Yes","No")) | AC18: =IF(A18="","",IF(LOWER(TRIM('01_Master_Data'!AI18&""))="yes","Yes","No")) | AD18: =IF(A18="","",IF(LOWER(TRIM('01_Master_Data'!AK18&""))="yes","Yes","No")) | AE18: =IF(A18="","",IF(LOWER(TRIM('01_Master_Data'!AJ18&""))="yes","Yes","No")) | AF18: =IF(A18="","",TRIM('01_Master_Data'!AL18&"")) | AG18: =IF(A18="","",IF(AF18="","—",IF(ISNUMBER(SEARCH("DNP",AF18)),"Unreachable / DNP",IF(ISNUMBER(SEARCH("interest",LOWER(AF18))),"High Interest / Terms",IF(OR(ISNUMBER(SEARCH("eligib",LOWER(AF18))),ISNUMBER(SEARCH("income",LOWER(AF18)))),"Eligibility / Income",IF(OR(ISNUMBER(SEARCH("start",LOWER(AF18))),ISNUMBER(SEARCH("Newer",AF18)),ISNUMBER(SEARCH("Will start",AF18))),"Process Yet to Start",IF(ISNUMBER(SEARCH("sure",LOWER(AF18))),"Undecided",IF(OR(ISNUMBER(SEARCH("reject",LOWER(AF18))),ISNUMBER(SEARCH("SBI",AF18))),"Rejected Elsewhere",IF(ISNUMBER(SEARCH("call",LOWER(AF18))),"Bank Communication",IF(OR(ISNUMBER(SEARCH("father",LOWER(AF18))),ISNUMBER(SEARCH("sister",LOWER(AF18)))),"Family / Dependency","Other")))))))))) | AH18: =IF(A18="","",'01_Master_Data'!AC18) | AI18: =IF(A18="","",IF(OR(AH18="",NOT(ISNUMBER(AH18))),"",MAX(0,'02_Configuration'!$B$82-AH18))) | AJ18: =IF(A18="","",IF(AI18="","Unknown",IF(AI18<=3,"0–3 Days",IF(AI18<=7,"4–7 Days",IF(AI18<=15,"8–15 Days",IF(AI18<=30,"16–30 Days","30+ Days")))))) | AK18: =IF(A18="","",IF(LOWER(H18)="yes","Yes","No")) | AL18: =IF(A18="","",'01_Master_Data'!T18) | AM18: =IF(A18="","",'01_Master_Data'!S18) | AN18: =IF(A18="","",'01_Master_Data'!I18) | AO18: =IF(A18="","",'01_Master_Data'!M18) | AP18: =IF(A18="","",IF(ISNUMBER(SEARCH("Icici",W18&"")),1,0)) | AQ18: =IF(A18="","",IF(ISNUMBER(SEARCH("Propelld",W18&"")),1,0)) | AR18: =IF(A18="","",IF(ISNUMBER(SEARCH("GyanDhan",W18&"")),1,0)) | AS18: =IF(A18="","",IF(ISNUMBER(SEARCH("vidyalakshmi",LOWER(W18&""))),1,0)) | AT18: =IF(A18="","",IF(ISNUMBER(SEARCH("other bank",LOWER(W18&""))),1,0)) | AU18: =IF(A18="","",IF(ISNUMBER(SEARCH("sanctioned",LOWER(W18&""))),1,0)) | AV18: =IF(A18="","",IF(ISNUMBER(SEARCH("Docs Pending",W18&"")),1,0)) | AW18: =IF(A18="","",IF(OR(X18="Rejected",ISNUMBER(SEARCH("Not eligbile",W18&""))),1,0))
